Workbook

Sheet Guia
A1: Modelo de evaluación de madurez de la información para estimación de proyectos
A3: Propósito | B3: Evaluar, antes de estimar, qué tanto se conoce el alcance del proyecto en cada dimensión de estimación y qué tan madura es esa información. El resultado indica la confianza con la que se puede estimar, la técnica recomendada y las brechas a cerrar.
A4: Qué NO mide | B4: No estima esfuerzo ni costo. No evalúa riesgo e incertidumbre (dimensión 12 del catálogo, fuera de alcance).
A5: Hojas del libro | B5: Guia · Dimensiones (11 dimensiones y escalas) · Rubricas (109 criterios con descriptores 0–3) · Parametros (pesos, niveles, umbrales) · Ficha (plantilla en blanco) · Ejemplo (ficha diligenciada) · Resultados (tablero de la ficha seleccionada) · Glosario.
A6: Paso 1 · Datos generales | B6: En la hoja Ficha, completar proyecto, cliente, evaluadores, fecha, momento de estimación y fuentes revisadas.
A7: Paso 2 · Caracterización (Parte A) | B7: Registrar los valores de clasificación del catálogo: composición del tipo de desarrollo, arquetipo, N° de procesos funcionales, factores de complejidad, interfaces, % de reuso, entorno, contexto, sector y comparables. La hoja calcula la clase de tamaño, el nivel de complejidad, I0–I3, R1–R4, M1–M4 y E1–E4.
A8: Paso 3 · Evaluación (Parte B) | B8: Calificar cada criterio de 0 a 3 con la rúbrica de la hoja Rubricas, y registrar la evidencia. Usar N/A solo cuando el criterio lo admite.
A9: Paso 4 · Revisar hallazgos | B9: La columna «Hallazgo o comentario sugerido» explica la brecha cuando el puntaje es 0–1 y pide validar cuando es 2.
A10: Paso 5 · Revisar validaciones | B10: El bloque de validaciones cruza la caracterización con los criterios y marca inconsistencias (⚠ Revisar).
A11: Paso 6 · Resultados | B11: En la hoja Resultados seleccionar la ficha (Ejemplo o Ficha) para ver madurez por dimensión, nivel general, top 10 brechas y validaciones.
A12: Cálculo · criterio | B12: Obtenido = puntaje × peso interno (1–3). Máximo = 3 × peso interno (0 si es N/A).
A13: Cálculo · dimensión | B13: Madurez de la dimensión = Σ obtenido / Σ máximo (0–100%). Criterio núcleo en blanco cuenta como 0. Dimensión complementaria sin ningún puntaje se excluye.
A14: Cálculo · general | B14: Madurez general = Σ (peso dimensión × madurez) / Σ peso de dimensiones incluidas. Núcleo = 70% del peso; cada núcleo pesa más que cualquier complementaria.
... A19: Reutilizar la ficha | B19: Para un nuevo proyecto, copiar la hoja Ficha (clic derecho › Mover o copiar) o limpiar las celdas amarillas. Para ver sus resultados en la hoja Resultados, el nombre debe ser «Ficha» o «Ejemplo» (o agregarlo a la lista de C3).

Sheet Dimensiones
A1: Dimensiones de estimación, subdimensiones y escalas de caracterización
A2: Se evalúan 11 dimensiones. La dimensión 12 (Riesgo e incertidumbre) queda fuera de este modelo. Las 5 dimensiones núcleo son obligatorias y concentran el mayor peso.
A3: Código | B3: Dimensión | C3: Tipo | D3: Peso | E3: Qué busca caracterizar | F3: Cómo determinarla | G3: Escala de caracterización (catálogo) | H3: Subdimensiones | I3: N° criterios | J3: Suma pesos internos | K3: Referencia
A4: D1 | B4: Tipo de desarrollo | C4: Núcleo | D4: =Parametros!D5 -> 0.12 | E4: Qué se está haciendo sobre el activo de software. | F4: Identificar qué porcentaje del alcance corresponde a crear, modificar, reemplazar o corregir software existente. | G4: Nuevo desarrollo / Enhancement-evolutivo / Modernización-redevelopment / Mantenimiento (componente predominante > 50%). | H4: Composición del cambio · Línea base del activo · Frontera y componentes · Impacto y regresión | I4: =COUNTIF(Rubricas!$B$4:$B$112,A4) -> 12 | J4: =SUMIF(Rubricas!$B$4:$B$112,A4,Rubricas!$M$4:$M$112) -> 27 | K4: ISBSG (Development Type) + GAO (software nuevo, modificado, reutilizado)
A5: D2 | B5: Tipo de solución / arquetipo | C5: Núcleo | D5: =Parametros!D6 -> 0.11 | E5: Naturaleza predominante de lo que se construye. | F5: Determinar el objeto tecnológico predominante del esfuerzo con la pregunta dominante del catálogo. | G5: Aplicaciones · Integración · Datos/IA · Plataforma · Seguridad · Modernización (principal + secundarios). | H5: Objeto predominante · Distribución del esfuerzo · Drivers de esfuerzo · Validación de la clasificación | I5: =COUNTIF(Rubricas!$B$4:$B$112,A5) -> 12 | J5: =SUMIF(Rubricas!$B$4:$B$112,A5,Rubricas!$M$4:$M$112) -> 23 | K5: ISBSG (Application Group/Type) + adaptación organizacional
A6: D3 | B6: Tamaño funcional | C6: Núcleo | D6: =Parametros!D7 -> 0.18 | E6: Cuánto producto debe construirse o modificarse. | F6: Medir la cantidad de funcionalidad mediante procesos funcionales y movimientos de datos (o unidad interna calibrada). | G6: XS (1–5) · S (6–15) · M (16–30) · L (31–60) · XL (>60) procesos funcionales; tamaño en puntos de función. | H6: Estrategia de medición · Usuarios funcionales y frontera · Procesos funcionales · Datos · Movimientos de datos · Requisitos no funcionales · Consolidación | I6: =COUNTIF(Rubricas!$B$4:$B$112,A6) -> 14 | J6: =SUMIF(Rubricas!$B$4:$B$112,A6,Rubricas!$M$4:$M$112) -> 31 | K6: ISBSG + GAO + medición funcional ISO/IEC 19761
A7: D4 | B7: Complejidad | C7: Núcleo | D7: =Parametros!D8 -> 0.15 | E7: Qué tan difícil es implementar ese tamaño. | F7: Calificar 5 factores de 0 a 2 (reglas, arquitectura, seguridad, procesamiento, dependencias). | G7: 0–2 Baja · 3–5 Media · 6–8 Alta · 9–10 Muy alta. | H7: Reglas de negocio · Procesamiento · Arquitectura · Seguridad · Calidad y operación · Cumplimiento · Dependencias · Consolidación | I7: =COUNTIF(Rubricas!$B$4:$B$112,A7) -> 12 | J7: =SUMIF(Rubricas!$B$4:$B$112,A7,Rubricas!$M$4:$M$112) -> 26 | K7: GAO (complejidad funcional y técnica)
A8: D5 | B8: Integración / interdependencia | C8: Núcleo | D8: =Parametros!D9 -> 0.14 | E8: Cuánto depende la solución de otros sistemas. | F8: Contar interfaces y evaluar su dificultad (cantidad + dificultad). | G8: I0 sin interfaces · I1 1–2 simples · I2 3–5 o alguna compleja · I3 >5, sistemas críticos, protocolos no conocidos o múltiples terceros. | H8: Inventario de interfaces · Contratos y protocolos · Transformación de datos · Comportamiento y errores · Seguridad de integración · Terceros y ambientes · Consolidación | I8: =COUNTIF(Rubricas!$B$4:$B$112,A8) -> 13 | J8: =SUMIF(Rubricas!$B$4:$B$112,A8,Rubricas!$M$4:$M$112) -> 28 | K8: GAO (interfaces e interacciones)
A9: D6 | B9: Novedad y reutilización | C9: Complementaria | D9: =Parametros!D10 -> 0.05 | E9: Cuánto puede aprovecharse de activos existentes. | F9: Estimar qué porcentaje del alcance puede resolverse con conocimiento, código, componentes o patrones existentes. | G9: R1 >70% · R2 40–70% · R3 10–40% · R4 <10% reutilizable. | H9: Inventario de activos · Clasificación del reuso · Calidad del activo · Consolidación | I9: =COUNTIF(Rubricas!$B$4:$B$112,A9) -> 7 | J9: =SUMIF(Rubricas!$B$4:$B$112,A9,Rubricas!$M$4:$M$112) -> 13 | K9: GAO (nuevo, adaptado, reutilizado, autogenerado)
A10: D7 | B10: Entorno tecnológico | C10: Complementaria | D10: =Parametros!D11 -> 0.05 | E10: Contexto técnico en que será implementado. | F10: Identificar tecnología y grado de familiaridad del equipo. | G10: T1 Conocido · T2 Parcialmente conocido · T3 Nuevo · T4 Experimental. | H10: Stack · Plataforma y datos · Familiaridad · Herramientas y ambientes · Restricciones | I10: =COUNTIF(Rubricas!$B$4:$B$112,A10) -> 7 | J10: =SUMIF(Rubricas!$B$4:$B$112,A10,Rubricas!$M$4:$M$112) -> 15 | K10: ISBSG + GAO
A11: D8 | B11: Madurez del alcance | C11: Complementaria | D11: =Parametros!D12 -> 0.07 | E11: Cuánto se conoce realmente de lo solicitado. | F11: Checklist de 8 elementos del catálogo (objetivo, roles, funcionalidades, reglas, integraciones, datos, RNF, criterios de aceptación). | G11: M1 Idea (0–2) · M2 Preliminar (3–4) · M3 Definido (5–6) · M4 Validado (7–8) elementos con puntaje ≥ 2. | H11: Definición del problema · Requisitos funcionales · Datos e integraciones · Requisitos no funcionales · Criterios de aceptación · Límites y validación | I11: =COUNTIF(Rubricas!$B$4:$B$112,A11) -> 11 | J11: =SUMIF(Rubricas!$B$4:$B$112,A11,Rubricas!$M$4:$M$112) -> 23 | K11: GAO + propuesta
A12: D9 | B12: Contexto de ejecución | C12: Complementaria | D12: =Parametros!D13 -> 0.05 | E12: Condiciones bajo las cuales se desarrollará. | F12: Evaluar condiciones del equipo y forma de ejecución (8 variables del catálogo). | G12: Estable · Parcialmente conocido · Incierto. | H12: Equipo · Forma de trabajo · Dependencias externas | I12: =COUNTIF(Rubricas!$B$4:$B$112,A12) -> 8 | J12: =SUMIF(Rubricas!$B$4:$B$112,A12,Rubricas!$M$4:$M$112) -> 16 | K12: GAO + ISBSG
A13: D10 | B13: Sector / contexto de negocio | C13: Complementaria | D13: =Parametros!D14 -> 0.03 | E13: Condiciones externas que afectan el proyecto. | F13: Clasificar dominio y restricciones externas. | G13: Gobierno · Financiero · Salud · Comercio · Telecomunicaciones · Otros. | H13: Dominio · Regulación · Contratación y gobierno del proyecto | I13: =COUNTIF(Rubricas!$B$4:$B$112,A13) -> 6 | J13: =SUMIF(Rubricas!$B$4:$B$112,A13,Rubricas!$M$4:$M$112) -> 11 | K13: ISBSG
A14: D11 | B14: Evidencia histórica disponible | C14: Complementaria | D14: =Parametros!D15 -> 0.05 | E14: Qué tan comparable es el histórico utilizado. | F14: Evaluar cantidad, similitud y calidad de los proyectos comparables (p. ej. Jira). | G14: E1 0–1 · E2 2–3 · E3 4–7 · E4 ≥8 comparables. | H14: Cantidad y similitud · Calidad del dato · Explotación del histórico | I14: =COUNTIF(Rubricas!$B$4:$B$112,A14) -> 7 | J14: =SUMIF(Rubricas!$B$4:$B$112,A14,Rubricas!$M$4:$M$112) -> 16 | K14: ISBSG + GAO
C15: Total | D15: =SUM(D4:D14) -> 1 | I15: =SUM(I4:I14) -> 109

Sheet Rubricas
A1: Matriz de rúbricas y subdimensiones
A2: Cada criterio se califica de 0 a 3 según los descriptores. El peso interno (1–3) indica la importancia del criterio dentro de su dimensión. El hallazgo sugerido se muestra en la ficha cuando el puntaje es 0 o 1.
A3: ID | B3: Código | C3: Dimensión | D3: Tipo | E3: Subdimensión | F3: Criterio | G3: Pregunta de evaluación | H3: Evidencia esperada | I3: 0 – Sin información | J3: 1 – Parcial / supuesto | K3: 2 – Definido con vacíos | L3: 3 – Completo y validado | M3: Peso interno (1–3) | N3: ¿Admite N/A? | O3: Hallazgo sugerido (puntaje 0–1) | P3: Origen
A4: D1.01 | B4: D1 | C4: Tipo de desarrollo | D4: Núcleo | E4: Composición del cambio | F4: Composición del alcance cuantificada | G4: ¿Se conoce qué porcentaje del alcance corresponde a crear, modificar, reemplazar/transformar o corregir software? | H4: Tabla de composición por tipo de cambio que suma 100%. | I4: No se conoce la naturaleza del cambio. | J4: Se describe cualitativamente (p. ej. «es un desarrollo nuevo») sin cuantificar. | K4: Porcentajes estimados por juicio, sin detalle por funcionalidad. | L4: Porcentajes derivados del inventario de funcionalidades clasificadas por tipo de cambio. | M4: 3 | N4: No | O4: No está cuantificada la proporción nuevo / modificado / reemplazado / correctivo. Clasificar cada funcionalidad del inventario por tipo de cambio y totalizar. | P4: Catálogo
A5: D1.02 | B5: D1 | C5: Tipo de desarrollo | D5: Núcleo | E5: Composición del cambio | F5: Tipo de desarrollo asignado y justificado | G5: ¿El tipo de desarrollo (Nuevo, Enhancement/evolutivo, Modernización/redevelopment, Mantenimiento) está asignado según el componente predominante? | H5: Clasificación registrada con justificación trazable a la composición. | I5: No asignado. | J5: Asignado por el nombre del proyecto o por percepción. | K5: Asignado según la composición, sin justificación documentada. | L5: Asignado por el componente predominante (>50%) y justificado; componentes secundarios registrados. | M5: 3 | N5: No | O5: El tipo de desarrollo no está asignado o no se justifica con la composición del alcance. Asignarlo según el tipo de cambio que concentra la mayor proporción. | P5: Catálogo
A6: D1.03 | B6: D1 | C6: Tipo de desarrollo | D6: Núcleo | E6: Línea base del activo | F6: Línea base funcional del sistema existente | G6: ¿Existe inventario de las funcionalidades actuales del sistema que se modifica, reemplaza o mantiene? | H6: Inventario funcional, manual de usuario o medición previa del sistema. | I6: No hay información del sistema actual. | J6: Solo conocimiento tácito de personas clave. | K6: Documentación parcial o desactualizada. | L6: Inventario funcional actualizado (idealmente con tamaño medido). | M6: 2 | N6: Sí | O6: No hay línea base funcional del activo existente; sin ella no puede medirse el tamaño del cambio ni el alcance de regresión. Levantar el inventario de funcionalidades actuales. | P6: Medición funcional
A7: D1.04 | B7: D1 | C7: Tipo de desarrollo | D7: Núcleo | E7: Composición del cambio | F7: Funcionalidades nuevas identificadas | G7: ¿Se listan las funcionalidades que se agregan, desagregadas al nivel de proceso funcional? | H7: Listado de funcionalidades nuevas con identificador único. | I7: No se han identificado. | J7: Descritas como módulos o épicas. | K7: Listadas con granularidad heterogénea. | L7: Listadas a nivel de proceso funcional (responde a un evento y termina al completar su respuesta) con ID. | M7: 3 | N7: Sí | O7: Las funcionalidades nuevas no están desagregadas a nivel de proceso funcional. Descomponer módulos/épicas en acciones completas iniciadas por un evento. | P7: Medición funcional
A8: D1.05 | B8: D1 | C8: Tipo de desarrollo | D8: Núcleo | E8: Composición del cambio | F8: Funcionalidades modificadas y naturaleza del cambio | G8: Para cada funcionalidad existente que cambia, ¿se identifica qué datos que entran, salen, se consultan o se almacenan se agregan, modifican o eliminan? | H8: Lista de funcionalidades impactadas con el detalle de los movimientos de datos afectados. | I8: No identificadas. | J8: Se sabe que hay cambios en ciertos módulos, sin listar funcionalidades. | K8: Funcionalidades impactadas listadas, sin detalle del cambio. | L8: Funcionalidades y movimientos de datos agregados / modificados / eliminados identificados. | M8: 3 | N8: Sí | O8: No se detalla qué cambia en las funcionalidades existentes. En evolutivos el tamaño es la suma de movimientos de datos agregados, modificados y eliminados; identificarlos. | P8: Medición funcional
A9: D1.06 | B9: D1 | C9: Tipo de desarrollo | D9: Núcleo | E9: Composición del cambio | F9: Funcionalidades retiradas | G9: ¿Se identifican funcionalidades, interfaces o datos que se eliminan o dan de baja (o se declara explícitamente que no existen)? | H9: Listado de retiros o declaración explícita de ausencia. | I9: No se ha analizado. | J9: Se mencionan retiros sin detalle. | K9: Retiros listados sin análisis de impacto (o ausencia no confirmada). | L9: Retiros listados con impacto en datos, usuarios e interfaces, o ausencia confirmada. | M9: 1 | N9: Sí | O9: No se ha analizado si hay funcionalidad a retirar; los retiros también consumen esfuerzo (movimientos eliminados, datos, pruebas). Confirmarlo explícitamente. | P9: Medición funcional
A10: D1.07 | B10: D1 | C10: Tipo de desarrollo | D10: Núcleo | E10: Frontera y componentes | F10: Frontera del software definida | G10: ¿Está claro qué software se construye o modifica (dentro del alcance) y qué sistemas, usuarios o componentes quedan fuera? | H10: Diagrama de contexto con piezas de software en alcance y actores externos. | I10: No definida. | J10: Implícita o ambigua. | K10: Diagrama de contexto sin validar o con ambigüedades menores. | L10: Frontera validada con piezas en alcance y usuarios externos explícitos. | M10: 3 | N10: No | O10: La frontera del software no es explícita; hay riesgo de contar de más o de menos. Elaborar diagrama de contexto con piezas en alcance y sistemas externos. | P10: Medición funcional
A11: D1.08 | B11: D1 | C11: Tipo de desarrollo | D11: Núcleo | E11: Frontera y componentes | F11: Capas y componentes afectados | G11: ¿Se identifican las capas (presentación, negocio, servicios, datos) y los componentes que se crean o modifican? | H11: Vista de arquitectura con componentes marcados como nuevos o modificados. | I11: No identificados. | J11: Se mencionan tecnologías sin ubicar componentes. | K11: Componentes identificados sin clasificar nuevo/modificado. | L11: Componentes por capa identificados y clasificados. | M11: 2 | N11: No | O11: No se identifican componentes/capas afectados; cada componente con frontera propia puede requerir medición y pruebas independientes. | P11: Medición funcional
A12: D1.09 | B12: D1 | C12: Tipo de desarrollo | D12: Núcleo | E12: Línea base del activo | F12: Documentación técnica y código del activo | G12: ¿Están disponibles y actualizados el código fuente, la documentación técnica y los ambientes del sistema existente? | H12: Acceso confirmado a repositorio, arquitectura y modelo de datos. | I12: No disponible. | J12: Disponible parcialmente o sin acceso confirmado. | K12: Disponible con vacíos conocidos. | L12: Disponible, actualizado y con acceso confirmado. | M12: 2 | N12: Sí | O12: No se confirma acceso ni estado del código/documentación del activo existente; aumenta el esfuerzo de análisis. Solicitar acceso y evaluar su estado. | P12: Buenas prácticas
A13: D1.10 | B13: D1 | C13: Tipo de desarrollo | D13: Núcleo | E13: Impacto y regresión | F13: Alcance de regresión | G13: ¿Se conocen las funcionalidades existentes que deben volver a probarse por efecto de los cambios? | H13: Matriz de impacto o suite de regresión identificada. | I13: No se ha considerado. | J13: Se reconoce la necesidad sin identificar funcionalidades. | K13: Funcionalidades a regresionar identificadas, sin estrategia. | L13: Alcance y estrategia de regresión definidos (manual/automatizada, suites existentes). | M13: 2 | N13: Sí | O13: No está definido el alcance de regresión; en evolutivos y modernizaciones es un driver de esfuerzo relevante. | P13: Buenas prácticas
A14: D1.11 | B14: D1 | C14: Tipo de desarrollo | D14: Núcleo | E14: Impacto y regresión | F14: Equivalencia funcional en modernización | G14: Cuando se transforma un activo, ¿se define qué comportamiento debe preservarse y cómo se verificará la equivalencia? | H14: Criterios de equivalencia y casos de referencia. | I14: No definido. | J14: Se asume «igual al actual» sin detalle. | K14: Funcionalidades a preservar listadas, sin criterio de verificación. | L14: Funcionalidades a preservar, cambios aceptados y método de verificación definidos. | M14: 2 | N14: Sí | O14: En la modernización no se define qué debe preservarse ni cómo verificar la equivalencia funcional. | P14: Catálogo
A15: D1.12 | B15: D1 | C15: Tipo de desarrollo | D15: Núcleo | E15: Composición del cambio | F15: Separación correctivo vs. evolutivo | G15: ¿Se distinguen las correcciones de defectos de los cambios y nuevas funcionalidades? | H15: Backlog clasificado (defecto / cambio / nueva funcionalidad). | I15: Mezclado sin clasificar. | J15: Separación parcial. | K15: Separado sin criterio formal. | L15: Clasificado con criterio acordado. | M15: 1 | N15: No | O15: Correcciones y nuevos requerimientos no están separados; distorsiona el tipo de desarrollo y la comparación con el histórico. | P15: Catálogo
... A112: D11.07 | B112: D11 | C112: Evidencia histórica disponible | D112: Complementaria | E112: Cantidad y similitud | F112: Vigencia de los comparables | G112: ¿Los comparables son recientes y con proceso y tecnología vigentes? | H112: Fechas y contexto. | I112: Obsoletos. | J112: > 5 años. | K112: 2–5 años. | L112: < 2 años y vigentes. | M112: 1 | N112: No | O112: Los comparables no son vigentes. | P112: Catálogo

Sheet Parametros
A1: Parámetros del modelo de madurez para estimación
A2: Los valores en azul con fondo amarillo son editables; todas las hojas se recalculan a partir de ellos.
A3: Pesos por dimensión | H3: Arquetipos | I3: Tipos de desarrollo | J3: Entorno tecnológico | K3: Contexto de ejecución | L3: Sector | M3: Sí / No
A4: Código | B4: Dimensión | C4: Tipo | D4: Peso | E4: Justificación del peso | H4: Aplicaciones y soluciones digitales | I4: Nuevo desarrollo | J4: T1 - Conocida | K4: Estable | L4: Gobierno | M4: Sí
A5: D1 | B5: Tipo de desarrollo | C5: Núcleo | D5: 0.12 | E5: Define si el tamaño se mide como producto completo o como cambio; condiciona la selección de comparables. | H5: Integración e interoperabilidad | I5: Enhancement / evolutivo | J5: T2 - Parcialmente conocida | K5: Parcialmente conocido | L5: Financiero | M5: No
A6: D2 | B6: Tipo de solución / arquetipo | C6: Núcleo | D6: 0.11 | E6: Determina drivers de esfuerzo y el grupo histórico de referencia. | H6: Datos, analítica e inteligencia artificial | I6: Modernización / redevelopment | J6: T3 - Nueva | K6: Incierto | L6: Salud
A7: D3 | B7: Tamaño funcional | C7: Núcleo | D7: 0.18 | E7: Principal variable explicativa del esfuerzo; por eso recibe el mayor peso. | H7: Plataforma, infraestructura y DevOps | I7: Mantenimiento | J7: T4 - Experimental | L7: Comercio
A8: D4 | B8: Complejidad | C8: Núcleo | D8: 0.15 | E8: Ajusta la productividad sobre el tamaño; captura lo que el tamaño funcional no mide (reglas, algoritmos, RNF). | H8: Seguridad, identidad y confianza digital | L8: Telecomunicaciones
A9: D5 | B9: Integración / interdependencia | C9: Núcleo | D9: 0.14 | E9: Las interfaces concentran incertidumbre y dependencias con terceros. | H9: Modernización y migración | L9: Otros
A10: D6 | B10: Novedad y reutilización | C10: Complementaria | D10: 0.05 | E10: Modula el esfuerzo (reuso vs. construcción).
A11: D7 | B11: Entorno tecnológico | C11: Complementaria | D11: 0.05 | E11: Afecta la productividad por curva de aprendizaje.
A12: D8 | B12: Madurez del alcance | C12: Complementaria | D12: 0.07 | E12: Visión transversal del estado de la documentación; mayor peso entre complementarias.
A13: D9 | B13: Contexto de ejecución | C13: Complementaria | D13: 0.05 | E13: Afecta la capacidad y la productividad de ejecución.
A14: D10 | B14: Sector / contexto de negocio | C14: Complementaria | D14: 0.03 | E14: Restricciones externas; bajo impacto directo en tamaño.
A15: D11 | B15: Evidencia histórica disponible | C15: Complementaria | D15: 0.05 | E15: Condiciona la técnica de estimación y la confianza en la conversión tamaño → esfuerzo.
C16: Total | D16: =SUM(D5:D15) -> 1 | E16: =IF(ABS(D16-1)<0.0001,"OK: los pesos suman 100%","⚠ Los pesos deben sumar 100%") -> OK: los pesos suman 100%
C17: Peso núcleo | D17: =SUMIF(C5:C15,"Núcleo",D5:D15) -> 0.7 | E17: =IF(MIN(D5:D9)>MAX(D10:D15),"OK: cada dimensión núcleo pesa más que cualquier complementaria","⚠ Una complementaria pesa igual o más que una núcleo") -> OK: cada dimensión núcleo pesa más que cualquier complementaria
A20: Escala de calificación de criterios
A21: Puntaje | B21: Significado | C21: Descripción
A22: 0 | B22: Sin información | C22: No existe información o evidencia sobre el criterio.
A23: 1 | B23: Parcial / supuesto | C23: Información mencionada, verbal o supuesta; sin documento o sin cuantificar.
A24: 2 | B24: Definido con vacíos | C24: Información documentada pero incompleta o sin validar.
A25: 3 | B25: Completo y validado | C25: Información completa, cuantificada, documentada y validada por el responsable.
A26: N/A | B26: No aplica | C26: Solo en criterios marcados como «Admite N/A». Se excluye del máximo posible.
A28: Niveles de madurez (dimensión y general)
A29: Límite inferior | B29: Nivel | C29: N° | D29: Interpretación | E29: Técnica de estimación sugerida
A30: 0 | B30: N1 - Incipiente | C30: 1 | D30: Información insuficiente; la estimación sería una conjetura. | E30: Juicio experto / Delphi con rango amplio; priorizar levantamiento de información antes de comprometer una cifra.
A31: 0.2 | B31: N2 - Preliminar | C31: 2 | D31: Visión general con vacíos críticos. | E31: Juicio experto + analogía; estimación de orden de magnitud.
A32: 0.4 | B32: N3 - Intermedio | C32: 3 | D32: Alcance principal conocido; faltan detalles relevantes. | E32: Analogía con histórico + descomposición (WBS); estimación preliminar.
A33: 0.6 | B33: N4 - Definido | C33: 4 | D33: Alcance definido y mayormente cuantificado. | E33: Tamaño funcional + productividad histórica, contrastado con descomposición.
A34: 0.8 | B34: N5 - Validado | C34: 5 | D34: Información completa, cuantificada y validada. | E34: Tamaño funcional + modelo paramétrico calibrado; desempeño empírico si el equipo es conocido.
A36: Regla de tope por dimensiones núcleo
A37: Umbral mínimo de madurez núcleo | B37: 0.4 | C37: Si alguna dimensión núcleo queda por debajo de este umbral…
A38: Nivel general máximo permitido | B38: 3 | C38: …la madurez general no puede superar este nivel (evita que las complementarias compensen vacíos críticos).
A40: Clases de tamaño (por N° de procesos funcionales)
A41: Mínimo de procesos | B41: Clase | C41: Rango del catálogo
A42: 1 | B42: XS | C42: 1–5
A43: 6 | B43: S | C43: 6–15
A44: 16 | B44: M | C44: 16–30
A45: 31 | B45: L | C45: 31–60
A46: 61 | B46: XL | C46: >60
A48: Tamaño de referencia
A49: Puntos de función promedio por proceso funcional | B49: 8 | C49: Supuesto inicial para la aproximación temprana del tamaño (N° procesos × promedio). Debe calibrarse con el histórico de la organización.
A51: Nivel de complejidad (suma de 5 factores, 0–10)
A52: Puntaje mínimo | B52: Nivel
A53: 0 | B53: Baja
A54: 3 | B54: Media
A55: 6 | B55: Alta
A56: 9 | B56: Muy alta

Sheet Ficha
A1: Ficha de evaluación de madurez para estimación
A2: Ingresar datos solo en celdas amarillas (texto azul). Puntajes de criterios: 0, 1, 2, 3 o N/A (solo si la rúbrica lo admite). Criterios núcleo sin calificar cuentan como 0. Una dimensión complementaria sin ningún criterio calificado se excluye del cálculo.
A4: Proyecto
A5: Cliente / área
A6: Evaluador(es)
A7: Fecha de evaluación
A8: Momento de estimación
A9: Fuentes revisadas
A10: Versión de la ficha
A12: PARTE A · CARACTERIZACIÓN DEL PROYECTO (valores de clasificación del catálogo)
A13: Dimensión | D13: Variable | E13: Valor (ingresar) | G13: Clasificación resultante | H13: Regla aplicada
A14: D1 · Tipo de desarrollo | D14: % del alcance: nuevo desarrollo | G14: =IF(SUM(E14:E17)=0,"Sin datos",INDEX(Parametros!$I$4:$I$7,MATCH(MAX(E14:E17),E14:E17,0))) -> Sin datos | H14: Componente predominante (mayor %). Los cuatro porcentajes deben sumar 100%.
D15: % del alcance: enhancement / evolutivo | G15: =IF(COUNT(E14:E17)=0,"",IF(ABS(SUM(E14:E17)-1)<0.001,"Composición suma 100%","⚠ La composición no suma 100%"))
D16: % del alcance: modernización / redevelopment
D17: % del alcance: mantenimiento (correctivo / menor)
A18: D2 · Tipo de solución / arquetipo | D18: Arquetipo principal | G18: =IF(E18="","Sin asignar",E18) -> Sin asignar | H18: Principal = trabajo que explica la mayor proporción del esfuerzo esperado, no el componente más visible.
D19: Arquetipos secundarios (texto)
D20: % del esfuerzo del arquetipo principal | G20: =IF(E20="","",IF(E20>=0.5,"Predominio claro","Predominio débil: revisar secundarios"))
A21: D3 · Tamaño funcional | D21: N° de procesos funcionales identificados | G21: =IF(N(E21)=0,"Sin datos","Clase "&LOOKUP(E21,Parametros!$A$42:$A$46,Parametros!$B$42:$B$46)) -> Sin datos | H21: XS 1–5 · S 6–15 · M 16–30 · L 31–60 · XL >60 procesos. Aproximación = procesos × promedio.
D22: Puntos de función promedio por proceso (vacío = referencia) | G22: =IF(N(E21)=0,"","≈ "&TEXT(E21*IF(N(E22)=0,Parametros!$B$49,E22),"0")&" PF (aproximación)")
D23: Tamaño medido en puntos de función (si existe) | G23: =IF(N(E23)=0,"Sin medición detallada","Medido: "&E23&" PF") -> Sin medición detallada
A24: D4 · Complejidad | D24: Factor reglas de negocio (0 simples · 1 moderadas · 2 complejas) | G24: =IF(COUNT(E24:E28)=0,"Sin datos","Puntaje "&SUM(E24:E28)&" / 10") -> Sin datos | H24: Suma 0–10: 0–2 Baja · 3–5 Media · 6–8 Alta · 9–10 Muy alta.
D25: Factor arquitectura (0 conocida · 1 algunas novedades · 2 nueva/sofisticada) | G25: =IF(COUNT(E24:E28)=0,"","Complejidad "&LOOKUP(SUM(E24:E28),Parametros!$A$53:$A$56,Parametros!$B$53:$B$56))
D26: Factor seguridad (0 estándar · 1 elevada · 2 crítica)
D27: Factor procesamiento (0 simple · 1 medio · 2 complejo/tiempo real)
D28: Factor dependencias (0 pocas · 1 varias · 2 muchas/críticas)
A29: D5 · Integración | D29: N° de interfaces | G29: =IF(E29="","Sin datos",IF(E29=0,"I0 - Sin interfaces",IF(OR(E29>5,E31="Sí"),"I3 - Alta",IF(OR(E29>=3,E30="Sí"),"I2 - Media","I1 - Baja")))) -> Sin datos | H29: I0 sin interfaces · I1 1–2 simples · I2 3–5 o alguna compleja · I3 >5, críticos, protocolos no conocidos o múltiples terceros.
D30: ¿Alguna interfaz compleja?
D31: ¿Sistemas críticos, protocolos no conocidos o múltiples terceros?
A32: D6 · Reutilización | D32: % del alcance reutilizable | G32: =IF(E32="","Sin datos",IF(E32>0.7,"R1 - Alta reutilización",IF(E32>=0.4,"R2 - Media",IF(E32>=0.1,"R3 - Baja","R4 - Nuevo")))) -> Sin datos | H32: R1 >70% · R2 40–70% · R3 10–40% · R4 <10%.
A33: D7 · Entorno tecnológico | D33: Familiaridad tecnológica del equipo | G33: =IF(E33="","Sin datos",E33) -> Sin datos | H33: T1 Conocida · T2 Parcialmente conocida · T3 Nueva · T4 Experimental.
A34: D8 · Madurez del alcance | D34: Elementos del checklist con puntaje ≥ 2 (cálculo automático, D8.01–D8.08) | E34: =COUNTIF(F165:F172,">=2") -> 0 | G34: =IF(COUNT(F165:F172)=0,"Sin datos",IF(E34<=2,"M1 - Idea",IF(E34<=4,"M2 - Preliminar",IF(E34<=6,"M3 - Definido","M4 - Validado")))) -> Sin datos | H34: M1 0–2 · M2 3–4 · M3 5–6 · M4 7–8 elementos.
A35: D9 · Contexto de ejecución | D35: Condición del contexto de ejecución | G35: =IF(E35="","Sin datos",E35) -> Sin datos | H35: Estable · Parcialmente conocido · Incierto.
A36: D10 · Sector | D36: Sector del cliente | G36: =IF(E36="","Sin datos",E36) -> Sin datos | H36: Gobierno · Financiero · Salud · Comercio · Telecomunicaciones · Otros.
A37: D11 · Evidencia histórica | D37: N° de proyectos comparables | G37: =IF(E37="","Sin datos",IF(E37<=1,"E1 - Muy baja",IF(E37<=3,"E2 - Baja",IF(E37<=7,"E3 - Media","E4 - Alta")))) -> Sin datos | H37: E1 0–1 · E2 2–3 · E3 4–7 · E4 ≥8 comparables.
A40: RESUMEN DE MADUREZ (cálculo automático)
A41: Dimensión | D41: Principal brecha identificada | E41: Peso | F41: Madurez | G41: Nivel | H41: Tipo | I41: Aporte a la madurez general | J41: ¿Incluida en el cálculo?
A42: D1 · Tipo de desarrollo | D42: =IF(MAX(K81:K92)=0,"Sin brechas relevantes",INDEX(J81:J92,MATCH(MAX(K81:K92),K81:K92,0))) -> Sin evaluar (núcleo, cuenta como 0) – Frontera del software definida | E42: =Parametros!D5 -> 0.12 | F42: =IF(SUMIF($B$80:$B$240,"D1",$I$80:$I$240)=0,0,SUMIF($B$80:$B$240,"D1",$H$80:$H$240)/SUMIF($B$80:$B$240,"D1",$I$80:$I$240)) -> 0 | G42: =IF(J42="No","No evaluada",INDEX(Parametros!$B$30:$B$34,MATCH(F42,Parametros!$A$30:$A$34,1))) -> N1 - Incipiente | H42: =Parametros!C5 -> Núcleo | I42: =IF(J42="No",0,E42*F42/SUMPRODUCT($E$42:$E$52*($J$42:$J$52="Sí"))) -> 0 | J42: ="Sí" -> Sí
A43: D2 · Tipo de solución / arquetipo | D43: =IF(MAX(K94:K105)=0,"Sin brechas relevantes",INDEX(J94:J105,MATCH(MAX(K94:K105),K94:K105,0))) -> Sin evaluar (núcleo, cuenta como 0) – Drivers del arquetipo principal | E43: =Parametros!D6 -> 0.11 | F43: =IF(SUMIF($B$80:$B$240,"D2",$I$80:$I$240)=0,0,SUMIF($B$80:$B$240,"D2",$H$80:$H$240)/SUMIF($B$80:$B$240,"D2",$I$80:$I$240)) -> 0 | G43: =IF(J43="No","No evaluada",INDEX(Parametros!$B$30:$B$34,MATCH(F43,Parametros!$A$30:$A$34,1))) -> N1 - Incipiente | H43: =Parametros!C6 -> Núcleo | I43: =IF(J43="No",0,E43*F43/SUMPRODUCT($E$42:$E$52*($J$42:$J$52="Sí"))) -> 0 | J43: ="Sí" -> Sí
A44: D3 · Tamaño funcional | D44: =IF(MAX(K107:K120)=0,"Sin brechas relevantes",INDEX(J107:J120,MATCH(MAX(K107:K120),K107:K120,0))) -> Sin evaluar (núcleo, cuenta como 0) – Unidad objetiva y clase de tamaño | E44: =Parametros!D7 -> 0.18 | F44: =IF(SUMIF($B$80:$B$240,"D3",$I$80:$I$240)=0,0,SUMIF($B$80:$B$240,"D3",$H$80:$H$240)/SUMIF($B$80:$B$240,"D3",$I$80:$I$240)) -> 0 | G44: =IF(J44="No","No evaluada",INDEX(Parametros!$B$30:$B$34,MATCH(F44,Parametros!$A$30:$A$34,1))) -> N1 - Incipiente | H44: =Parametros!C7 -> Núcleo | I44: =IF(J44="No",0,E44*F44/SUMPRODUCT($E$42:$E$52*($J$42:$J$52="Sí"))) -> 0 | J44: ="Sí" -> Sí
A45: D4 · Complejidad | D45: =IF(MAX(K122:K133)=0,"Sin brechas relevantes",INDEX(J122:J133,MATCH(MAX(K122:K133),K122:K133,0))) -> Sin evaluar (núcleo, cuenta como 0) – Requisitos de seguridad clasificados | E45: =Parametros!D8 -> 0.15 | F45: =IF(SUMIF($B$80:$B$240,"D4",$I$80:$I$240)=0,0,SUMIF($B$80:$B$240,"D4",$H$80:$H$240)/SUMIF($B$80:$B$240,"D4",$I$80:$I$240)) -> 0 | G45: =IF(J45="No","No evaluada",INDEX(Parametros!$B$30:$B$34,MATCH(F45,Parametros!$A$30:$A$34,1))) -> N1 - Incipiente | H45: =Parametros!C8 -> Núcleo | I45: =IF(J45="No",0,E45*F45/SUMPRODUCT($E$42:$E$52*($J$42:$J$52="Sí"))) -> 0 | J45: ="Sí" -> Sí
A46: D5 · Integración / interdependencia | D46: =IF(MAX(K135:K147)=0,"Sin brechas relevantes",INDEX(J135:J147,MATCH(MAX(K135:K147),K135:K147,0))) -> Sin evaluar (núcleo, cuenta como 0) – Contratos de interfaz | E46: =Parametros!D9 -> 0.14 | F46: =IF(SUMIF($B$80:$B$240,"D5",$I$80:$I$240)=0,0,SUMIF($B$80:$B$240,"D5",$H$80:$H$240)/SUMIF($B$80:$B$240,"D5",$I$80:$I$240)) -> 0 | G46: =IF(J46="No","No evaluada",INDEX(Parametros!$B$30:$B$34,MATCH(F46,Parametros!$A$30:$A$34,1))) -> N1 - Incipiente | H46: =Parametros!C9 -> Núcleo | I46: =IF(J46="No",0,E46*F46/SUMPRODUCT($E$42:$E$52*($J$42:$J$52="Sí"))) -> 0 | J46: ="Sí" -> Sí
A47: D6 · Novedad y reutilización | D47: =IF(MAX(K149:K155)=0,"Sin brechas relevantes",INDEX(J149:J155,MATCH(MAX(K149:K155),K149:K155,0))) -> Sin brechas relevantes | E47: =Parametros!D10 -> 0.05 | F47: =IF(SUMIF($B$80:$B$240,"D6",$I$80:$I$240)=0,0,SUMIF($B$80:$B$240,"D6",$H$80:$H$240)/SUMIF($B$80:$B$240,"D6",$I$80:$I$240)) -> 0 | G47: =IF(J47="No","No evaluada",INDEX(Parametros!$B$30:$B$34,MATCH(F47,Parametros!$A$30:$A$34,1))) -> No evaluada | H47: =Parametros!C10 -> Complementaria | I47: =IF(J47="No",0,E47*F47/SUMPRODUCT($E$42:$E$52*($J$42:$J$52="Sí"))) -> 0 | J47: =IF(SUMPRODUCT(($B$80:$B$240="D6")*ISNUMBER($F$80:$F$240))>0,"Sí","No") -> No
A48: D7 · Entorno tecnológico | D48: =IF(MAX(K157:K163)=0,"Sin brechas relevantes",INDEX(J157:J163,MATCH(MAX(K157:K163),K157:K163,0))) -> Sin brechas relevantes | E48: =Parametros!D11 -> 0.05 | F48: =IF(SUMIF($B$80:$B$240,"D7",$I$80:$I$240)=0,0,SUMIF($B$80:$B$240,"D7",$H$80:$H$240)/SUMIF($B$80:$B$240,"D7",$I$80:$I$240)) -> 0 | G48: =IF(J48="No","No evaluada",INDEX(Parametros!$B$30:$B$34,MATCH(F48,Parametros!$A$30:$A$34,1))) -> No evaluada | H48: =Parametros!C11 -> Complementaria | I48: =IF(J48="No",0,E48*F48/SUMPRODUCT($E$42:$E$52*($J$42:$J$52="Sí"))) -> 0 | J48: =IF(SUMPRODUCT(($B$80:$B$240="D7")*ISNUMBER($F$80:$F$240))>0,"Sí","No") -> No
A49: D8 · Madurez del alcance | D49: =IF(MAX(K165:K175)=0,"Sin brechas relevantes",INDEX(J165:J175,MATCH(MAX(K165:K175),K165:K175,0))) -> Sin brechas relevantes | E49: =Parametros!D12 -> 0.07 | F49: =IF(SUMIF($B$80:$B$240,"D8",$I$80:$I$240)=0,0,SUMIF($B$80:$B$240,"D8",$H$80:$H$240)/SUMIF($B$80:$B$240,"D8",$I$80:$I$240)) -> 0 | G49: =IF(J49="No","No evaluada",INDEX(Parametros!$B$30:$B$34,MATCH(F49,Parametros!$A$30:$A$34,1))) -> No evaluada | H49: =Parametros!C12 -> Complementaria | I49: =IF(J49="No",0,E49*F49/SUMPRODUCT($E$42:$E$52*($J$42:$J$52="Sí"))) -> 0 | J49: =IF(SUMPRODUCT(($B$80:$B$240="D8")*ISNUMBER($F$80:$F$240))>0,"Sí","No") -> No
A50: D9 · Contexto de ejecución | D50: =IF(MAX(K177:K184)=0,"Sin brechas relevantes",INDEX(J177:J184,MATCH(MAX(K177:K184),K177:K184,0))) -> Sin brechas relevantes | E50: =Parametros!D13 -> 0.05 | F50: =IF(SUMIF($B$80:$B$240,"D9",$I$80:$I$240)=0,0,SUMIF($B$80:$B$240,"D9",$H$80:$H$240)/SUMIF($B$80:$B$240,"D9",$I$80:$I$240)) -> 0 | G50: =IF(J50="No","No evaluada",INDEX(Parametros!$B$30:$B$34,MATCH(F50,Parametros!$A$30:$A$34,1))) -> No evaluada | H50: =Parametros!C13 -> Complementaria | I50: =IF(J50="No",0,E50*F50/SUMPRODUCT($E$42:$E$52*($J$42:$J$52="Sí"))) -> 0 | J50: =IF(SUMPRODUCT(($B$80:$B$240="D9")*ISNUMBER($F$80:$F$240))>0,"Sí","No") -> No
A51: D10 · Sector / contexto de negocio | D51: =IF(MAX(K186:K191)=0,"Sin brechas relevantes",INDEX(J186:J191,MATCH(MAX(K186:K191),K186:K191,0))) -> Sin brechas relevantes | E51: =Parametros!D14 -> 0.03 | F51: =IF(SUMIF($B$80:$B$240,"D10",$I$80:$I$240)=0,0,SUMIF($B$80:$B$240,"D10",$H$80:$H$240)/SUMIF($B$80:$B$240,"D10",$I$80:$I$240)) -> 0 | G51: =IF(J51="No","No evaluada",INDEX(Parametros!$B$30:$B$34,MATCH(F51,Parametros!$A$30:$A$34,1))) -> No evaluada | H51: =Parametros!C14 -> Complementaria | I51: =IF(J51="No",0,E51*F51/SUMPRODUCT($E$42:$E$52*($J$42:$J$52="Sí"))) -> 0 | J51: =IF(SUMPRODUCT(($B$80:$B$240="D10")*ISNUMBER($F$80:$F$240))>0,"Sí","No") -> No
A52: D11 · Evidencia histórica disponible | D52: =IF(MAX(K193:K199)=0,"Sin brechas relevantes",INDEX(J193:J199,MATCH(MAX(K193:K199),K193:K199,0))) -> Sin brechas relevantes | E52: =Parametros!D15 -> 0.05 | F52: =IF(SUMIF($B$80:$B$240,"D11",$I$80:$I$240)=0,0,SUMIF($B$80:$B$240,"D11",$H$80:$H$240)/SUMIF($B$80:$B$240,"D11",$I$80:$I$240)) -> 0 | G52: =IF(J52="No","No evaluada",INDEX(Parametros!$B$30:$B$34,MATCH(F52,Parametros!$A$30:$A$34,1))) -> No evaluada | H52: =Parametros!C15 -> Complementaria | I52: =IF(J52="No",0,E52*F52/SUMPRODUCT($E$42:$E$52*($J$42:$J$52="Sí"))) -> 0 | J52: =IF(SUMPRODUCT(($B$80:$B$240="D11")*ISNUMBER($F$80:$F$240))>0,"Sí","No") -> No
A53: Madurez general ponderada | F53: =SUM(I42:I52) -> 0 | G53: =INDEX(Parametros!$B$30:$B$34,MATCH(F53,Parametros!$A$30:$A$34,1)) -> N1 - Incipiente | H53: Nivel según puntaje (antes de la regla de tope)
A54: Menor madurez entre dimensiones núcleo | F54: =MIN(F42:F46) -> 0 | G54: =IF(F54<Parametros!$B$37,"Aplica tope: nivel máximo "&INDEX(Parametros!$B$30:$B$34,Parametros!$B$38),"No aplica tope") -> Aplica tope: nivel máximo N3 - Intermedio
A55: NIVEL DE MADUREZ GENERAL (final) | F55: =MIN(MATCH(F53,Parametros!$A$30:$A$34,1),IF(F54<Parametros!$B$37,Parametros!$B$38,5)) -> 1 | G55: =IF(COUNT($F$80:$F$240)=0,"Sin evaluar",INDEX(Parametros!$B$30:$B$34,F55)) -> Sin evaluar
A56: Interpretación | D56: =IF(COUNT($F$80:$F$240)=0,"",INDEX(Parametros!$D$30:$D$34,F55))
A57: Técnica de estimación sugerida | D57: =IF(COUNT($F$80:$F$240)=0,"",INDEX(Parametros!$E$30:$E$34,F55))
A59: VALIDACIONES DE CONSISTENCIA (cruce entre caracterización y criterios)
A60: ID | B60: Regla de consistencia | E60: Estado | G60: Acción sugerida si hay inconsistencia
A61: V1 | B61: Los porcentajes de composición del tipo de desarrollo suman 100%. | E61: =IF(COUNT($F$80:$F$240)+COUNT(E14:E37)-COUNT(E34)=0,"Sin datos",IF(AND(COUNT(E14:E17)>0,ABS(SUM(E14:E17)-1)>0.001),"⚠ Revisar","OK")) -> Sin datos | G61: =IF(E61="⚠ Revisar","Ajustar los porcentajes de nuevo / evolutivo / modernización / mantenimiento para que sumen 100%.","")
A62: V2 | B62: Si hay componente evolutivo, de modernización o mantenimiento, existe línea base del activo (D1.03). | E62: =IF(COUNT($F$80:$F$240)+COUNT(E14:E37)-COUNT(E34)=0,"Sin datos",IF(AND(SUM(E15:E17)>0,OR(F83="N/A",AND(ISNUMBER(F83),F83<=1))),"⚠ Revisar","OK")) -> Sin datos | G62: =IF(E62="⚠ Revisar","Se modifica un activo existente sin línea base funcional: D1.03 no debería ser N/A ni ≤ 1.","")
A63: V3 | B63: El arquetipo Modernización no convive con un tipo de desarrollo predominantemente nuevo. | E63: =IF(COUNT($F$80:$F$240)+COUNT(E14:E37)-COUNT(E34)=0,"Sin datos",IF(AND(E18="Modernización y migración",G14="Nuevo desarrollo"),"⚠ Revisar","OK")) -> Sin datos | G63: =IF(E63="⚠ Revisar","Revisar el arquetipo o la composición del tipo de desarrollo.","")
A64: V4 | B64: El arquetipo principal Integración tiene al menos 3 interfaces. | E64: =IF(COUNT($F$80:$F$240)+COUNT(E14:E37)-COUNT(E34)=0,"Sin datos",IF(AND(E18="Integración e interoperabilidad",N(E29)<3),"⚠ Revisar","OK")) -> Sin datos | G64: =IF(E64="⚠ Revisar","Con pocas interfaces el esfuerzo difícilmente se concentra en integración; revisar la clasificación.","")
A65: V5 | B65: Si se declara Integración (principal o secundario) se registra el N° de interfaces. | E65: =IF(COUNT($F$80:$F$240)+COUNT(E14:E37)-COUNT(E34)=0,"Sin datos",IF(AND(OR(E18="Integración e interoperabilidad",ISNUMBER(SEARCH("Integración",E19))),E29=""),"⚠ Revisar","OK")) -> Sin datos | G65: =IF(E65="⚠ Revisar","Registrar el número de interfaces en la Parte A.","")
A66: V6 | B66: Las interfaces declaradas cuentan con inventario (D5.01 ≥ 2). | E66: =IF(COUNT($F$80:$F$240)+COUNT(E14:E37)-COUNT(E34)=0,"Sin datos",IF(AND(N(E29)>0,AND(ISNUMBER(F135),F135<=1)),"⚠ Revisar","OK")) -> Sin datos | G66: =IF(E66="⚠ Revisar","Se declara un número de interfaces que no está respaldado por un inventario.","")
A67: V7 | B67: El N° de procesos funcionales está respaldado por inventario (D3.05 ≥ 2). | E67: =IF(COUNT($F$80:$F$240)+COUNT(E14:E37)-COUNT(E34)=0,"Sin datos",IF(AND(N(E21)>0,AND(ISNUMBER(F111),F111<=1)),"⚠ Revisar","OK")) -> Sin datos | G67: =IF(E67="⚠ Revisar","El número de procesos registrado no tiene inventario que lo respalde; el tamaño es una suposición.","")
A68: V8 | B68: Si el inventario de procesos está calificado (D3.05 ≥ 2) se registra la cantidad. | E68: =IF(COUNT($F$80:$F$240)+COUNT(E14:E37)-COUNT(E34)=0,"Sin datos",IF(AND(ISNUMBER(F111),F111>=2,N(E21)=0),"⚠ Revisar","OK")) -> Sin datos | G68: =IF(E68="⚠ Revisar","Registrar el N° de procesos funcionales en la Parte A para obtener la clase de tamaño.","")
A69: V9 | B69: Seguridad calificada como crítica (factor = 2) tiene requisitos especificados (D4.06 ≥ 2). | E69: =IF(COUNT($F$80:$F$240)+COUNT(E14:E37)-COUNT(E34)=0,"Sin datos",IF(AND(E26=2,AND(ISNUMBER(F127),F127<=1)),"⚠ Revisar","OK")) -> Sin datos | G69: =IF(E69="⚠ Revisar","Se califica la seguridad como crítica sin requisitos especificados; la complejidad no está sustentada.","")
A70: V10 | B70: Reglas calificadas como complejas (factor = 2) están caracterizadas (D4.02 ≥ 2). | E70: =IF(COUNT($F$80:$F$240)+COUNT(E14:E37)-COUNT(E34)=0,"Sin datos",IF(AND(E24=2,AND(ISNUMBER(F123),F123<=1)),"⚠ Revisar","OK")) -> Sin datos | G70: =IF(E70="⚠ Revisar","Se califican reglas complejas sin caracterizarlas; documentar condiciones y excepciones.","")
A71: V11 | B71: Reutilización alta (> 70%) respaldada por la evaluación de los activos (D6.03 ≥ 2). | E71: =IF(COUNT($F$80:$F$240)+COUNT(E14:E37)-COUNT(E34)=0,"Sin datos",IF(AND(N(E32)>0.7,OR(F151="N/A",AND(ISNUMBER(F151),F151<=1))),"⚠ Revisar","OK")) -> Sin datos | G71: =IF(E71="⚠ Revisar","El porcentaje de reuso no está respaldado por una evaluación de los activos.","")
A72: V12 | B72: Tecnología T1 respaldada por la evaluación de familiaridad (D7.04 ≥ 2). | E72: =IF(COUNT($F$80:$F$240)+COUNT(E14:E37)-COUNT(E34)=0,"Sin datos",IF(AND(LEFT(E33,2)="T1",AND(ISNUMBER(F160),F160<=1)),"⚠ Revisar","OK")) -> Sin datos | G72: =IF(E72="⚠ Revisar","Se declara tecnología conocida sin evaluar la experiencia del equipo por tecnología.","")
A73: V13 | B73: Con 4 o más comparables, sus datos están completos (D11.03 ≥ 2). | E73: =IF(COUNT($F$80:$F$240)+COUNT(E14:E37)-COUNT(E34)=0,"Sin datos",IF(AND(N(E37)>=4,AND(ISNUMBER(F195),F195<=1)),"⚠ Revisar","OK")) -> Sin datos | G73: =IF(E73="⚠ Revisar","Los comparables existen pero sus datos son incompletos; la evidencia real es menor.","")
A74: V14 | B74: Un alcance M3/M4 es coherente con una madurez de tamaño ≥ umbral núcleo. | E74: =IF(COUNT($F$80:$F$240)+COUNT(E14:E37)-COUNT(E34)=0,"Sin datos",IF(AND(E34>=5,F44<Parametros!$B$37),"⚠ Revisar","OK")) -> Sin datos | G74: =IF(E74="⚠ Revisar","El alcance se declara definido pero el tamaño no es medible; revisar D3 y D8.","")
A75: V15 | B75: Integración I3 con ambientes de prueba de terceros confirmados (D5.09 ≥ 2). | E75: =IF(COUNT($F$80:$F$240)+COUNT(E14:E37)-COUNT(E34)=0,"Sin datos",IF(AND(LEFT(G29,2)="I3",AND(ISNUMBER(F143),F143<=1)),"⚠ Revisar","OK")) -> Sin datos | G75: =IF(E75="⚠ Revisar","Integración de alta dificultad sin ambientes de prueba confirmados: alerta crítica para la planificación.","")
A78: PARTE B · EVALUACIÓN DE MADUREZ POR CRITERIO
A79: ID | B79: Dim. | C79: Subdimensión | D79: Criterio y pregunta de evaluación | E79: Peso | F79: Puntaje (0–3 / N/A) | G79: Evidencia / observaciones del evaluador | H79: Obtenido | I79: Máximo | J79: Hallazgo o comentario sugerido | K79: Índice de prioridad
A80: ="D1 · Tipo de desarrollo — Núcleo · peso "&TEXT(Parametros!$D$5,"0%")&" · 12 criterios" -> D1 · Tipo de desarrollo — Núcleo · peso 12% · 12 criterios
A81: D1.01 | B81: D1 | C81: Composición del cambio | D81: Composición del alcance cuantificada: ¿Se conoce qué porcentaje del alcance corresponde a crear, modificar, reemplazar/transformar o corregir software? | E81: =INDEX(Rubricas!$M$4:$M$112,MATCH(A81,Rubricas!$A$4:$A$112,0)) -> 3 | H81: =IF(ISNUMBER(F81),F81*E81,0) -> 0 | I81: =IF(F81="N/A",0,3*E81) -> 9 | J81: =IF(F81="","Sin evaluar (núcleo, cuenta como 0) – "&INDEX(Rubricas!$F$4:$F$112,MATCH(A81,Rubricas!$A$4:$A$112,0)),IF(F81="N/A","⚠ Este criterio no admite N/A: calificar de 0 a 3.",IF(F81<=1,INDEX(Rubricas!$O$4:$O$112,MATCH(A81,Rubricas!$A$4:$A$112,0)),IF(F81=2,"Por completar o validar – "&INDEX(Rubricas!$F$4:$F$112,MATCH(A81,Rubricas!$A$4:$A$112,0)),"")))) -> Sin evaluar (núcleo, cuenta como 0) – Composición del alcance cuantificada | K81: =IF(ISNUMBER(F81),IF(F81<3,(3-F81)*E81*VLOOKUP(B81,Parametros!$A$5:$D$15,4,0)*100+ROW()/100000,0),IF(F81="",3*E81*VLOOKUP(B81,Parametros!$A$5:$D$15,4,0)*100+ROW()/100000,0)) -> 108.00081
A82: D1.02 | B82: D1 | C82: Composición del cambio | D82: Tipo de desarrollo asignado y justificado: ¿El tipo de desarrollo (Nuevo, Enhancement/evolutivo, Modernización/redevelopment, Mantenimiento) está asignado según el componente predominante? | E82: =INDEX(Rubricas!$M$4:$M$112,MATCH(A82,Rubricas!$A$4:$A$112,0)) -> 3 | H82: =IF(ISNUMBER(F82),F82*E82,0) -> 0 | I82: =IF(F82="N/A",0,3*E82) -> 9 | J82: =IF(F82="","Sin evaluar (núcleo, cuenta como 0) – "&INDEX(Rubricas!$F$4:$F$112,MATCH(A82,Rubricas!$A$4:$A$112,0)),IF(F82="N/A","⚠ Este criterio no admite N/A: calificar de 0 a 3.",IF(F82<=1,INDEX(Rubricas!$O$4:$O$112,MATCH(A82,Rubricas!$A$4:$A$112,0)),IF(F82=2,"Por completar o validar – "&INDEX(Rubricas!$F$4:$F$112,MATCH(A82,Rubricas!$A$4:$A$112,0)),"")))) -> Sin evaluar (núcleo, cuenta como 0) – Tipo de desarrollo asignado y justificado | K82: =IF(ISNUMBER(F82),IF(F82<3,(3-F82)*E82*VLOOKUP(B82,Parametros!$A$5:$D$15,4,0)*100+ROW()/100000,0),IF(F82="",3*E82*VLOOKUP(B82,Parametros!$A$5:$D$15,4,0)*100+ROW()/100000,0)) -> 108.00082
A83: D1.03 | B83: D1 | C83: Línea base del activo | D83: Línea base funcional del sistema existente: ¿Existe inventario de las funcionalidades actuales del sistema que se modifica, reemplaza o mantiene? (Admite N/A) | E83: =INDEX(Rubricas!$M$4:$M$112,MATCH(A83,Rubricas!$A$4:$A$112,0)) -> 2 | H83: =IF(ISNUMBER(F83),F83*E83,0) -> 0 | I83: =IF(F83="N/A",0,3*E83) -> 6 | J83: =IF(F83="","Sin evaluar (núcleo, cuenta como 0) – "&INDEX(Rubricas!$F$4:$F$112,MATCH(A83,Rubricas!$A$4:$A$112,0)),IF(F83="N/A","",IF(F83<=1,INDEX(Rubricas!$O$4:$O$112,MATCH(A83,Rubricas!$A$4:$A$112,0)),IF(F83=2,"Por completar o validar – "&INDEX(Rubricas!$F$4:$F$112,MATCH(A83,Rubricas!$A$4:$A$112,0)),"")))) -> Sin evaluar (núcleo, cuenta como 0) – Línea base funcional del sistema existente | K83: =IF(ISNUMBER(F83),IF(F83<3,(3-F83)*E83*VLOOKUP(B83,Parametros!$A$5:$D$15,4,0)*100+ROW()/100000,0),IF(F83="",3*E83*VLOOKUP(B83,Parametros!$A$5:$D$15,4,0)*100+ROW()/100000,0)) -> 72.00083
A84: D1.04 | B84: D1 | C84: Composición del cambio | D84: Funcionalidades nuevas identificadas: ¿Se listan las funcionalidades que se agregan, desagregadas al nivel de proceso funcional? (Admite N/A) | E84: =INDEX(Rubricas!$M$4:$M$112,MATCH(A84,Rubricas!$A$4:$A$112,0)) -> 3 | H84: =IF(ISNUMBER(F84),F84*E84,0) -> 0 | I84: =IF(F84="N/A",0,3*E84) -> 9 | J84: =IF(F84="","Sin evaluar (núcleo, cuenta como 0) – "&INDEX(Rubricas!$F$4:$F$112,MATCH(A84,Rubricas!$A$4:$A$112,0)),IF(F84="N/A","",IF(F84<=1,INDEX(Rubricas!$O$4:$O$112,MATCH(A84,Rubricas!$A$4:$A$112,0)),IF(F84=2,"Por completar o validar – "&INDEX(Rubricas!$F$4:$F$112,MATCH(A84,Rubricas!$A$4:$A$112,0)),"")))) -> Sin evaluar (núcleo, cuenta como 0) – Funcionalidades nuevas identificadas | K84: =IF(ISNUMBER(F84),IF(F84<3,(3-F84)*E84*VLOOKUP(B84,Parametros!$A$5:$D$15,4,0)*100+ROW()/100000,0),IF(F84="",3*E84*VLOOKUP(B84,Parametros!$A$5:$D$15,4,0)*100+ROW()/100000,0)) -> 108.00084
A85: D1.05 | B85: D1 | C85: Composición del cambio | D85: Funcionalidades modificadas y naturaleza del cambio: Para cada funcionalidad existente que cambia, ¿se identifica qué datos que entran, salen, se consultan o se almacenan se agregan, modifican o eliminan? (Admite N/A) | E85: =INDEX(Rubricas!$M$4:$M$112,MATCH(A85,Rubricas!$A$4:$A$112,0)) -> 3 | H85: =IF(ISNUMBER(F85),F85*E85,0) -> 0 | I85: =IF(F85="N/A",0,3*E85) -> 9 | J85: =IF(F85="","Sin evaluar (núcleo, cuenta como 0) – "&INDEX(Rubricas!$F$4:$F$112,MATCH(A85,Rubricas!$A$4:$A$112,0)),IF(F85="N/A","",IF(F85<=1,INDEX(Rubricas!$O$4:$O$112,MATCH(A85,Rubricas!$A$4:$A$112,0)),IF(F85=2,"Por completar o validar – "&INDEX(Rubricas!$F$4:$F$112,MATCH(A85,Rubricas!$A$4:$A$112,0)),"")))) -> Sin evaluar (núcleo, cuenta como 0) – Funcionalidades modificadas y naturaleza del cambio | K85: =IF(ISNUMBER(F85),IF(F85<3,(3-F85)*E85*VLOOKUP(B85,Parametros!$A$5:$D$15,4,0)*100+ROW()/100000,0),IF(F85="",3*E85*VLOOKUP(B85,Parametros!$A$5:$D$15,4,0)*100+ROW()/100000,0)) -> 108.00085
A86: D1.06 | B86: D1 | C86: Composición del cambio | D86: Funcionalidades retiradas: ¿Se identifican funcionalidades, interfaces o datos que se eliminan o dan de baja (o se declara explícitamente que no existen)? (Admite N/A) | E86: =INDEX(Rubricas!$M$4:$M$112,MATCH(A86,Rubricas!$A$4:$A$112,0)) -> 1 | H86: =IF(ISNUMBER(F86),F86*E86,0) -> 0 | I86: =IF(F86="N/A",0,3*E86) -> 3 | J86: =IF(F86="","Sin evaluar (núcleo, cuenta como 0) – "&INDEX(Rubricas!$F$4:$F$112,MATCH(A86,Rubricas!$A$4:$A$112,0)),IF(F86="N/A","",IF(F86<=1,INDEX(Rubricas!$O$4:$O$112,MATCH(A86,Rubricas!$A$4:$A$112,0)),IF(F86=2,"Por completar o validar – "&INDEX(Rubricas!$F$4:$F$112,MATCH(A86,Rubricas!$A$4:$A$112,0)),"")))) -> Sin evaluar (núcleo, cuenta como 0) – Funcionalidades retiradas | K86: =IF(ISNUMBER(F86),IF(F86<3,(3-F86)*E86*VLOOKUP(B86,Parametros!$A$5:$D$15,4,0)*100+ROW()/100000,0),IF(F86="",3*E86*VLOOKUP(B86,Parametros!$A$5:$D$15,4,0)*100+ROW()/100000,0)) -> 36.00086
A87: D1.07 | B87: D1 | C87: Frontera y componentes | D87: Frontera del software definida: ¿Está claro qué software se construye o modifica (dentro del alcance) y qué sistemas, usuarios o componentes quedan fuera? | E87: =INDEX(Rubricas!$M$4:$M$112,MATCH(A87,Rubricas!$A$4:$A$112,0)) -> 3 | H87: =IF(ISNUMBER(F87),F87*E87,0) -> 0 | I87: =IF(F87="N/A",0,3*E87) -> 9 | J87: =IF(F87="","Sin evaluar (núcleo, cuenta como 0) – "&INDEX(Rubricas!$F$4:$F$112,MATCH(A87,Rubricas!$A$4:$A$112,0)),IF(F87="N/A","⚠ Este criterio no admite N/A: calificar de 0 a 3.",IF(F87<=1,INDEX(Rubricas!$O$4:$O$112,MATCH(A87,Rubricas!$A$4:$A$112,0)),IF(F87=2,"Por completar o validar – "&INDEX(Rubricas!$F$4:$F$112,MATCH(A87,Rubricas!$A$4:$A$112,0)),"")))) -> Sin evaluar (núcleo, cuenta como 0) – Frontera del software definida | K87: =IF(ISNUMBER(F87),IF(F87<3,(3-F87)*E87*VLOOKUP(B87,Parametros!$A$5:$D$15,4,0)*100+ROW()/100000,0),IF(F87="",3*E87*VLOOKUP(B87,Parametros!$A$5:$D$15,4,0)*100+ROW()/100000,0)) -> 108.00087
A88: D1.08 | B88: D1 | C88: Frontera y componentes | D88: Capas y componentes afectados: ¿Se identifican las capas (presentación, negocio, servicios, datos) y los componentes que se crean o modifican? | E88: =INDEX(Rubricas!$M$4:$M$112,MATCH(A88,Rubricas!$A$4:$A$112,0)) -> 2 | H88: =IF(ISNUMBER(F88),F88*E88,0) -> 0 | I88: =IF(F88="N/A",0,3*E88) -> 6 | J88: =IF(F88="","Sin evaluar (núcleo, cuenta como 0) – "&INDEX(Rubricas!$F$4:$F$112,MATCH(A88,Rubricas!$A$4:$A$112,0)),IF(F88="N/A","⚠ Este criterio no admite N/A: calificar de 0 a 3.",IF(F88<=1,INDEX(Rubricas!$O$4:$O$112,MATCH(A88,Rubricas!$A$4:$A$112,0)),IF(F88=2,"Por completar o validar – "&INDEX(Rubricas!$F$4:$F$112,MATCH(A88,Rubricas!$A$4:$A$112,0)),"")))) -> Sin evaluar (núcleo, cuenta como 0) – Capas y componentes afectados | K88: =IF(ISNUMBER(F88),IF(F88<3,(3-F88)*E88*VLOOKUP(B88,Parametros!$A$5:$D$15,4,0)*100+ROW()/100000,0),IF(F88="",3*E88*VLOOKUP(B88,Parametros!$A$5:$D$15,4,0)*100+ROW()/100000,0)) -> 72.00088
A89: D1.09 | B89: D1 | C89: Línea base del activo | D89: Documentación técnica y código del activo: ¿Están disponibles y actualizados el código fuente, la documentación técnica y los ambientes del sistema existente? (Admite N/A) | E89: =INDEX(Rubricas!$M$4:$M$112,MATCH(A89,Rubricas!$A$4:$A$112,0)) -> 2 | H89: =IF(ISNUMBER(F89),F89*E89,0) -> 0 | I89: =IF(F89="N/A",0,3*E89) -> 6 | J89: =IF(F89="","Sin evaluar (núcleo, cuenta como 0) – "&INDEX(Rubricas!$F$4:$F$112,MATCH(A89,Rubricas!$A$4:$A$112,0)),IF(F89="N/A","",IF(F89<=1,INDEX(Rubricas!$O$4:$O$112,MATCH(A89,Rubricas!$A$4:$A$112,0)),IF(F89=2,"Por completar o validar – "&INDEX(Rubricas!$F$4:$F$112,MATCH(A89,Rubricas!$A$4:$A$112,0)),"")))) -> Sin evaluar (núcleo, cuenta como 0) – Documentación técnica y código del activo | K89: =IF(ISNUMBER(F89),IF(F89<3,(3-F89)*E89*VLOOKUP(B89,Parametros!$A$5:$D$15,4,0)*100+ROW()/100000,0),IF(F89="",3*E89*VLOOKUP(B89,Parametros!$A$5:$D$15,4,0)*100+ROW()/100000,0)) -> 72.00089
A90: D1.10 | B90: D1 | C90: Impacto y regresión | D90: Alcance de regresión: ¿Se conocen las funcionalidades existentes que deben volver a probarse por efecto de los cambios? (Admite N/A) | E90: =INDEX(Rubricas!$M$4:$M$112,MATCH(A90,Rubricas!$A$4:$A$112,0)) -> 2 | H90: =IF(ISNUMBER(F90),F90*E90,0) -> 0 | I90: =IF(F90="N/A",0,3*E90) -> 6 | J90: =IF(F90="","Sin evaluar (núcleo, cuenta como 0) – "&INDEX(Rubricas!$F$4:$F$112,MATCH(A90,Rubricas!$A$4:$A$112,0)),IF(F90="N/A","",IF(F90<=1,INDEX(Rubricas!$O$4:$O$112,MATCH(A90,Rubricas!$A$4:$A$112,0)),IF(F90=2,"Por completar o validar – "&INDEX(Rubricas!$F$4:$F$112,MATCH(A90,Rubricas!$A$4:$A$112,0)),"")))) -> Sin evaluar (núcleo, cuenta como 0) – Alcance de regresión | K90: =IF(ISNUMBER(F90),IF(F90<3,(3-F90)*E90*VLOOKUP(B90,Parametros!$A$5:$D$15,4,0)*100+ROW()/100000,0),IF(F90="",3*E90*VLOOKUP(B90,Parametros!$A$5:$D$15,4,0)*100+ROW()/100000,0)) -> 72.0009
A91: D1.11 | B91: D1 | C91: Impacto y regresión | D91: Equivalencia funcional en modernización: Cuando se transforma un activo, ¿se define qué comportamiento debe preservarse y cómo se verificará la equivalencia? (Admite N/A) | E91: =INDEX(Rubricas!$M$4:$M$112,MATCH(A91,Rubricas!$A$4:$A$112,0)) -> 2 | H91: =IF(ISNUMBER(F91),F91*E91,0) -> 0 | I91: =IF(F91="N/A",0,3*E91) -> 6 | J91: =IF(F91="","Sin evaluar (núcleo, cuenta como 0) – "&INDEX(Rubricas!$F$4:$F$112,MATCH(A91,Rubricas!$A$4:$A$112,0)),IF(F91="N/A","",IF(F91<=1,INDEX(Rubricas!$O$4:$O$112,MATCH(A91,Rubricas!$A$4:$A$112,0)),IF(F91=2,"Por completar o validar – "&INDEX(Rubricas!$F$4:$F$112,MATCH(A91,Rubricas!$A$4:$A$112,0)),"")))) -> Sin evaluar (núcleo, cuenta como 0) – Equivalencia funcional en modernización | K91: =IF(ISNUMBER(F91),IF(F91<3,(3-F91)*E91*VLOOKUP(B91,Parametros!$A$5:$D$15,4,0)*100+ROW()/100000,0),IF(F91="",3*E91*VLOOKUP(B91,Parametros!$A$5:$D$15,4,0)*100+ROW()/100000,0)) -> 72.00091
A92: D1.12 | B92: D1 | C92: Composición del cambio | D92: Separación correctivo vs. evolutivo: ¿Se distinguen las correcciones de defectos de los cambios y nuevas funcionalidades? | E92: =INDEX(Rubricas!$M$4:$M$112,MATCH(A92,Rubricas!$A$4:$A$112,0)) -> 1 | H92: =IF(ISNUMBER(F92),F92*E92,0) -> 0 | I92: =IF(F92="N/A",0,3*E92) -> 3 | J92: =IF(F92="","Sin evaluar (núcleo, cuenta como 0) – "&INDEX(Rubricas!$F$4:$F$112,MATCH(A92,Rubricas!$A$4:$A$112,0)),IF(F92="N/A","⚠ Este criterio no admite N/A: calificar de 0 a 3.",IF(F92<=1,INDEX(Rubricas!$O$4:$O$112,MATCH(A92,Rubricas!$A$4:$A$112,0)),IF(F92=2,"Por completar o validar – "&INDEX(Rubricas!$F$4:$F$112,MATCH(A92,Rubricas!$A$4:$A$112,0)),"")))) -> Sin evaluar (núcleo, cuenta como 0) – Separación correctivo vs. evolutivo | K92: =IF(ISNUMBER(F92),IF(F92<3,(3-F92)*E92*VLOOKUP(B92,Parametros!$A$5:$D$15,4,0)*100+ROW()/100000,0),IF(F92="",3*E92*VLOOKUP(B92,Parametros!$A$5:$D$15,4,0)*100+ROW()/100000,0)) -> 36.00092
A93: ="D2 · Tipo de solución / arquetipo — Núcleo · peso "&TEXT(Parametros!$D$6,"0%")&" · 12 criterios" -> D2 · Tipo de solución / arquetipo — Núcleo · peso 11% · 12 criterios
A94: D2.01 | B94: D2 | C94: Objeto predominante | D94: Objeto tecnológico predominante: ¿Se identifica qué concentra el trabajo: funcionalidades y reglas, intercambio entre sistemas, datos/modelos, capacidades compartidas, controles/identidad o transformación de un activo existente? | E94: =INDEX(Rubricas!$M$4:$M$112,MATCH(A94,Rubricas!$A$4:$A$112,0)) -> 3 | H94: =IF(ISNUMBER(F94),F94*E94,0) -> 0 | I94: =IF(F94="N/A",0,3*E94) -> 9 | J94: =IF(F94="","Sin evaluar (núcleo, cuenta como 0) – "&INDEX(Rubricas!$F$4:$F$112,MATCH(A94,Rubricas!$A$4:$A$112,0)),IF(F94="N/A","⚠ Este criterio no admite N/A: calificar de 0 a 3.",IF(F94<=1,INDEX(Rubricas!$O$4:$O$112,MATCH(A94,Rubricas!$A$4:$A$112,0)),IF(F94=2,"Por completar o validar – "&INDEX(Rubricas!$F$4:$F$112,MATCH(A94,Rubricas!$A$4:$A$112,0)),"")))) -> Sin evaluar (núcleo, cuenta como 0) – Objeto tecnológico predominante | K94: =IF(ISNUMBER(F94),IF(F94<3,(3-F94)*E94*VLOOKUP(B94,Parametros!$A$5:$D$15,4,0)*100+ROW()/100000,0),IF(F94="",3*E94*VLOOKUP(B94,Parametros!$A$5:$D$15,4,0)*100+ROW()/100000,0)) -> 99.00094
A95: D2.02 | B95: D2 | C95: Objeto predominante | D95: Arquetipo principal según esfuerzo: ¿El arquetipo principal corresponde al trabajo que explica la mayor proporción del esfuerzo esperado, y no al componente más visible? | E95: =INDEX(Rubricas!$M$4:$M$112,MATCH(A95,Rubricas!$A$4:$A$112,0)) -> 3 | H95: =IF(ISNUMBER(F95),F95*E95,0) -> 0 | I95: =IF(F95="N/A",0,3*E95) -> 9 | J95: =IF(F95="","Sin evaluar (núcleo, cuenta como 0) – "&INDEX(Rubricas!$F$4:$F$112,MATCH(A95,Rubricas!$A$4:$A$112,0)),IF(F95="N/A","⚠ Este criterio no admite N/A: calificar de 0 a 3.",IF(F95<=1,INDEX(Rubricas!$O$4:$O$112,MATCH(A95,Rubricas!$A$4:$A$112,0)),IF(F95=2,"Por completar o validar – "&INDEX(Rubricas!$F$4:$F$112,MATCH(A95,Rubricas!$A$4:$A$112,0)),"")))) -> Sin evaluar (núcleo, cuenta como 0) – Arquetipo principal según esfuerzo | K95: =IF(ISNUMBER(F95),IF(F95<3,(3-F95)*E95*VLOOKUP(B95,Parametros!$A$5:$D$15,4,0)*100+ROW()/100000,0),IF(F95="",3*E95*VLOOKUP(B95,Parametros!$A$5:$D$15,4,0)*100+ROW()/100000,0)) -> 99.00095
A96: D2.03 | B96: D2 | C96: Distribución del esfuerzo | D96: Distribución del alcance por arquetipo: ¿Se estima qué porcentaje del alcance o esfuerzo corresponde a cada arquetipo? | E96: =INDEX(Rubricas!$M$4:$M$112,MATCH(A96,Rubricas!$A$4:$A$112,0)) -> 2 | H96: =IF(ISNUMBER(F96),F96*E96,0) -> 0 | I96: =IF(F96="N/A",0,3*E96) -> 6 | J96: =IF(F96="","Sin evaluar (núcleo, cuenta como 0) – "&INDEX(Rubricas!$F$4:$F$112,MATCH(A96,Rubricas!$A$4:$A$112,0)),IF(F96="N/A","⚠ Este criterio no admite N/A: calificar de 0 a 3.",IF(F96<=1,INDEX(Rubricas!$O$4:$O$112,MATCH(A96,Rubricas!$A$4:$A$112,0)),IF(F96=2,"Por completar o validar – "&INDEX(Rubricas!$F$4:$F$112,MATCH(A96,Rubricas!$A$4:$A$112,0)),"")))) -> Sin evaluar (núcleo, cuenta como 0) – Distribución del alcance por arquetipo | K96: =IF(ISNUMBER(F96),IF(F96<3,(3-F96)*E96*VLOOKUP(B96,Parametros!$A$5:$D$15,4,0)*100+ROW()/100000,0),IF(F96="",3*E96*VLOOKUP(B96,Parametros!$A$5:$D$15,4,0)*100+ROW()/100000,0)) -> 66.00096
A97: D2.04 | B97: D2 | C97: Distribución del esfuerzo | D97: Arquetipos secundarios: ¿Se registran los arquetipos secundarios cuando una parte significativa (≈ ≥15%) del alcance pertenece a otras categorías? | E97: =INDEX(Rubricas!$M$4:$M$112,MATCH(A97,Rubricas!$A$4:$A$112,0)) -> 2 | H97: =IF(ISNUMBER(F97),F97*E97,0) -> 0 | I97: =IF(F97="N/A",0,3*E97) -> 6 | J97: =IF(F97="","Sin evaluar (núcleo, cuenta como 0) – "&INDEX(Rubricas!$F$4:$F$112,MATCH(A97,Rubricas!$A$4:$A$112,0)),IF(F97="N/A","⚠ Este criterio no admite N/A: calificar de 0 a 3.",IF(F97<=1,INDEX(Rubricas!$O$4:$O$112,MATCH(A97,Rubricas!$A$4:$A$112,0)),IF(F97=2,"Por completar o validar – "&INDEX(Rubricas!$F$4:$F$112,MATCH(A97,Rubricas!$A$4:$A$112,0)),"")))) -> Sin evaluar (núcleo, cuenta como 0) – Arquetipos secundarios | K97: =IF(ISNUMBER(F97),IF(F97<3,(3-F97)*E97*VLOOKUP(B97,Parametros!$A$5:$D$15,4,0)*100+ROW()/100000,0),IF(F97="",3*E97*VLOOKUP(B97,Parametros!$A$5:$D$15,4,0)*100+ROW()/100000,0)) -> 66.00097
A98: D2.05 | B98: D2 | C98: Validación de la clasificación | D98: Independencia del nombre comercial: ¿La clasificación se contrastó contra el contenido real del alcance y no depende del nombre del proyecto? | E98: =INDEX(Rubricas!$M$4:$M$112,MATCH(A98,Rubricas!$A$4:$A$112,0)) -> 1 | H98: =IF(ISNUMBER(F98),F98*E98,0) -> 0 | I98: =IF(F98="N/A",0,3*E98) -> 3 | J98: =IF(F98="","Sin evaluar (núcleo, cuenta como 0) – "&INDEX(Rubricas!$F$4:$F$112,MATCH(A98,Rubricas!$A$4:$A$112,0)),IF(F98="N/A","⚠ Este criterio no admite N/A: calificar de 0 a 3.",IF(F98<=1,INDEX(Rubricas!$O$4:$O$112,MATCH(A98,Rubricas!$A$4:$A$112,0)),IF(F98=2,"Por completar o validar – "&INDEX(Rubricas!$F$4:$F$112,MATCH(A98,Rubricas!$A$4:$A$112,0)),"")))) -> Sin evaluar (núcleo, cuenta como 0) – Independencia del nombre comercial | K98: =IF(ISNUMBER(F98),IF(F98<3,(3-F98)*E98*VLOOKUP(B98,Parametros!$A$5:$D$15,4,0)*100+ROW()/100000,0),IF(F98="",3*E98*VLOOKUP(B98,Parametros!$A$5:$D$15,4,0)*100+ROW()/100000,0)) -> 33.00098
A99: D2.06 | B99: D2 | C99: Drivers de esfuerzo | D99: Drivers del arquetipo principal: ¿Se identifican y cuantifican los drivers típicos del arquetipo principal (p. ej. Aplicaciones: funcionalidades, reglas, roles, pantallas, flujos; Integración: interfaces, protocolos, transformaciones; Datos/IA: fuentes, volumen, calidad, modelos; Plataforma: ambientes, componentes, SLA; Seguridad: identidades, controles, certificados; Modernización: tamaño del activo, deuda técnica, datos a migrar)? | E99: =INDEX(Rubricas!$M$4:$M$112,MATCH(A99,Rubricas!$A$4:$A$112,0)) -> 3 | H99: =IF(ISNUMBER(F99),F99*E99,0) -> 0 | I99: =IF(F99="N/A",0,3*E99) -> 9 | J99: =IF(F99="","Sin evaluar (núcleo, cuenta como 0) – "&INDEX(Rubricas!$F$4:$F$112,MATCH(A99,Rubricas!$A$4:$A$112,0)),IF(F99="N/A","⚠ Este criterio no admite N/A: calificar de 0 a 3.",IF(F99<=1,INDEX(Rubricas!$O$4:$O$112,MATCH(A99,Rubricas!$A$4:$A$112,0)),IF(F99=2,"Por completar o validar – "&INDEX(Rubricas!$F$4:$F$112,MATCH(A99,Rubricas!$A$4:$A$112,0)),"")))) -> Sin evaluar (núcleo, cuenta como 0) – Drivers del arquetipo principal | K99: =IF(ISNUMBER(F99),IF(F99<3,(3-F99)*E99*VLOOKUP(B99,Parametros!$A$5:$D$15,4,0)*100+ROW()/100000,0),IF(F99="",3*E99*VLOOKUP(B99,Parametros!$A$5:$D$15,4,0)*100+ROW()/100000,0)) -> 99.00099
A100: D2.07 | B100: D2 | C100: Drivers de esfuerzo | D100: Drivers de arquetipos secundarios: ¿Se identifican y cuantifican los drivers de los arquetipos secundarios? (Admite N/A) | E100: =INDEX(Rubricas!$M$4:$M$112,MATCH(A100,Rubricas!$A$4:$A$112,0)) -> 2 | H100: =IF(ISNUMBER(F100),F100*E100,0) -> 0 | I100: =IF(F100="N/A",0,3*E100) -> 6 | J100: =IF(F100="","Sin evaluar (núcleo, cuenta como 0) – "&INDEX(Rubricas!$F$4:$F$112,MATCH(A100,Rubricas!$A$4:$A$112,0)),IF(F100="N/A","",IF(F100<=1,INDEX(Rubricas!$O$4:$O$112,MATCH(A100,Rubricas!$A$4:$A$112,0)),IF(F100=2,"Por completar o validar – "&INDEX(Rubricas!$F$4:$F$112,MATCH(A100,Rubricas!$A$4:$A$112,0)),"")))) -> Sin evaluar (núcleo, cuenta como 0) – Drivers de arquetipos secundarios | K100: =IF(ISNUMBER(F100),IF(F100<3,(3-F100)*E100*VLOOKUP(B100,Parametros!$A$5:$D$15,4,0)*100+ROW()/100000,0),IF(F100="",3*E100*VLOOKUP(B100,Parametros!$A$5:$D$15,4,0)*100+ROW()/100000,0)) -> 66.001
A101: D2.08 | B101: D2 | C101: Objeto predominante | D101: Tipo de usuario funcional predominante: ¿Se identifica quién intercambia datos con la solución (personas por rol, otros sistemas, dispositivos) y es coherente con el arquetipo (p. ej. en Integración predominan sistemas)? | E101: =INDEX(Rubricas!$M$4:$M$112,MATCH(A101,Rubricas!$A$4:$A$112,0)) -> 2 | H101: =IF(ISNUMBER(F101),F101*E101,0) -> 0 | I101: =IF(F101="N/A",0,3*E101) -> 6 | J101: =IF(F101="","Sin evaluar (núcleo, cuenta como 0) – "&INDEX(Rubricas!$F$4:$F$112,MATCH(A101,Rubricas!$A$4:$A$112,0)),IF(F101="N/A","⚠ Este criterio no admite N/A: calificar de 0 a 3.",IF(F101<=1,INDEX(Rubricas!$O$4:$O$112,MATCH(A101,Rubricas!$A$4:$A$112,0)),IF(F101=2,"Por completar o validar – "&INDEX(Rubricas!$F$4:$F$112,MATCH(A101,Rubricas!$A$4:$A$112,0)),"")))) -> Sin evaluar (núcleo, cuenta como 0) – Tipo de usuario funcional predominante | K101: =IF(ISNUMBER(F101),IF(F101<3,(3-F101)*E101*VLOOKUP(B101,Parametros!$A$5:$D$15,4,0)*100+ROW()/100000,0),IF(F101="",3*E101*VLOOKUP(B101,Parametros!$A$5:$D$15,4,0)*100+ROW()/100000,0)) -> 66.00101
A102: D2.09 | B102: D2 | C102: Distribución del esfuerzo | D102: Componentes de terceros / SaaS: ¿Se identifican productos de terceros, paquetes o SaaS y se distingue configuración de desarrollo a medida? (Admite N/A) | E102: =INDEX(Rubricas!$M$4:$M$112,MATCH(A102,Rubricas!$A$4:$A$112,0)) -> 2 | H102: =IF(ISNUMBER(F102),F102*E102,0) -> 0 | I102: =IF(F102="N/A",0,3*E102) -> 6 | J102: =IF(F102="","Sin evaluar (núcleo, cuenta como 0) – "&INDEX(Rubricas!$F$4:$F$112,MATCH(A102,Rubricas!$A$4:$A$112,0)),IF(F102="N/A","",IF(F102<=1,INDEX(Rubricas!$O$4:$O$112,MATCH(A102,Rubricas!$A$4:$A$112,0)),IF(F102=2,"Por completar o validar – "&INDEX(Rubricas!$F$4:$F$112,MATCH(A102,Rubricas!$A$4:$A$112,0)),"")))) -> Sin evaluar (núcleo, cuenta como 0) – Componentes de terceros / SaaS | K102: =IF(ISNUMBER(F102),IF(F102<3,(3-F102)*E102*VLOOKUP(B102,Parametros!$A$5:$D$15,4,0)*100+ROW()/100000,0),IF(F102="",3*E102*VLOOKUP(B102,Parametros!$A$5:$D$15,4,0)*100+ROW()/100000,0)) -> 66.00102
A103: D2.10 | B103: D2 | C103: Distribución del esfuerzo | D103: Entregables no software separados: ¿Se separan del alcance de software los entregables que no son funcionalidad (licencias, infraestructura, capacitación, migración manual, soporte, documentación)? | E103: =INDEX(Rubricas!$M$4:$M$112,MATCH(A103,Rubricas!$A$4:$A$112,0)) -> 1 | H103: =IF(ISNUMBER(F103),F103*E103,0) -> 0 | I103: =IF(F103="N/A",0,3*E103) -> 3 | J103: =IF(F103="","Sin evaluar (núcleo, cuenta como 0) – "&INDEX(Rubricas!$F$4:$F$112,MATCH(A103,Rubricas!$A$4:$A$112,0)),IF(F103="N/A","⚠ Este criterio no admite N/A: calificar de 0 a 3.",IF(F103<=1,INDEX(Rubricas!$O$4:$O$112,MATCH(A103,Rubricas!$A$4:$A$112,0)),IF(F103=2,"Por completar o validar – "&INDEX(Rubricas!$F$4:$F$112,MATCH(A103,Rubricas!$A$4:$A$112,0)),"")))) -> Sin evaluar (núcleo, cuenta como 0) – Entregables no software separados | K103: =IF(ISNUMBER(F103),IF(F103<3,(3-F103)*E103*VLOOKUP(B103,Parametros!$A$5:$D$15,4,0)*100+ROW()/100000,0),IF(F103="",3*E103*VLOOKUP(B103,Parametros!$A$5:$D$15,4,0)*100+ROW()/100000,0)) -> 33.00103
A104: D2.11 | B104: D2 | C104: Validación de la clasificación | D104: Resolución de solapamientos: Cuando el trabajo cae entre categorías (IA vs. Datos, DevOps vs. Plataforma, SaaS personalizado vs. Aplicación, middleware vs. Integración), ¿se aplicó la regla de consolidación del catálogo? (Admite N/A) | E104: =INDEX(Rubricas!$M$4:$M$112,MATCH(A104,Rubricas!$A$4:$A$112,0)) -> 1 | H104: =IF(ISNUMBER(F104),F104*E104,0) -> 0 | I104: =IF(F104="N/A",0,3*E104) -> 3 | J104: =IF(F104="","Sin evaluar (núcleo, cuenta como 0) – "&INDEX(Rubricas!$F$4:$F$112,MATCH(A104,Rubricas!$A$4:$A$112,0)),IF(F104="N/A","",IF(F104<=1,INDEX(Rubricas!$O$4:$O$112,MATCH(A104,Rubricas!$A$4:$A$112,0)),IF(F104=2,"Por completar o validar – "&INDEX(Rubricas!$F$4:$F$112,MATCH(A104,Rubricas!$A$4:$A$112,0)),"")))) -> Sin evaluar (núcleo, cuenta como 0) – Resolución de solapamientos | K104: =IF(ISNUMBER(F104),IF(F104<3,(3-F104)*E104*VLOOKUP(B104,Parametros!$A$5:$D$15,4,0)*100+ROW()/100000,0),IF(F104="",3*E104*VLOOKUP(B104,Parametros!$A$5:$D$15,4,0)*100+ROW()/100000,0)) -> 33.00104
A105: D2.12 | B105: D2 | C105: Validación de la clasificación | D105: Clasificación validada: ¿La clasificación fue revisada por al menos dos roles (p. ej. arquitecto y estimador) y registrada? | E105: =INDEX(Rubricas!$M$4:$M$112,MATCH(A105,Rubricas!$A$4:$A$112,0)) -> 1 | H105: =IF(ISNUMBER(F105),F105*E105,0) -> 0 | I105: =IF(F105="N/A",0,3*E105) -> 3 | J105: =IF(F105="","Sin evaluar (núcleo, cuenta como 0) – "&INDEX(Rubricas!$F$4:$F$112,MATCH(A105,Rubricas!$A$4:$A$112,0)),IF(F105="N/A","⚠ Este criterio no admite N/A: calificar de 0 a 3.",IF(F105<=1,INDEX(Rubricas!$O$4:$O$112,MATCH(A105,Rubricas!$A$4:$A$112,0)),IF(F105=2,"Por completar o validar – "&INDEX(Rubricas!$F$4:$F$112,MATCH(A105,Rubricas!$A$4:$A$112,0)),"")))) -> Sin evaluar (núcleo, cuenta como 0) – Clasificación validada | K105: =IF(ISNUMBER(F105),IF(F105<3,(3-F105)*E105*VLOOKUP(B105,Parametros!$A$5:$D$15,4,0)*100+ROW()/100000,0),IF(F105="",3*E105*VLOOKUP(B105,Parametros!$A$5:$D$15,4,0)*100+ROW()/100000,0)) -> 33.00105
A106: ="D3 · Tamaño funcional — Núcleo · peso "&TEXT(Parametros!$D$7,"0%")&" · 14 criterios" -> D3 · Tamaño funcional — Núcleo · peso 18% · 14 criterios
A107: D3.01 | B107: D3 | C107: Estrategia de medición | D107: Propósito y alcance de la medición: ¿Está definido para qué se mide (cotización/estimación), qué piezas de software y capas se incluyen y qué se excluye? | E107: =INDEX(Rubricas!$M$4:$M$112,MATCH(A107,Rubricas!$A$4:$A$112,0)) -> 3 | H107: =IF(ISNUMBER(F107),F107*E107,0) -> 0 | I107: =IF(F107="N/A",0,3*E107) -> 9 | J107: =IF(F107="","Sin evaluar (núcleo, cuenta como 0) – "&INDEX(Rubricas!$F$4:$F$112,MATCH(A107,Rubricas!$A$4:$A$112,0)),IF(F107="N/A","⚠ Este criterio no admite N/A: calificar de 0 a 3.",IF(F107<=1,INDEX(Rubricas!$O$4:$O$112,MATCH(A107,Rubricas!$A$4:$A$112,0)),IF(F107=2,"Por completar o validar – "&INDEX(Rubricas!$F$4:$F$112,MATCH(A107,Rubricas!$A$4:$A$112,0)),"")))) -> Sin evaluar (núcleo, cuenta como 0) – Propósito y alcance de la medición | K107: =IF(ISNUMBER(F107),IF(F107<3,(3-F107)*E107*VLOOKUP(B107,Parametros!$A$5:$D$15,4,0)*100+ROW()/100000,0),IF(F107="",3*E107*VLOOKUP(B107,Parametros!$A$5:$D$15,4,0)*100+ROW()/100000,0)) -> 162.00107
...

Sheet Ejemplo
A1: Ficha de evaluación de madurez para estimación — EJEMPLO ILUSTRATIVO
A2: Ingresar datos solo en celdas amarillas (texto azul). Puntajes de criterios: 0, 1, 2, 3 o N/A (solo si la rúbrica lo admite). Criterios núcleo sin calificar cuentan como 0. Una dimensión complementaria sin ningún criterio calificado se excluye del cálculo.
A4: Proyecto | D4: Portal de gestión y firma electrónica de contratos
A5: Cliente / área | D5: Entidad pública – Dirección de Contratación
A6: Evaluador(es) | D6: Arquitecto de soluciones + Líder de estimación
A7: Fecha de evaluación | D7: 2026-09-22
A8: Momento de estimación | D8: Propuesta comercial (preventa)
A9: Fuentes revisadas | D9: Documento de alcance v0.3, 2 talleres, backlog Jira (34 ítems)
A10: Versión de la ficha | D10: 1.0
A12: PARTE A · CARACTERIZACIÓN DEL PROYECTO (valores de clasificación del catálogo)
A13: Dimensión | D13: Variable | E13: Valor (ingresar) | G13: Clasificación resultante | H13: Regla aplicada
A14: D1 · Tipo de desarrollo | D14: % del alcance: nuevo desarrollo | E14: 0.75 | G14: =IF(SUM(E14:E17)=0,"Sin datos",INDEX(Parametros!$I$4:$I$7,MATCH(MAX(E14:E17),E14:E17,0))) -> Nuevo desarrollo | H14: Componente predominante (mayor %). Los cuatro porcentajes deben sumar 100%.
D15: % del alcance: enhancement / evolutivo | E15: 0.25 | G15: =IF(COUNT(E14:E17)=0,"",IF(ABS(SUM(E14:E17)-1)<0.001,"Composición suma 100%","⚠ La composición no suma 100%")) -> Composición suma 100%
D16: % del alcance: modernización / redevelopment | E16: 0
D17: % del alcance: mantenimiento (correctivo / menor) | E17: 0
A18: D2 · Tipo de solución / arquetipo | D18: Arquetipo principal | E18: Aplicaciones y soluciones digitales | G18: =IF(E18="","Sin asignar",E18) -> Aplicaciones y soluciones digitales | H18: Principal = trabajo que explica la mayor proporción del esfuerzo esperado, no el componente más visible.
D19: Arquetipos secundarios (texto) | E19: Seguridad, identidad y confianza digital; Integración e interoperabilidad
D20: % del esfuerzo del arquetipo principal | E20: 0.6 | G20: =IF(E20="","",IF(E20>=0.5,"Predominio claro","Predominio débil: revisar secundarios")) -> Predominio claro
A21: D3 · Tamaño funcional | D21: N° de procesos funcionales identificados | E21: 34 | G21: =IF(N(E21)=0,"Sin datos","Clase "&LOOKUP(E21,Parametros!$A$42:$A$46,Parametros!$B$42:$B$46)) -> Clase L | H21: XS 1–5 · S 6–15 · M 16–30 · L 31–60 · XL >60 procesos. Aproximación = procesos × promedio.
D22: Puntos de función promedio por proceso (vacío = referencia) | G22: =IF(N(E21)=0,"","≈ "&TEXT(E21*IF(N(E22)=0,Parametros!$B$49,E22),"0")&" PF (aproximación)") -> ≈ 272 PF (aproximación)
D23: Tamaño medido en puntos de función (si existe) | G23: =IF(N(E23)=0,"Sin medición detallada","Medido: "&E23&" PF") -> Sin medición detallada
A24: D4 · Complejidad | D24: Factor reglas de negocio (0 simples · 1 moderadas · 2 complejas) | E24: 1 | G24: =IF(COUNT(E24:E28)=0,"Sin datos","Puntaje "&SUM(E24:E28)&" / 10") -> Puntaje 7 / 10 | H24: Suma 0–10: 0–2 Baja · 3–5 Media · 6–8 Alta · 9–10 Muy alta.
D25: Factor arquitectura (0 conocida · 1 algunas novedades · 2 nueva/sofisticada) | E25: 1 | G25: =IF(COUNT(E24:E28)=0,"","Complejidad "&LOOKUP(SUM(E24:E28),Parametros!$A$53:$A$56,Parametros!$B$53:$B$56)) -> Complejidad Alta
D26: Factor seguridad (0 estándar · 1 elevada · 2 crítica) | E26: 2
D27: Factor procesamiento (0 simple · 1 medio · 2 complejo/tiempo real) | E27: 1
D28: Factor dependencias (0 pocas · 1 varias · 2 muchas/críticas) | E28: 2
A29: D5 · Integración | D29: N° de interfaces | E29: 4 | G29: =IF(E29="","Sin datos",IF(E29=0,"I0 - Sin interfaces",IF(OR(E29>5,E31="Sí"),"I3 - Alta",IF(OR(E29>=3,E30="Sí"),"I2 - Media","I1 - Baja")))) -> I2 - Media | H29: I0 sin interfaces · I1 1–2 simples · I2 3–5 o alguna compleja · I3 >5, críticos, protocolos no conocidos o múltiples terceros.
D30: ¿Alguna interfaz compleja? | E30: Sí
D31: ¿Sistemas críticos, protocolos no conocidos o múltiples terceros? | E31: No
A32: D6 · Reutilización | D32: % del alcance reutilizable | E32: 0.3 | G32: =IF(E32="","Sin datos",IF(E32>0.7,"R1 - Alta reutilización",IF(E32>=0.4,"R2 - Media",IF(E32>=0.1,"R3 - Baja","R4 - Nuevo")))) -> R3 - Baja | H32: R1 >70% · R2 40–70% · R3 10–40% · R4 <10%.
A33: D7 · Entorno tecnológico | D33: Familiaridad tecnológica del equipo | E33: T2 - Parcialmente conocida | G33: =IF(E33="","Sin datos",E33) -> T2 - Parcialmente conocida | H33: T1 Conocida · T2 Parcialmente conocida · T3 Nueva · T4 Experimental.
A34: D8 · Madurez del alcance | D34: Elementos del checklist con puntaje ≥ 2 (cálculo automático, D8.01–D8.08) | E34: =COUNTIF(F165:F172,">=2") -> 5 | G34: =IF(COUNT(F165:F172)=0,"Sin datos",IF(E34<=2,"M1 - Idea",IF(E34<=4,"M2 - Preliminar",IF(E34<=6,"M3 - Definido","M4 - Validado")))) -> M3 - Definido | H34: M1 0–2 · M2 3–4 · M3 5–6 · M4 7–8 elementos.
A35: D9 · Contexto de ejecución | D35: Condición del contexto de ejecución | E35: Parcialmente conocido | G35: =IF(E35="","Sin datos",E35) -> Parcialmente conocido | H35: Estable · Parcialmente conocido · Incierto.
A36: D10 · Sector | D36: Sector del cliente | E36: Gobierno | G36: =IF(E36="","Sin datos",E36) -> Gobierno | H36: Gobierno · Financiero · Salud · Comercio · Telecomunicaciones · Otros.
A37: D11 · Evidencia histórica | D37: N° de proyectos comparables | E37: 3 | G37: =IF(E37="","Sin datos",IF(E37<=1,"E1 - Muy baja",IF(E37<=3,"E2 - Baja",IF(E37<=7,"E3 - Media","E4 - Alta")))) -> E2 - Baja | H37: E1 0–1 · E2 2–3 · E3 4–7 · E4 ≥8 comparables.
A40: RESUMEN DE MADUREZ (cálculo automático)
A41: Dimensión | D41: Principal brecha identificada | E41: Peso | F41: Madurez | G41: Nivel | H41: Tipo | I41: Aporte a la madurez general | J41: ¿Incluida en el cálculo?
A42: D1 · Tipo de desarrollo | D42: =IF(MAX(K81:K92)=0,"Sin brechas relevantes",INDEX(J81:J92,MATCH(MAX(K81:K92),K81:K92,0))) -> No se detalla qué cambia en las funcionalidades existentes. En evolutivos el tamaño es la suma de movimientos de datos agregados, modificados y eliminados; identificarlos. | E42: =Parametros!D5 -> 0.12 | F42: =IF(SUMIF($B$80:$B$240,"D1",$I$80:$I$240)=0,0,SUMIF($B$80:$B$240,"D1",$H$80:$H$240)/SUMIF($B$80:$B$240,"D1",$I$80:$I$240)) -> 0.6 | G42: =IF(J42="No","No evaluada",INDEX(Parametros!$B$30:$B$34,MATCH(F42,Parametros!$A$30:$A$34,1))) -> N4 - Definido | H42: =Parametros!C5 -> Núcleo | I42: =IF(J42="No",0,E42*F42/SUMPRODUCT($E$42:$E$52*($J$42:$J$52="Sí"))) -> 0.072 | J42: ="Sí" -> Sí
A43: D2 · Tipo de solución / arquetipo | D43: =IF(MAX(K94:K105)=0,"Sin brechas relevantes",INDEX(J94:J105,MATCH(MAX(K94:K105),K94:K105,0))) -> Los drivers de los arquetipos secundarios no están cuantificados. | E43: =Parametros!D6 -> 0.11 | F43: =IF(SUMIF($B$80:$B$240,"D2",$I$80:$I$240)=0,0,SUMIF($B$80:$B$240,"D2",$H$80:$H$240)/SUMIF($B$80:$B$240,"D2",$I$80:$I$240)) -> 0.71014493 | G43: =IF(J43="No","No evaluada",INDEX(Parametros!$B$30:$B$34,MATCH(F43,Parametros!$A$30:$A$34,1))) -> N4 - Definido | H43: =Parametros!C6 -> Núcleo | I43: =IF(J43="No",0,E43*F43/SUMPRODUCT($E$42:$E$52*($J$42:$J$52="Sí"))) -> 0.078115942 | J43: ="Sí" -> Sí
A44: D3 · Tamaño funcional | D44: =IF(MAX(K107:K120)=0,"Sin brechas relevantes",INDEX(J107:J120,MATCH(MAX(K107:K120),K107:K120,0))) -> No se identifican los movimientos de datos (Entradas, Salidas, Lecturas, Escrituras); el tamaño queda como aproximación. Medir al menos una muestra representativa. | E44: =Parametros!D7 -> 0.18 | F44: =IF(SUMIF($B$80:$B$240,"D3",$I$80:$I$240)=0,0,SUMIF($B$80:$B$240,"D3",$H$80:$H$240)/SUMIF($B$80:$B$240,"D3",$I$80:$I$240)) -> 0.49462366 | G44: =IF(J44="No","No evaluada",INDEX(Parametros!$B$30:$B$34,MATCH(F44,Parametros!$A$30:$A$34,1))) -> N3 - Intermedio | H44: =Parametros!C7 -> Núcleo | I44: =IF(J44="No",0,E44*F44/SUMPRODUCT($E$42:$E$52*($J$42:$J$52="Sí"))) -> 0.089032258 | J44: ="Sí" -> Sí
A45: D4 · Complejidad | D45: =IF(MAX(K122:K133)=0,"Sin brechas relevantes",INDEX(J122:J133,MATCH(MAX(K122:K133),K122:K133,0))) -> Los requisitos de seguridad no están especificados ni clasificados. | E45: =Parametros!D8 -> 0.15 | F45: =IF(SUMIF($B$80:$B$240,"D4",$I$80:$I$240)=0,0,SUMIF($B$80:$B$240,"D4",$H$80:$H$240)/SUMIF($B$80:$B$240,"D4",$I$80:$I$240)) -> 0.58974359 | G45: =IF(J45="No","No evaluada",INDEX(Parametros!$B$30:$B$34,MATCH(F45,Parametros!$A$30:$A$34,1))) -> N3 - Intermedio | H45: =Parametros!C8 -> Núcleo | I45: =IF(J45="No",0,E45*F45/SUMPRODUCT($E$42:$E$52*($J$42:$J$52="Sí"))) -> 0.088461538 | J45: ="Sí" -> Sí
A46: D5 · Integración / interdependencia | D46: =IF(MAX(K135:K147)=0,"Sin brechas relevantes",INDEX(J135:J147,MATCH(MAX(K135:K147),K135:K147,0))) -> No está definido el manejo de errores (reintentos, idempotencia, conciliación). | E46: =Parametros!D9 -> 0.14 | F46: =IF(SUMIF($B$80:$B$240,"D5",$I$80:$I$240)=0,0,SUMIF($B$80:$B$240,"D5",$H$80:$H$240)/SUMIF($B$80:$B$240,"D5",$I$80:$I$240)) -> 0.51190476 | G46: =IF(J46="No","No evaluada",INDEX(Parametros!$B$30:$B$34,MATCH(F46,Parametros!$A$30:$A$34,1))) -> N3 - Intermedio | H46: =Parametros!C9 -> Núcleo | I46: =IF(J46="No",0,E46*F46/SUMPRODUCT($E$42:$E$52*($J$42:$J$52="Sí"))) -> 0.071666667 | J46: ="Sí" -> Sí
A47: D6 · Novedad y reutilización | D47: =IF(MAX(K149:K155)=0,"Sin brechas relevantes",INDEX(J149:J155,MATCH(MAX(K149:K155),K149:K155,0))) -> El reuso no está clasificado por funcionalidad; el porcentaje reutilizable es una suposición. | E47: =Parametros!D10 -> 0.05 | F47: =IF(SUMIF($B$80:$B$240,"D6",$I$80:$I$240)=0,0,SUMIF($B$80:$B$240,"D6",$H$80:$H$240)/SUMIF($B$80:$B$240,"D6",$I$80:$I$240)) -> 0.47222222 | G47: =IF(J47="No","No evaluada",INDEX(Parametros!$B$30:$B$34,MATCH(F47,Parametros!$A$30:$A$34,1))) -> N3 - Intermedio | H47: =Parametros!C10 -> Complementaria | I47: =IF(J47="No",0,E47*F47/SUMPRODUCT($E$42:$E$52*($J$42:$J$52="Sí"))) -> 0.023611111 | J47: =IF(SUMPRODUCT(($B$80:$B$240="D6")*ISNUMBER($F$80:$F$240))>0,"Sí","No") -> Sí
A48: D7 · Entorno tecnológico | D48: =IF(MAX(K157:K163)=0,"Sin brechas relevantes",INDEX(J157:J163,MATCH(MAX(K157:K163),K157:K163,0))) -> No se conocen las restricciones tecnológicas del cliente. | E48: =Parametros!D11 -> 0.05 | F48: =IF(SUMIF($B$80:$B$240,"D7",$I$80:$I$240)=0,0,SUMIF($B$80:$B$240,"D7",$H$80:$H$240)/SUMIF($B$80:$B$240,"D7",$I$80:$I$240)) -> 0.68888889 | G48: =IF(J48="No","No evaluada",INDEX(Parametros!$B$30:$B$34,MATCH(F48,Parametros!$A$30:$A$34,1))) -> N4 - Definido | H48: =Parametros!C11 -> Complementaria | I48: =IF(J48="No",0,E48*F48/SUMPRODUCT($E$42:$E$52*($J$42:$J$52="Sí"))) -> 0.034444444 | J48: =IF(SUMPRODUCT(($B$80:$B$240="D7")*ISNUMBER($F$80:$F$240))>0,"Sí","No") -> Sí
A49: D8 · Madurez del alcance | D49: =IF(MAX(K165:K175)=0,"Sin brechas relevantes",INDEX(J165:J175,MATCH(MAX(K165:K175),K165:K175,0))) -> No hay criterios de aceptación verificables; sin ellos el alcance de pruebas y la aceptación son inciertos. | E49: =Parametros!D12 -> 0.07 | F49: =IF(SUMIF($B$80:$B$240,"D8",$I$80:$I$240)=0,0,SUMIF($B$80:$B$240,"D8",$H$80:$H$240)/SUMIF($B$80:$B$240,"D8",$I$80:$I$240)) -> 0.56521739 | G49: =IF(J49="No","No evaluada",INDEX(Parametros!$B$30:$B$34,MATCH(F49,Parametros!$A$30:$A$34,1))) -> N3 - Intermedio | H49: =Parametros!C12 -> Complementaria | I49: =IF(J49="No",0,E49*F49/SUMPRODUCT($E$42:$E$52*($J$42:$J$52="Sí"))) -> 0.039565217 | J49: =IF(SUMPRODUCT(($B$80:$B$240="D8")*ISNUMBER($F$80:$F$240))>0,"Sí","No") -> Sí
A50: D9 · Contexto de ejecución | D50: =IF(MAX(K177:K184)=0,"Sin brechas relevantes",INDEX(J177:J184,MATCH(MAX(K177:K184),K177:K184,0))) -> No se conocen las dependencias externas de ejecución ni sus tiempos. | E50: =Parametros!D13 -> 0.05 | F50: =IF(SUMIF($B$80:$B$240,"D9",$I$80:$I$240)=0,0,SUMIF($B$80:$B$240,"D9",$H$80:$H$240)/SUMIF($B$80:$B$240,"D9",$I$80:$I$240)) -> 0.64583333 | G50: =IF(J50="No","No evaluada",INDEX(Parametros!$B$30:$B$34,MATCH(F50,Parametros!$A$30:$A$34,1))) -> N4 - Definido | H50: =Parametros!C13 -> Complementaria | I50: =IF(J50="No",0,E50*F50/SUMPRODUCT($E$42:$E$52*($J$42:$J$52="Sí"))) -> 0.032291667 | J50: =IF(SUMPRODUCT(($B$80:$B$240="D9")*ISNUMBER($F$80:$F$240))>0,"Sí","No") -> Sí
A51: D10 · Sector / contexto de negocio | D51: =IF(MAX(K186:K191)=0,"Sin brechas relevantes",INDEX(J186:J191,MATCH(MAX(K186:K191),K186:K191,0))) -> No se conocen los stakeholders ni el ciclo de aprobaciones. | E51: =Parametros!D14 -> 0.03 | F51: =IF(SUMIF($B$80:$B$240,"D10",$I$80:$I$240)=0,0,SUMIF($B$80:$B$240,"D10",$H$80:$H$240)/SUMIF($B$80:$B$240,"D10",$I$80:$I$240)) -> 0.60606061 | G51: =IF(J51="No","No evaluada",INDEX(Parametros!$B$30:$B$34,MATCH(F51,Parametros!$A$30:$A$34,1))) -> N4 - Definido | H51: =Parametros!C14 -> Complementaria | I51: =IF(J51="No",0,E51*F51/SUMPRODUCT($E$42:$E$52*($J$42:$J$52="Sí"))) -> 0.018181818 | J51: =IF(SUMPRODUCT(($B$80:$B$240="D10")*ISNUMBER($F$80:$F$240))>0,"Sí","No") -> Sí
A52: D11 · Evidencia histórica disponible | D52: =IF(MAX(K193:K199)=0,"Sin brechas relevantes",INDEX(J193:J199,MATCH(MAX(K193:K199),K193:K199,0))) -> El tamaño de los comparables no está normalizado. | E52: =Parametros!D15 -> 0.05 | F52: =IF(SUMIF($B$80:$B$240,"D11",$I$80:$I$240)=0,0,SUMIF($B$80:$B$240,"D11",$H$80:$H$240)/SUMIF($B$80:$B$240,"D11",$I$80:$I$240)) -> 0.39583333 | G52: =IF(J52="No","No evaluada",INDEX(Parametros!$B$30:$B$34,MATCH(F52,Parametros!$A$30:$A$34,1))) -> N2 - Preliminar | H52: =Parametros!C15 -> Complementaria | I52: =IF(J52="No",0,E52*F52/SUMPRODUCT($E$42:$E$52*($J$42:$J$52="Sí"))) -> 0.019791667 | J52: =IF(SUMPRODUCT(($B$80:$B$240="D11")*ISNUMBER($F$80:$F$240))>0,"Sí","No") -> Sí
A53: Madurez general ponderada | F53: =SUM(I42:I52) -> 0.56716233 | G53: =INDEX(Parametros!$B$30:$B$34,MATCH(F53,Parametros!$A$30:$A$34,1)) -> N3 - Intermedio | H53: Nivel según puntaje (antes de la regla de tope)
A54: Menor madurez entre dimensiones núcleo | F54: =MIN(F42:F46) -> 0.49462366 | G54: =IF(F54<Parametros!$B$37,"Aplica tope: nivel máximo "&INDEX(Parametros!$B$30:$B$34,Parametros!$B$38),"No aplica tope") -> No aplica tope
A55: NIVEL DE MADUREZ GENERAL (final) | F55: =MIN(MATCH(F53,Parametros!$A$30:$A$34,1),IF(F54<Parametros!$B$37,Parametros!$B$38,5)) -> 3 | G55: =IF(COUNT($F$80:$F$240)=0,"Sin evaluar",INDEX(Parametros!$B$30:$B$34,F55)) -> N3 - Intermedio
A56: Interpretación | D56: =IF(COUNT($F$80:$F$240)=0,"",INDEX(Parametros!$D$30:$D$34,F55)) -> Alcance principal conocido; faltan detalles relevantes.
A57: Técnica de estimación sugerida | D57: =IF(COUNT($F$80:$F$240)=0,"",INDEX(Parametros!$E$30:$E$34,F55)) -> Analogía con histórico + descomposición (WBS); estimación preliminar.
A59: VALIDACIONES DE CONSISTENCIA (cruce entre caracterización y criterios)
A60: ID | B60: Regla de consistencia | E60: Estado | G60: Acción sugerida si hay inconsistencia
A61: V1 | B61: Los porcentajes de composición del tipo de desarrollo suman 100%. | E61: =IF(COUNT($F$80:$F$240)+COUNT(E14:E37)-COUNT(E34)=0,"Sin datos",IF(AND(COUNT(E14:E17)>0,ABS(SUM(E14:E17)-1)>0.001),"⚠ Revisar","OK")) -> OK | G61: =IF(E61="⚠ Revisar","Ajustar los porcentajes de nuevo / evolutivo / modernización / mantenimiento para que sumen 100%.","")
A62: V2 | B62: Si hay componente evolutivo, de modernización o mantenimiento, existe línea base del activo (D1.03). | E62: =IF(COUNT($F$80:$F$240)+COUNT(E14:E37)-COUNT(E34)=0,"Sin datos",IF(AND(SUM(E15:E17)>0,OR(F83="N/A",AND(ISNUMBER(F83),F83<=1))),"⚠ Revisar","OK")) -> ⚠ Revisar | G62: =IF(E62="⚠ Revisar","Se modifica un activo existente sin línea base funcional: D1.03 no debería ser N/A ni ≤ 1.","") -> Se modifica un activo existente sin línea base funcional: D1.03 no debería ser N/A ni ≤ 1.
A63: V3 | B63: El arquetipo Modernización no convive con un tipo de desarrollo predominantemente nuevo. | E63: =IF(COUNT($F$80:$F$240)+COUNT(E14:E37)-COUNT(E34)=0,"Sin datos",IF(AND(E18="Modernización y migración",G14="Nuevo desarrollo"),"⚠ Revisar","OK")) -> OK | G63: =IF(E63="⚠ Revisar","Revisar el arquetipo o la composición del tipo de desarrollo.","")
A64: V4 | B64: El arquetipo principal Integración tiene al menos 3 interfaces. | E64: =IF(COUNT($F$80:$F$240)+COUNT(E14:E37)-COUNT(E34)=0,"Sin datos",IF(AND(E18="Integración e interoperabilidad",N(E29)<3),"⚠ Revisar","OK")) -> OK | G64: =IF(E64="⚠ Revisar","Con pocas interfaces el esfuerzo difícilmente se concentra en integración; revisar la clasificación.","")
A65: V5 | B65: Si se declara Integración (principal o secundario) se registra el N° de interfaces. | E65: =IF(COUNT($F$80:$F$240)+COUNT(E14:E37)-COUNT(E34)=0,"Sin datos",IF(AND(OR(E18="Integración e interoperabilidad",ISNUMBER(SEARCH("Integración",E19))),E29=""),"⚠ Revisar","OK")) -> OK | G65: =IF(E65="⚠ Revisar","Registrar el número de interfaces en la Parte A.","")
A66: V6 | B66: Las interfaces declaradas cuentan con inventario (D5.01 ≥ 2). | E66: =IF(COUNT($F$80:$F$240)+COUNT(E14:E37)-COUNT(E34)=0,"Sin datos",IF(AND(N(E29)>0,AND(ISNUMBER(F135),F135<=1)),"⚠ Revisar","OK")) -> OK | G66: =IF(E66="⚠ Revisar","Se declara un número de interfaces que no está respaldado por un inventario.","")
A67: V7 | B67: El N° de procesos funcionales está respaldado por inventario (D3.05 ≥ 2). | E67: =IF(COUNT($F$80:$F$240)+COUNT(E14:E37)-COUNT(E34)=0,"Sin datos",IF(AND(N(E21)>0,AND(ISNUMBER(F111),F111<=1)),"⚠ Revisar","OK")) -> OK | G67: =IF(E67="⚠ Revisar","El número de procesos registrado no tiene inventario que lo respalde; el tamaño es una suposición.","")
A68: V8 | B68: Si el inventario de procesos está calificado (D3.05 ≥ 2) se registra la cantidad. | E68: =IF(COUNT($F$80:$F$240)+COUNT(E14:E37)-COUNT(E34)=0,"Sin datos",IF(AND(ISNUMBER(F111),F111>=2,N(E21)=0),"⚠ Revisar","OK")) -> OK | G68: =IF(E68="⚠ Revisar","Registrar el N° de procesos funcionales en la Parte A para obtener la clase de tamaño.","")
A69: V9 | B69: Seguridad calificada como crítica (factor = 2) tiene requisitos especificados (D4.06 ≥ 2). | E69: =IF(COUNT($F$80:$F$240)+COUNT(E14:E37)-COUNT(E34)=0,"Sin datos",IF(AND(E26=2,AND(ISNUMBER(F127),F127<=1)),"⚠ Revisar","OK")) -> ⚠ Revisar | G69: =IF(E69="⚠ Revisar","Se califica la seguridad como crítica sin requisitos especificados; la complejidad no está sustentada.","") -> Se califica la seguridad como crítica sin requisitos especificados; la complejidad no está sustentada.
A70: V10 | B70: Reglas calificadas como complejas (factor = 2) están caracterizadas (D4.02 ≥ 2). | E70: =IF(COUNT($F$80:$F$240)+COUNT(E14:E37)-COUNT(E34)=0,"Sin datos",IF(AND(E24=2,AND(ISNUMBER(F123),F123<=1)),"⚠ Revisar","OK")) -> OK | G70: =IF(E70="⚠ Revisar","Se califican reglas complejas sin caracterizarlas; documentar condiciones y excepciones.","")
A71: V11 | B71: Reutilización alta (> 70%) respaldada por la evaluación de los activos (D6.03 ≥ 2). | E71: =IF(COUNT($F$80:$F$240)+COUNT(E14:E37)-COUNT(E34)=0,"Sin datos",IF(AND(N(E32)>0.7,OR(F151="N/A",AND(ISNUMBER(F151),F151<=1))),"⚠ Revisar","OK")) -> OK | G71: =IF(E71="⚠ Revisar","El porcentaje de reuso no está respaldado por una evaluación de los activos.","")
A72: V12 | B72: Tecnología T1 respaldada por la evaluación de familiaridad (D7.04 ≥ 2). | E72: =IF(COUNT($F$80:$F$240)+COUNT(E14:E37)-COUNT(E34)=0,"Sin datos",IF(AND(LEFT(E33,2)="T1",AND(ISNUMBER(F160),F160<=1)),"⚠ Revisar","OK")) -> OK | G72: =IF(E72="⚠ Revisar","Se declara tecnología conocida sin evaluar la experiencia del equipo por tecnología.","")
A73: V13 | B73: Con 4 o más comparables, sus datos están completos (D11.03 ≥ 2). | E73: =IF(COUNT($F$80:$F$240)+COUNT(E14:E37)-COUNT(E34)=0,"Sin datos",IF(AND(N(E37)>=4,AND(ISNUMBER(F195),F195<=1)),"⚠ Revisar","OK")) -> OK | G73: =IF(E73="⚠ Revisar","Los comparables existen pero sus datos son incompletos; la evidencia real es menor.","")
A74: V14 | B74: Un alcance M3/M4 es coherente con una madurez de tamaño ≥ umbral núcleo. | E74: =IF(COUNT($F$80:$F$240)+COUNT(E14:E37)-COUNT(E34)=0,"Sin datos",IF(AND(E34>=5,F44<Parametros!$B$37),"⚠ Revisar","OK")) -> OK | G74: =IF(E74="⚠ Revisar","El alcance se declara definido pero el tamaño no es medible; revisar D3 y D8.","")
A75: V15 | B75: Integración I3 con ambientes de prueba de terceros confirmados (D5.09 ≥ 2). | E75: =IF(COUNT($F$80:$F$240)+COUNT(E14:E37)-COUNT(E34)=0,"Sin datos",IF(AND(LEFT(G29,2)="I3",AND(ISNUMBER(F143),F143<=1)),"⚠ Revisar","OK")) -> OK | G75: =IF(E75="⚠ Revisar","Integración de alta dificultad sin ambientes de prueba confirmados: alerta crítica para la planificación.","")
A78: PARTE B · EVALUACIÓN DE MADUREZ POR CRITERIO
A79: ID | B79: Dim. | C79: Subdimensión | D79: Criterio y pregunta de evaluación | E79: Peso | F79: Puntaje (0–3 / N/A) | G79: Evidencia / observaciones del evaluador | H79: Obtenido | I79: Máximo | J79: Hallazgo o comentario sugerido | K79: Índice de prioridad
A80: ="D1 · Tipo de desarrollo — Núcleo · peso "&TEXT(Parametros!$D$5,"0%")&" · 12 criterios" -> D1 · Tipo de desarrollo — Núcleo · peso 12% · 12 criterios
A81: D1.01 | B81: D1 | C81: Composición del cambio | D81: Composición del alcance cuantificada: ¿Se conoce qué porcentaje del alcance corresponde a crear, modificar, reemplazar/transformar o corregir software? | E81: =INDEX(Rubricas!$M$4:$M$112,MATCH(A81,Rubricas!$A$4:$A$112,0)) -> 3 | F81: 2 | G81: 75% nuevo / 25% evolutivo según el líder técnico; no se clasificó cada funcionalidad. | H81: =IF(ISNUMBER(F81),F81*E81,0) -> 6 | I81: =IF(F81="N/A",0,3*E81) -> 9 | J81: =IF(F81="","Sin evaluar (núcleo, cuenta como 0) – "&INDEX(Rubricas!$F$4:$F$112,MATCH(A81,Rubricas!$A$4:$A$112,0)),IF(F81="N/A","⚠ Este criterio no admite N/A: calificar de 0 a 3.",IF(F81<=1,INDEX(Rubricas!$O$4:$O$112,MATCH(A81,Rubricas!$A$4:$A$112,0)),IF(F81=2,"Por completar o validar – "&INDEX(Rubricas!$F$4:$F$112,MATCH(A81,Rubricas!$A$4:$A$112,0)),"")))) -> Por completar o validar – Composición del alcance cuantificada | K81: =IF(ISNUMBER(F81),IF(F81<3,(3-F81)*E81*VLOOKUP(B81,Parametros!$A$5:$D$15,4,0)*100+ROW()/100000,0),IF(F81="",3*E81*VLOOKUP(B81,Parametros!$A$5:$D$15,4,0)*100+ROW()/100000,0)) -> 36.00081
A82: D1.02 | B82: D1 | C82: Composición del cambio | D82: Tipo de desarrollo asignado y justificado: ¿El tipo de desarrollo (Nuevo, Enhancement/evolutivo, Modernización/redevelopment, Mantenimiento) está asignado según el componente predominante? | E82: =INDEX(Rubricas!$M$4:$M$112,MATCH(A82,Rubricas!$A$4:$A$112,0)) -> 3 | F82: 3 | G82: Nuevo desarrollo (75%); componente evolutivo sobre el portal de proveedores. | H82: =IF(ISNUMBER(F82),F82*E82,0) -> 9 | I82: =IF(F82="N/A",0,3*E82) -> 9 | J82: =IF(F82="","Sin evaluar (núcleo, cuenta como 0) – "&INDEX(Rubricas!$F$4:$F$112,MATCH(A82,Rubricas!$A$4:$A$112,0)),IF(F82="N/A","⚠ Este criterio no admite N/A: calificar de 0 a 3.",IF(F82<=1,INDEX(Rubricas!$O$4:$O$112,MATCH(A82,Rubricas!$A$4:$A$112,0)),IF(F82=2,"Por completar o validar – "&INDEX(Rubricas!$F$4:$F$112,MATCH(A82,Rubricas!$A$4:$A$112,0)),"")))) | K82: =IF(ISNUMBER(F82),IF(F82<3,(3-F82)*E82*VLOOKUP(B82,Parametros!$A$5:$D$15,4,0)*100+ROW()/100000,0),IF(F82="",3*E82*VLOOKUP(B82,Parametros!$A$5:$D$15,4,0)*100+ROW()/100000,0)) -> 0
A83: D1.03 | B83: D1 | C83: Línea base del activo | D83: Línea base funcional del sistema existente: ¿Existe inventario de las funcionalidades actuales del sistema que se modifica, reemplaza o mantiene? (Admite N/A) | E83: =INDEX(Rubricas!$M$4:$M$112,MATCH(A83,Rubricas!$A$4:$A$112,0)) -> 2 | F83: 1 | G83: El portal de proveedores solo lo conoce el equipo del cliente; sin inventario funcional. | H83: =IF(ISNUMBER(F83),F83*E83,0) -> 2 | I83: =IF(F83="N/A",0,3*E83) -> 6 | J83: =IF(F83="","Sin evaluar (núcleo, cuenta como 0) – "&INDEX(Rubricas!$F$4:$F$112,MATCH(A83,Rubricas!$A$4:$A$112,0)),IF(F83="N/A","",IF(F83<=1,INDEX(Rubricas!$O$4:$O$112,MATCH(A83,Rubricas!$A$4:$A$112,0)),IF(F83=2,"Por completar o validar – "&INDEX(Rubricas!$F$4:$F$112,MATCH(A83,Rubricas!$A$4:$A$112,0)),"")))) -> No hay línea base funcional del activo existente; sin ella no puede medirse el tamaño del cambio ni el alcance de regresión. Levantar el inventario de funcionalidades actuales. | K83: =IF(ISNUMBER(F83),IF(F83<3,(3-F83)*E83*VLOOKUP(B83,Parametros!$A$5:$D$15,4,0)*100+ROW()/100000,0),IF(F83="",3*E83*VLOOKUP(B83,Parametros!$A$5:$D$15,4,0)*100+ROW()/100000,0)) -> 48.00083
A84: D1.04 | B84: D1 | C84: Composición del cambio | D84: Funcionalidades nuevas identificadas: ¿Se listan las funcionalidades que se agregan, desagregadas al nivel de proceso funcional? (Admite N/A) | E84: =INDEX(Rubricas!$M$4:$M$112,MATCH(A84,Rubricas!$A$4:$A$112,0)) -> 3 | F84: 2 | G84: 26 funcionalidades nuevas en backlog; algunas siguen como épicas («Gestión de contratos»). | H84: =IF(ISNUMBER(F84),F84*E84,0) -> 6 | I84: =IF(F84="N/A",0,3*E84) -> 9 | J84: =IF(F84="","Sin evaluar (núcleo, cuenta como 0) – "&INDEX(Rubricas!$F$4:$F$112,MATCH(A84,Rubricas!$A$4:$A$112,0)),IF(F84="N/A","",IF(F84<=1,INDEX(Rubricas!$O$4:$O$112,MATCH(A84,Rubricas!$A$4:$A$112,0)),IF(F84=2,"Por completar o validar – "&INDEX(Rubricas!$F$4:$F$112,MATCH(A84,Rubricas!$A$4:$A$112,0)),"")))) -> Por completar o validar – Funcionalidades nuevas identificadas | K84: =IF(ISNUMBER(F84),IF(F84<3,(3-F84)*E84*VLOOKUP(B84,Parametros!$A$5:$D$15,4,0)*100+ROW()/100000,0),IF(F84="",3*E84*VLOOKUP(B84,Parametros!$A$5:$D$15,4,0)*100+ROW()/100000,0)) -> 36.00084
A85: D1.05 | B85: D1 | C85: Composición del cambio | D85: Funcionalidades modificadas y naturaleza del cambio: Para cada funcionalidad existente que cambia, ¿se identifica qué datos que entran, salen, se consultan o se almacenan se agregan, modifican o eliminan? (Admite N/A) | E85: =INDEX(Rubricas!$M$4:$M$112,MATCH(A85,Rubricas!$A$4:$A$112,0)) -> 3 | F85: 1 | G85: Cambian registro y consulta de proveedores; no se detallan los datos afectados. | H85: =IF(ISNUMBER(F85),F85*E85,0) -> 3 | I85: =IF(F85="N/A",0,3*E85) -> 9 | J85: =IF(F85="","Sin evaluar (núcleo, cuenta como 0) – "&INDEX(Rubricas!$F$4:$F$112,MATCH(A85,Rubricas!$A$4:$A$112,0)),IF(F85="N/A","",IF(F85<=1,INDEX(Rubricas!$O$4:$O$112,MATCH(A85,Rubricas!$A$4:$A$112,0)),IF(F85=2,"Por completar o validar – "&INDEX(Rubricas!$F$4:$F$112,MATCH(A85,Rubricas!$A$4:$A$112,0)),"")))) -> No se detalla qué cambia en las funcionalidades existentes. En evolutivos el tamaño es la suma de movimientos de datos agregados, modificados y eliminados; identificarlos. | K85: =IF(ISNUMBER(F85),IF(F85<3,(3-F85)*E85*VLOOKUP(B85,Parametros!$A$5:$D$15,4,0)*100+ROW()/100000,0),IF(F85="",3*E85*VLOOKUP(B85,Parametros!$A$5:$D$15,4,0)*100+ROW()/100000,0)) -> 72.00085
A86: D1.06 | B86: D1 | C86: Composición del cambio | D86: Funcionalidades retiradas: ¿Se identifican funcionalidades, interfaces o datos que se eliminan o dan de baja (o se declara explícitamente que no existen)? (Admite N/A) | E86: =INDEX(Rubricas!$M$4:$M$112,MATCH(A86,Rubricas!$A$4:$A$112,0)) -> 1 | F86: 2 | G86: Se indica verbalmente que no hay retiros; sin confirmación formal. | H86: =IF(ISNUMBER(F86),F86*E86,0) -> 2 | I86: =IF(F86="N/A",0,3*E86) -> 3 | J86: =IF(F86="","Sin evaluar (núcleo, cuenta como 0) – "&INDEX(Rubricas!$F$4:$F$112,MATCH(A86,Rubricas!$A$4:$A$112,0)),IF(F86="N/A","",IF(F86<=1,INDEX(Rubricas!$O$4:$O$112,MATCH(A86,Rubricas!$A$4:$A$112,0)),IF(F86=2,"Por completar o validar – "&INDEX(Rubricas!$F$4:$F$112,MATCH(A86,Rubricas!$A$4:$A$112,0)),"")))) -> Por completar o validar – Funcionalidades retiradas | K86: =IF(ISNUMBER(F86),IF(F86<3,(3-F86)*E86*VLOOKUP(B86,Parametros!$A$5:$D$15,4,0)*100+ROW()/100000,0),IF(F86="",3*E86*VLOOKUP(B86,Parametros!$A$5:$D$15,4,0)*100+ROW()/100000,0)) -> 12.00086
A87: D1.07 | B87: D1 | C87: Frontera y componentes | D87: Frontera del software definida: ¿Está claro qué software se construye o modifica (dentro del alcance) y qué sistemas, usuarios o componentes quedan fuera? | E87: =INDEX(Rubricas!$M$4:$M$112,MATCH(A87,Rubricas!$A$4:$A$112,0)) -> 3 | F87: 2 | G87: Diagrama de contexto borrador: portal, 3 sistemas de la entidad y proveedor de firma. | H87: =IF(ISNUMBER(F87),F87*E87,0) -> 6 | I87: =IF(F87="N/A",0,3*E87) -> 9 | J87: =IF(F87="","Sin evaluar (núcleo, cuenta como 0) – "&INDEX(Rubricas!$F$4:$F$112,MATCH(A87,Rubricas!$A$4:$A$112,0)),IF(F87="N/A","⚠ Este criterio no admite N/A: calificar de 0 a 3.",IF(F87<=1,INDEX(Rubricas!$O$4:$O$112,MATCH(A87,Rubricas!$A$4:$A$112,0)),IF(F87=2,"Por completar o validar – "&INDEX(Rubricas!$F$4:$F$112,MATCH(A87,Rubricas!$A$4:$A$112,0)),"")))) -> Por completar o validar – Frontera del software definida | K87: =IF(ISNUMBER(F87),IF(F87<3,(3-F87)*E87*VLOOKUP(B87,Parametros!$A$5:$D$15,4,0)*100+ROW()/100000,0),IF(F87="",3*E87*VLOOKUP(B87,Parametros!$A$5:$D$15,4,0)*100+ROW()/100000,0)) -> 36.00087
A88: D1.08 | B88: D1 | C88: Frontera y componentes | D88: Capas y componentes afectados: ¿Se identifican las capas (presentación, negocio, servicios, datos) y los componentes que se crean o modifican? | E88: =INDEX(Rubricas!$M$4:$M$112,MATCH(A88,Rubricas!$A$4:$A$112,0)) -> 2 | F88: 2 | G88: Frontend web, API de negocio y BD identificados; no se marca nuevo vs. modificado. | H88: =IF(ISNUMBER(F88),F88*E88,0) -> 4 | I88: =IF(F88="N/A",0,3*E88) -> 6 | J88: =IF(F88="","Sin evaluar (núcleo, cuenta como 0) – "&INDEX(Rubricas!$F$4:$F$112,MATCH(A88,Rubricas!$A$4:$A$112,0)),IF(F88="N/A","⚠ Este criterio no admite N/A: calificar de 0 a 3.",IF(F88<=1,INDEX(Rubricas!$O$4:$O$112,MATCH(A88,Rubricas!$A$4:$A$112,0)),IF(F88=2,"Por completar o validar – "&INDEX(Rubricas!$F$4:$F$112,MATCH(A88,Rubricas!$A$4:$A$112,0)),"")))) -> Por completar o validar – Capas y componentes afectados | K88: =IF(ISNUMBER(F88),IF(F88<3,(3-F88)*E88*VLOOKUP(B88,Parametros!$A$5:$D$15,4,0)*100+ROW()/100000,0),IF(F88="",3*E88*VLOOKUP(B88,Parametros!$A$5:$D$15,4,0)*100+ROW()/100000,0)) -> 24.00088
A89: D1.09 | B89: D1 | C89: Línea base del activo | D89: Documentación técnica y código del activo: ¿Están disponibles y actualizados el código fuente, la documentación técnica y los ambientes del sistema existente? (Admite N/A) | E89: =INDEX(Rubricas!$M$4:$M$112,MATCH(A89,Rubricas!$A$4:$A$112,0)) -> 2 | F89: 1 | G89: Acceso al repositorio del portal de proveedores no confirmado. | H89: =IF(ISNUMBER(F89),F89*E89,0) -> 2 | I89: =IF(F89="N/A",0,3*E89) -> 6 | J89: =IF(F89="","Sin evaluar (núcleo, cuenta como 0) – "&INDEX(Rubricas!$F$4:$F$112,MATCH(A89,Rubricas!$A$4:$A$112,0)),IF(F89="N/A","",IF(F89<=1,INDEX(Rubricas!$O$4:$O$112,MATCH(A89,Rubricas!$A$4:$A$112,0)),IF(F89=2,"Por completar o validar – "&INDEX(Rubricas!$F$4:$F$112,MATCH(A89,Rubricas!$A$4:$A$112,0)),"")))) -> No se confirma acceso ni estado del código/documentación del activo existente; aumenta el esfuerzo de análisis. Solicitar acceso y evaluar su estado. | K89: =IF(ISNUMBER(F89),IF(F89<3,(3-F89)*E89*VLOOKUP(B89,Parametros!$A$5:$D$15,4,0)*100+ROW()/100000,0),IF(F89="",3*E89*VLOOKUP(B89,Parametros!$A$5:$D$15,4,0)*100+ROW()/100000,0)) -> 48.00089
A90: D1.10 | B90: D1 | C90: Impacto y regresión | D90: Alcance de regresión: ¿Se conocen las funcionalidades existentes que deben volver a probarse por efecto de los cambios? (Admite N/A) | E90: =INDEX(Rubricas!$M$4:$M$112,MATCH(A90,Rubricas!$A$4:$A$112,0)) -> 2 | F90: 1 | G90: Se reconoce regresión en el portal de proveedores sin casos identificados. | H90: =IF(ISNUMBER(F90),F90*E90,0) -> 2 | I90: =IF(F90="N/A",0,3*E90) -> 6 | J90: =IF(F90="","Sin evaluar (núcleo, cuenta como 0) – "&INDEX(Rubricas!$F$4:$F$112,MATCH(A90,Rubricas!$A$4:$A$112,0)),IF(F90="N/A","",IF(F90<=1,INDEX(Rubricas!$O$4:$O$112,MATCH(A90,Rubricas!$A$4:$A$112,0)),IF(F90=2,"Por completar o validar – "&INDEX(Rubricas!$F$4:$F$112,MATCH(A90,Rubricas!$A$4:$A$112,0)),"")))) -> No está definido el alcance de regresión; en evolutivos y modernizaciones es un driver de esfuerzo relevante. | K90: =IF(ISNUMBER(F90),IF(F90<3,(3-F90)*E90*VLOOKUP(B90,Parametros!$A$5:$D$15,4,0)*100+ROW()/100000,0),IF(F90="",3*E90*VLOOKUP(B90,Parametros!$A$5:$D$15,4,0)*100+ROW()/100000,0)) -> 48.0009
A91: D1.11 | B91: D1 | C91: Impacto y regresión | D91: Equivalencia funcional en modernización: Cuando se transforma un activo, ¿se define qué comportamiento debe preservarse y cómo se verificará la equivalencia? (Admite N/A) | E91: =INDEX(Rubricas!$M$4:$M$112,MATCH(A91,Rubricas!$A$4:$A$112,0)) -> 2 | F91: N/A | G91: No es un proyecto de modernización. | H91: =IF(ISNUMBER(F91),F91*E91,0) -> 0 | I91: =IF(F91="N/A",0,3*E91) -> 0 | J91: =IF(F91="","Sin evaluar (núcleo, cuenta como 0) – "&INDEX(Rubricas!$F$4:$F$112,MATCH(A91,Rubricas!$A$4:$A$112,0)),IF(F91="N/A","",IF(F91<=1,INDEX(Rubricas!$O$4:$O$112,MATCH(A91,Rubricas!$A$4:$A$112,0)),IF(F91=2,"Por completar o validar – "&INDEX(Rubricas!$F$4:$F$112,MATCH(A91,Rubricas!$A$4:$A$112,0)),"")))) | K91: =IF(ISNUMBER(F91),IF(F91<3,(3-F91)*E91*VLOOKUP(B91,Parametros!$A$5:$D$15,4,0)*100+ROW()/100000,0),IF(F91="",3*E91*VLOOKUP(B91,Parametros!$A$5:$D$15,4,0)*100+ROW()/100000,0)) -> 0
A92: D1.12 | B92: D1 | C92: Composición del cambio | D92: Separación correctivo vs. evolutivo: ¿Se distinguen las correcciones de defectos de los cambios y nuevas funcionalidades? | E92: =INDEX(Rubricas!$M$4:$M$112,MATCH(A92,Rubricas!$A$4:$A$112,0)) -> 1 | F92: 3 | G92: Backlog clasificado en Jira (historia / defecto). | H92: =IF(ISNUMBER(F92),F92*E92,0) -> 3 | I92: =IF(F92="N/A",0,3*E92) -> 3 | J92: =IF(F92="","Sin evaluar (núcleo, cuenta como 0) – "&INDEX(Rubricas!$F$4:$F$112,MATCH(A92,Rubricas!$A$4:$A$112,0)),IF(F92="N/A","⚠ Este criterio no admite N/A: calificar de 0 a 3.",IF(F92<=1,INDEX(Rubricas!$O$4:$O$112,MATCH(A92,Rubricas!$A$4:$A$112,0)),IF(F92=2,"Por completar o validar – "&INDEX(Rubricas!$F$4:$F$112,MATCH(A92,Rubricas!$A$4:$A$112,0)),"")))) | K92: =IF(ISNUMBER(F92),IF(F92<3,(3-F92)*E92*VLOOKUP(B92,Parametros!$A$5:$D$15,4,0)*100+ROW()/100000,0),IF(F92="",3*E92*VLOOKUP(B92,Parametros!$A$5:$D$15,4,0)*100+ROW()/100000,0)) -> 0
A93: ="D2 · Tipo de solución / arquetipo — Núcleo · peso "&TEXT(Parametros!$D$6,"0%")&" · 12 criterios" -> D2 · Tipo de solución / arquetipo — Núcleo · peso 11% · 12 criterios
A94: D2.01 | B94: D2 | C94: Objeto predominante | D94: Objeto tecnológico predominante: ¿Se identifica qué concentra el trabajo: funcionalidades y reglas, intercambio entre sistemas, datos/modelos, capacidades compartidas, controles/identidad o transformación de un activo existente? | E94: =INDEX(Rubricas!$M$4:$M$112,MATCH(A94,Rubricas!$A$4:$A$112,0)) -> 3 | F94: 3 | G94: Predominan flujos de gestión contractual, aprobaciones y pantallas. | H94: =IF(ISNUMBER(F94),F94*E94,0) -> 9 | I94: =IF(F94="N/A",0,3*E94) -> 9 | J94: =IF(F94="","Sin evaluar (núcleo, cuenta como 0) – "&INDEX(Rubricas!$F$4:$F$112,MATCH(A94,Rubricas!$A$4:$A$112,0)),IF(F94="N/A","⚠ Este criterio no admite N/A: calificar de 0 a 3.",IF(F94<=1,INDEX(Rubricas!$O$4:$O$112,MATCH(A94,Rubricas!$A$4:$A$112,0)),IF(F94=2,"Por completar o validar – "&INDEX(Rubricas!$F$4:$F$112,MATCH(A94,Rubricas!$A$4:$A$112,0)),"")))) | K94: =IF(ISNUMBER(F94),IF(F94<3,(3-F94)*E94*VLOOKUP(B94,Parametros!$A$5:$D$15,4,0)*100+ROW()/100000,0),IF(F94="",3*E94*VLOOKUP(B94,Parametros!$A$5:$D$15,4,0)*100+ROW()/100000,0)) -> 0
A95: D2.02 | B95: D2 | C95: Objeto predominante | D95: Arquetipo principal según esfuerzo: ¿El arquetipo principal corresponde al trabajo que explica la mayor proporción del esfuerzo esperado, y no al componente más visible? | E95: =INDEX(Rubricas!$M$4:$M$112,MATCH(A95,Rubricas!$A$4:$A$112,0)) -> 3 | F95: 2 | G95: Aplicaciones por esfuerzo; justificación cualitativa. | H95: =IF(ISNUMBER(F95),F95*E95,0) -> 6 | I95: =IF(F95="N/A",0,3*E95) -> 9 | J95: =IF(F95="","Sin evaluar (núcleo, cuenta como 0) – "&INDEX(Rubricas!$F$4:$F$112,MATCH(A95,Rubricas!$A$4:$A$112,0)),IF(F95="N/A","⚠ Este criterio no admite N/A: calificar de 0 a 3.",IF(F95<=1,INDEX(Rubricas!$O$4:$O$112,MATCH(A95,Rubricas!$A$4:$A$112,0)),IF(F95=2,"Por completar o validar – "&INDEX(Rubricas!$F$4:$F$112,MATCH(A95,Rubricas!$A$4:$A$112,0)),"")))) -> Por completar o validar – Arquetipo principal según esfuerzo | K95: =IF(ISNUMBER(F95),IF(F95<3,(3-F95)*E95*VLOOKUP(B95,Parametros!$A$5:$D$15,4,0)*100+ROW()/100000,0),IF(F95="",3*E95*VLOOKUP(B95,Parametros!$A$5:$D$15,4,0)*100+ROW()/100000,0)) -> 33.00095
A96: D2.03 | B96: D2 | C96: Distribución del esfuerzo | D96: Distribución del alcance por arquetipo: ¿Se estima qué porcentaje del alcance o esfuerzo corresponde a cada arquetipo? | E96: =INDEX(Rubricas!$M$4:$M$112,MATCH(A96,Rubricas!$A$4:$A$112,0)) -> 2 | F96: 2 | G96: Aproximado: 60% aplicación, 25% integración, 15% seguridad. | H96: =IF(ISNUMBER(F96),F96*E96,0) -> 4 | I96: =IF(F96="N/A",0,3*E96) -> 6 | J96: =IF(F96="","Sin evaluar (núcleo, cuenta como 0) – "&INDEX(Rubricas!$F$4:$F$112,MATCH(A96,Rubricas!$A$4:$A$112,0)),IF(F96="N/A","⚠ Este criterio no admite N/A: calificar de 0 a 3.",IF(F96<=1,INDEX(Rubricas!$O$4:$O$112,MATCH(A96,Rubricas!$A$4:$A$112,0)),IF(F96=2,"Por completar o validar – "&INDEX(Rubricas!$F$4:$F$112,MATCH(A96,Rubricas!$A$4:$A$112,0)),"")))) -> Por completar o validar – Distribución del alcance por arquetipo | K96: =IF(ISNUMBER(F96),IF(F96<3,(3-F96)*E96*VLOOKUP(B96,Parametros!$A$5:$D$15,4,0)*100+ROW()/100000,0),IF(F96="",3*E96*VLOOKUP(B96,Parametros!$A$5:$D$15,4,0)*100+ROW()/100000,0)) -> 22.00096
A97: D2.04 | B97: D2 | C97: Distribución del esfuerzo | D97: Arquetipos secundarios: ¿Se registran los arquetipos secundarios cuando una parte significativa (≈ ≥15%) del alcance pertenece a otras categorías? | E97: =INDEX(Rubricas!$M$4:$M$112,MATCH(A97,Rubricas!$A$4:$A$112,0)) -> 2 | F97: 2 | G97: Secundarios: Integración y Seguridad (firma), con peso aproximado. | H97: =IF(ISNUMBER(F97),F97*E97,0) -> 4 | I97: =IF(F97="N/A",0,3*E97) -> 6 | J97: =IF(F97="","Sin evaluar (núcleo, cuenta como 0) – "&INDEX(Rubricas!$F$4:$F$112,MATCH(A97,Rubricas!$A$4:$A$112,0)),IF(F97="N/A","⚠ Este criterio no admite N/A: calificar de 0 a 3.",IF(F97<=1,INDEX(Rubricas!$O$4:$O$112,MATCH(A97,Rubricas!$A$4:$A$112,0)),IF(F97=2,"Por completar o validar – "&INDEX(Rubricas!$F$4:$F$112,MATCH(A97,Rubricas!$A$4:$A$112,0)),"")))) -> Por completar o validar – Arquetipos secundarios | K97: =IF(ISNUMBER(F97),IF(F97<3,(3-F97)*E97*VLOOKUP(B97,Parametros!$A$5:$D$15,4,0)*100+ROW()/100000,0),IF(F97="",3*E97*VLOOKUP(B97,Parametros!$A$5:$D$15,4,0)*100+ROW()/100000,0)) -> 22.00097
A98: D2.05 | B98: D2 | C98: Validación de la clasificación | D98: Independencia del nombre comercial: ¿La clasificación se contrastó contra el contenido real del alcance y no depende del nombre del proyecto? | E98: =INDEX(Rubricas!$M$4:$M$112,MATCH(A98,Rubricas!$A$4:$A$112,0)) -> 1 | F98: 2 | G98: Contrastado con backlog; el nombre sugería «firma digital» como principal. | H98: =IF(ISNUMBER(F98),F98*E98,0) -> 2 | I98: =IF(F98="N/A",0,3*E98) -> 3 | J98: =IF(F98="","Sin evaluar (núcleo, cuenta como 0) – "&INDEX(Rubricas!$F$4:$F$112,MATCH(A98,Rubricas!$A$4:$A$112,0)),IF(F98="N/A","⚠ Este criterio no admite N/A: calificar de 0 a 3.",IF(F98<=1,INDEX(Rubricas!$O$4:$O$112,MATCH(A98,Rubricas!$A$4:$A$112,0)),IF(F98=2,"Por completar o validar – "&INDEX(Rubricas!$F$4:$F$112,MATCH(A98,Rubricas!$A$4:$A$112,0)),"")))) -> Por completar o validar – Independencia del nombre comercial | K98: =IF(ISNUMBER(F98),IF(F98<3,(3-F98)*E98*VLOOKUP(B98,Parametros!$A$5:$D$15,4,0)*100+ROW()/100000,0),IF(F98="",3*E98*VLOOKUP(B98,Parametros!$A$5:$D$15,4,0)*100+ROW()/100000,0)) -> 11.00098
A99: D2.06 | B99: D2 | C99: Drivers de esfuerzo | D99: Drivers del arquetipo principal: ¿Se identifican y cuantifican los drivers típicos del arquetipo principal (p. ej. Aplicaciones: funcionalidades, reglas, roles, pantallas, flujos; Integración: interfaces, protocolos, transformaciones; Datos/IA: fuentes, volumen, calidad, modelos; Plataforma: ambientes, componentes, SLA; Seguridad: identidades, controles, certificados; Modernización: tamaño del activo, deuda técnica, datos a migrar)? | E99: =INDEX(Rubricas!$M$4:$M$112,MATCH(A99,Rubricas!$A$4:$A$112,0)) -> 3 | F99: 2 | G99: 34 funcionalidades, 5 roles, 18 pantallas; reglas sin cuantificar. | H99: =IF(ISNUMBER(F99),F99*E99,0) -> 6 | I99: =IF(F99="N/A",0,3*E99) -> 9 | J99: =IF(F99="","Sin evaluar (núcleo, cuenta como 0) – "&INDEX(Rubricas!$F$4:$F$112,MATCH(A99,Rubricas!$A$4:$A$112,0)),IF(F99="N/A","⚠ Este criterio no admite N/A: calificar de 0 a 3.",IF(F99<=1,INDEX(Rubricas!$O$4:$O$112,MATCH(A99,Rubricas!$A$4:$A$112,0)),IF(F99=2,"Por completar o validar – "&INDEX(Rubricas!$F$4:$F$112,MATCH(A99,Rubricas!$A$4:$A$112,0)),"")))) -> Por completar o validar – Drivers del arquetipo principal | K99: =IF(ISNUMBER(F99),IF(F99<3,(3-F99)*E99*VLOOKUP(B99,Parametros!$A$5:$D$15,4,0)*100+ROW()/100000,0),IF(F99="",3*E99*VLOOKUP(B99,Parametros!$A$5:$D$15,4,0)*100+ROW()/100000,0)) -> 33.00099
A100: D2.07 | B100: D2 | C100: Drivers de esfuerzo | D100: Drivers de arquetipos secundarios: ¿Se identifican y cuantifican los drivers de los arquetipos secundarios? (Admite N/A) | E100: =INDEX(Rubricas!$M$4:$M$112,MATCH(A100,Rubricas!$A$4:$A$112,0)) -> 2 | F100: 1 | G100: Drivers de seguridad (certificados, niveles de firma) no cuantificados. | H100: =IF(ISNUMBER(F100),F100*E100,0) -> 2 | I100: =IF(F100="N/A",0,3*E100) -> 6 | J100: =IF(F100="","Sin evaluar (núcleo, cuenta como 0) – "&INDEX(Rubricas!$F$4:$F$112,MATCH(A100,Rubricas!$A$4:$A$112,0)),IF(F100="N/A","",IF(F100<=1,INDEX(Rubricas!$O$4:$O$112,MATCH(A100,Rubricas!$A$4:$A$112,0)),IF(F100=2,"Por completar o validar – "&INDEX(Rubricas!$F$4:$F$112,MATCH(A100,Rubricas!$A$4:$A$112,0)),"")))) -> Los drivers de los arquetipos secundarios no están cuantificados. | K100: =IF(ISNUMBER(F100),IF(F100<3,(3-F100)*E100*VLOOKUP(B100,Parametros!$A$5:$D$15,4,0)*100+ROW()/100000,0),IF(F100="",3*E100*VLOOKUP(B100,Parametros!$A$5:$D$15,4,0)*100+ROW()/100000,0)) -> 44.001
A101: D2.08 | B101: D2 | C101: Objeto predominante | D101: Tipo de usuario funcional predominante: ¿Se identifica quién intercambia datos con la solución (personas por rol, otros sistemas, dispositivos) y es coherente con el arquetipo (p. ej. en Integración predominan sistemas)? | E101: =INDEX(Rubricas!$M$4:$M$112,MATCH(A101,Rubricas!$A$4:$A$112,0)) -> 2 | F101: 3 | G101: Abogados, supervisores, proveedores, firmantes, administrador + 4 sistemas. | H101: =IF(ISNUMBER(F101),F101*E101,0) -> 6 | I101: =IF(F101="N/A",0,3*E101) -> 6 | J101: =IF(F101="","Sin evaluar (núcleo, cuenta como 0) – "&INDEX(Rubricas!$F$4:$F$112,MATCH(A101,Rubricas!$A$4:$A$112,0)),IF(F101="N/A","⚠ Este criterio no admite N/A: calificar de 0 a 3.",IF(F101<=1,INDEX(Rubricas!$O$4:$O$112,MATCH(A101,Rubricas!$A$4:$A$112,0)),IF(F101=2,"Por completar o validar – "&INDEX(Rubricas!$F$4:$F$112,MATCH(A101,Rubricas!$A$4:$A$112,0)),"")))) | K101: =IF(ISNUMBER(F101),IF(F101<3,(3-F101)*E101*VLOOKUP(B101,Parametros!$A$5:$D$15,4,0)*100+ROW()/100000,0),IF(F101="",3*E101*VLOOKUP(B101,Parametros!$A$5:$D$15,4,0)*100+ROW()/100000,0)) -> 0
A102: D2.09 | B102: D2 | C102: Distribución del esfuerzo | D102: Componentes de terceros / SaaS: ¿Se identifican productos de terceros, paquetes o SaaS y se distingue configuración de desarrollo a medida? (Admite N/A) | E102: =INDEX(Rubricas!$M$4:$M$112,MATCH(A102,Rubricas!$A$4:$A$112,0)) -> 2 | F102: 2 | G102: Servicio de firma SaaS por API; falta confirmar configuración de plantillas. | H102: =IF(ISNUMBER(F102),F102*E102,0) -> 4 | I102: =IF(F102="N/A",0,3*E102) -> 6 | J102: =IF(F102="","Sin evaluar (núcleo, cuenta como 0) – "&INDEX(Rubricas!$F$4:$F$112,MATCH(A102,Rubricas!$A$4:$A$112,0)),IF(F102="N/A","",IF(F102<=1,INDEX(Rubricas!$O$4:$O$112,MATCH(A102,Rubricas!$A$4:$A$112,0)),IF(F102=2,"Por completar o validar – "&INDEX(Rubricas!$F$4:$F$112,MATCH(A102,Rubricas!$A$4:$A$112,0)),"")))) -> Por completar o validar – Componentes de terceros / SaaS | K102: =IF(ISNUMBER(F102),IF(F102<3,(3-F102)*E102*VLOOKUP(B102,Parametros!$A$5:$D$15,4,0)*100+ROW()/100000,0),IF(F102="",3*E102*VLOOKUP(B102,Parametros!$A$5:$D$15,4,0)*100+ROW()/100000,0)) -> 22.00102
A103: D2.10 | B103: D2 | C103: Distribución del esfuerzo | D103: Entregables no software separados: ¿Se separan del alcance de software los entregables que no son funcionalidad (licencias, infraestructura, capacitación, migración manual, soporte, documentación)? | E103: =INDEX(Rubricas!$M$4:$M$112,MATCH(A103,Rubricas!$A$4:$A$112,0)) -> 1 | F103: 1 | G103: Capacitación y soporte post-producción mezclados con el alcance. | H103: =IF(ISNUMBER(F103),F103*E103,0) -> 1 | I103: =IF(F103="N/A",0,3*E103) -> 3 | J103: =IF(F103="","Sin evaluar (núcleo, cuenta como 0) – "&INDEX(Rubricas!$F$4:$F$112,MATCH(A103,Rubricas!$A$4:$A$112,0)),IF(F103="N/A","⚠ Este criterio no admite N/A: calificar de 0 a 3.",IF(F103<=1,INDEX(Rubricas!$O$4:$O$112,MATCH(A103,Rubricas!$A$4:$A$112,0)),IF(F103=2,"Por completar o validar – "&INDEX(Rubricas!$F$4:$F$112,MATCH(A103,Rubricas!$A$4:$A$112,0)),"")))) -> Entregables que no son funcionalidad están mezclados con el alcance de software; deben estimarse por separado. | K103: =IF(ISNUMBER(F103),IF(F103<3,(3-F103)*E103*VLOOKUP(B103,Parametros!$A$5:$D$15,4,0)*100+ROW()/100000,0),IF(F103="",3*E103*VLOOKUP(B103,Parametros!$A$5:$D$15,4,0)*100+ROW()/100000,0)) -> 22.00103
A104: D2.11 | B104: D2 | C104: Validación de la clasificación | D104: Resolución de solapamientos: Cuando el trabajo cae entre categorías (IA vs. Datos, DevOps vs. Plataforma, SaaS personalizado vs. Aplicación, middleware vs. Integración), ¿se aplicó la regla de consolidación del catálogo? (Admite N/A) | E104: =INDEX(Rubricas!$M$4:$M$112,MATCH(A104,Rubricas!$A$4:$A$112,0)) -> 1 | F104: 3 | G104: Regla aplicada: portal de firma → Aplicaciones + secundarios Seguridad e Integración. | H104: =IF(ISNUMBER(F104),F104*E104,0) -> 3 | I104: =IF(F104="N/A",0,3*E104) -> 3 | J104: =IF(F104="","Sin evaluar (núcleo, cuenta como 0) – "&INDEX(Rubricas!$F$4:$F$112,MATCH(A104,Rubricas!$A$4:$A$112,0)),IF(F104="N/A","",IF(F104<=1,INDEX(Rubricas!$O$4:$O$112,MATCH(A104,Rubricas!$A$4:$A$112,0)),IF(F104=2,"Por completar o validar – "&INDEX(Rubricas!$F$4:$F$112,MATCH(A104,Rubricas!$A$4:$A$112,0)),"")))) | K104: =IF(ISNUMBER(F104),IF(F104<3,(3-F104)*E104*VLOOKUP(B104,Parametros!$A$5:$D$15,4,0)*100+ROW()/100000,0),IF(F104="",3*E104*VLOOKUP(B104,Parametros!$A$5:$D$15,4,0)*100+ROW()/100000,0)) -> 0
A105: D2.12 | B105: D2 | C105: Validación de la clasificación | D105: Clasificación validada: ¿La clasificación fue revisada por al menos dos roles (p. ej. arquitecto y estimador) y registrada? | E105: =INDEX(Rubricas!$M$4:$M$112,MATCH(A105,Rubricas!$A$4:$A$112,0)) -> 1 | F105: 2 | G105: Revisado por arquitecto; falta registro con el estimador. | H105: =IF(ISNUMBER(F105),F105*E105,0) -> 2 | I105: =IF(F105="N/A",0,3*E105) -> 3 | J105: =IF(F105="","Sin evaluar (núcleo, cuenta como 0) – "&INDEX(Rubricas!$F$4:$F$112,MATCH(A105,Rubricas!$A$4:$A$112,0)),IF(F105="N/A","⚠ Este criterio no admite N/A: calificar de 0 a 3.",IF(F105<=1,INDEX(Rubricas!$O$4:$O$112,MATCH(A105,Rubricas!$A$4:$A$112,0)),IF(F105=2,"Por completar o validar – "&INDEX(Rubricas!$F$4:$F$112,MATCH(A105,Rubricas!$A$4:$A$112,0)),"")))) -> Por completar o validar – Clasificación validada | K105: =IF(ISNUMBER(F105),IF(F105<3,(3-F105)*E105*VLOOKUP(B105,Parametros!$A$5:$D$15,4,0)*100+ROW()/100000,0),IF(F105="",3*E105*VLOOKUP(B105,Parametros!$A$5:$D$15,4,0)*100+ROW()/100000,0)) -> 11.00105
A106: ="D3 · Tamaño funcional — Núcleo · peso "&TEXT(Parametros!$D$7,"0%")&" · 14 criterios" -> D3 · Tamaño funcional — Núcleo · peso 18% · 14 criterios
A107: D3.01 | B107: D3 | C107: Estrategia de medición | D107: Propósito y alcance de la medición: ¿Está definido para qué se mide (cotización/estimación), qué piezas de software y capas se incluyen y qué se excluye? | E107: =INDEX(Rubricas!$M$4:$M$112,MATCH(A107,Rubricas!$A$4:$A$112,0)) -> 3 | F107: 2 | G107: Propósito: cotización; incluye portal y API; exclusión de BI no documentada. | H107: =IF(ISNUMBER(F107),F107*E107,0) -> 6 | I107: =IF(F107="N/A",0,3*E107) -> 9 | J107: =IF(F107="","Sin evaluar (núcleo, cuenta como 0) – "&INDEX(Rubricas!$F$4:$F$112,MATCH(A107,Rubricas!$A$4:$A$112,0)),IF(F107="N/A","⚠ Este criterio no admite N/A: calificar de 0 a 3.",IF(F107<=1,INDEX(Rubricas!$O$4:$O$112,MATCH(A107,Rubricas!$A$4:$A$112,0)),IF(F107=2,"Por completar o validar – "&INDEX(Rubricas!$F$4:$F$112,MATCH(A107,Rubricas!$A$4:$A$112,0)),"")))) -> Por completar o validar – Propósito y alcance de la medición | K107: =IF(ISNUMBER(F107),IF(F107<3,(3-F107)*E107*VLOOKUP(B107,Parametros!$A$5:$D$15,4,0)*100+ROW()/100000,0),IF(F107="",3*E107*VLOOKUP(B107,Parametros!$A$5:$D$15,4,0)*100+ROW()/100000,0)) -> 54.00107
...

Sheet Resultados
B1: Resultados de la evaluación de madurez
B3: Ficha a analizar (seleccionar): | C3: Ejemplo | D3: Todas las cifras de esta hoja se leen de la ficha seleccionada (Ejemplo o Ficha).
B5: Proyecto | C5: =IF(INDIRECT("'"&$C$3&"'!D4")="","",INDIRECT("'"&$C$3&"'!D4")) -> Portal de gestión y firma electrónica de contratos
B6: Cliente / área | C6: =IF(INDIRECT("'"&$C$3&"'!D5")="","",INDIRECT("'"&$C$3&"'!D5")) -> Entidad pública – Dirección de Contratación
B7: Evaluador(es) | C7: =IF(INDIRECT("'"&$C$3&"'!D6")="","",INDIRECT("'"&$C$3&"'!D6")) -> Arquitecto de soluciones + Líder de estimación
B8: Fecha de evaluación | C8: =IF(INDIRECT("'"&$C$3&"'!D7")="","",INDIRECT("'"&$C$3&"'!D7")) -> 2026-09-22
B9: Momento de estimación | C9: =IF(INDIRECT("'"&$C$3&"'!D8")="","",INDIRECT("'"&$C$3&"'!D8")) -> Propuesta comercial (preventa)
B11: Madurez general | C11: Nivel final | F11: Arquetipo principal | O11: Técnica de estimación sugerida
B12: =INDIRECT("'"&$C$3&"'!F53") -> 0.56716233 | C12: =INDIRECT("'"&$C$3&"'!G55") -> N3 - Intermedio | F12: =INDIRECT("'"&$C$3&"'!G18") -> Aplicaciones y soluciones digitales | O12: =INDIRECT("'"&$C$3&"'!D57") -> Analogía con histórico + descomposición (WBS); estimación preliminar.
B14: Madurez por dimensión
B15: Dimensión | C15: Tipo | D15: Peso | E15: Madurez | F15: Nivel | G15: Aporte | H15: N° criterios | I15: En 0 | J15: En 1 | K15: En 2 | L15: En 3 | M15: N/A | N15: Sin evaluar | O15: Principal brecha
B16: D1 · Tipo de desarrollo | C16: =INDIRECT("'"&$C$3&"'!H42") -> Núcleo | D16: =INDIRECT("'"&$C$3&"'!E42") -> 0.12 | E16: =INDIRECT("'"&$C$3&"'!F42") -> 0.6 | F16: =INDIRECT("'"&$C$3&"'!G42") -> N4 - Definido | G16: =INDIRECT("'"&$C$3&"'!I42") -> 0.072 | H16: =COUNTIF(INDIRECT("'"&$C$3&"'!$B$80:$B$240"),"D1") -> 12 | I16: =COUNTIFS(INDIRECT("'"&$C$3&"'!$B$80:$B$240"),"D1",INDIRECT("'"&$C$3&"'!$F$80:$F$240"),0) -> 0 | J16: =COUNTIFS(INDIRECT("'"&$C$3&"'!$B$80:$B$240"),"D1",INDIRECT("'"&$C$3&"'!$F$80:$F$240"),1) -> 4 | K16: =COUNTIFS(INDIRECT("'"&$C$3&"'!$B$80:$B$240"),"D1",INDIRECT("'"&$C$3&"'!$F$80:$F$240"),2) -> 5 | L16: =COUNTIFS(INDIRECT("'"&$C$3&"'!$B$80:$B$240"),"D1",INDIRECT("'"&$C$3&"'!$F$80:$F$240"),3) -> 2 | M16: =COUNTIFS(INDIRECT("'"&$C$3&"'!$B$80:$B$240"),"D1",INDIRECT("'"&$C$3&"'!$F$80:$F$240"),"N/A") -> 1 | N16: =H16-SUM(I16:M16) -> 0 | O16: =INDIRECT("'"&$C$3&"'!D42") -> No se detalla qué cambia en las funcionalidades existentes. En evolutivos el tamaño es la suma de movimientos de datos agregados, modificados y eliminados; identificarlos.
B17: D2 · Tipo de solución / arquetipo | C17: =INDIRECT("'"&$C$3&"'!H43") -> Núcleo | D17: =INDIRECT("'"&$C$3&"'!E43") -> 0.11 | E17: =INDIRECT("'"&$C$3&"'!F43") -> 0.71014493 | F17: =INDIRECT("'"&$C$3&"'!G43") -> N4 - Definido | G17: =INDIRECT("'"&$C$3&"'!I43") -> 0.078115942 | H17: =COUNTIF(INDIRECT("'"&$C$3&"'!$B$80:$B$240"),"D2") -> 12 | I17: =COUNTIFS(INDIRECT("'"&$C$3&"'!$B$80:$B$240"),"D2",INDIRECT("'"&$C$3&"'!$F$80:$F$240"),0) -> 0 | J17: =COUNTIFS(INDIRECT("'"&$C$3&"'!$B$80:$B$240"),"D2",INDIRECT("'"&$C$3&"'!$F$80:$F$240"),1) -> 2 | K17: =COUNTIFS(INDIRECT("'"&$C$3&"'!$B$80:$B$240"),"D2",INDIRECT("'"&$C$3&"'!$F$80:$F$240"),2) -> 7 | L17: =COUNTIFS(INDIRECT("'"&$C$3&"'!$B$80:$B$240"),"D2",INDIRECT("'"&$C$3&"'!$F$80:$F$240"),3) -> 3 | M17: =COUNTIFS(INDIRECT("'"&$C$3&"'!$B$80:$B$240"),"D2",INDIRECT("'"&$C$3&"'!$F$80:$F$240"),"N/A") -> 0 | N17: =H17-SUM(I17:M17) -> 0 | O17: =INDIRECT("'"&$C$3&"'!D43") -> Los drivers de los arquetipos secundarios no están cuantificados.
B18: D3 · Tamaño funcional | C18: =INDIRECT("'"&$C$3&"'!H44") -> Núcleo | D18: =INDIRECT("'"&$C$3&"'!E44") -> 0.18 | E18: =INDIRECT("'"&$C$3&"'!F44") -> 0.49462366 | F18: =INDIRECT("'"&$C$3&"'!G44") -> N3 - Intermedio | G18: =INDIRECT("'"&$C$3&"'!I44") -> 0.089032258 | H18: =COUNTIF(INDIRECT("'"&$C$3&"'!$B$80:$B$240"),"D3") -> 14 | I18: =COUNTIFS(INDIRECT("'"&$C$3&"'!$B$80:$B$240"),"D3",INDIRECT("'"&$C$3&"'!$F$80:$F$240"),0) -> 1 | J18: =COUNTIFS(INDIRECT("'"&$C$3&"'!$B$80:$B$240"),"D3",INDIRECT("'"&$C$3&"'!$F$80:$F$240"),1) -> 7 | K18: =COUNTIFS(INDIRECT("'"&$C$3&"'!$B$80:$B$240"),"D3",INDIRECT("'"&$C$3&"'!$F$80:$F$240"),2) -> 6 | L18: =COUNTIFS(INDIRECT("'"&$C$3&"'!$B$80:$B$240"),"D3",INDIRECT("'"&$C$3&"'!$F$80:$F$240"),3) -> 0 | M18: =COUNTIFS(INDIRECT("'"&$C$3&"'!$B$80:$B$240"),"D3",INDIRECT("'"&$C$3&"'!$F$80:$F$240"),"N/A") -> 0 | N18: =H18-SUM(I18:M18) -> 0 | O18: =INDIRECT("'"&$C$3&"'!D44") -> No se identifican los movimientos de datos (Entradas, Salidas, Lecturas, Escrituras); el tamaño queda como aproximación. Medir al menos una muestra representativa.
B19: D4 · Complejidad | C19: =INDIRECT("'"&$C$3&"'!H45") -> Núcleo | D19: =INDIRECT("'"&$C$3&"'!E45") -> 0.15 | E19: =INDIRECT("'"&$C$3&"'!F45") -> 0.58974359 | F19: =INDIRECT("'"&$C$3&"'!G45") -> N3 - Intermedio | G19: =INDIRECT("'"&$C$3&"'!I45") -> 0.088461538 | H19: =COUNTIF(INDIRECT("'"&$C$3&"'!$B$80:$B$240"),"D4") -> 12 | I19: =COUNTIFS(INDIRECT("'"&$C$3&"'!$B$80:$B$240"),"D4",INDIRECT("'"&$C$3&"'!$F$80:$F$240"),0) -> 1 | J19: =COUNTIFS(INDIRECT("'"&$C$3&"'!$B$80:$B$240"),"D4",INDIRECT("'"&$C$3&"'!$F$80:$F$240"),1) -> 3 | K19: =COUNTIFS(INDIRECT("'"&$C$3&"'!$B$80:$B$240"),"D4",INDIRECT("'"&$C$3&"'!$F$80:$F$240"),2) -> 6 | L19: =COUNTIFS(INDIRECT("'"&$C$3&"'!$B$80:$B$240"),"D4",INDIRECT("'"&$C$3&"'!$F$80:$F$240"),3) -> 2 | M19: =COUNTIFS(INDIRECT("'"&$C$3&"'!$B$80:$B$240"),"D4",INDIRECT("'"&$C$3&"'!$F$80:$F$240"),"N/A") -> 0 | N19: =H19-SUM(I19:M19) -> 0 | O19: =INDIRECT("'"&$C$3&"'!D45") -> Los requisitos de seguridad no están especificados ni clasificados.
B20: D5 · Integración / interdependencia | C20: =INDIRECT("'"&$C$3&"'!H46") -> Núcleo | D20: =INDIRECT("'"&$C$3&"'!E46") -> 0.14 | E20: =INDIRECT("'"&$C$3&"'!F46") -> 0.51190476 | F20: =INDIRECT("'"&$C$3&"'!G46") -> N3 - Intermedio | G20: =INDIRECT("'"&$C$3&"'!I46") -> 0.071666667 | H20: =COUNTIF(INDIRECT("'"&$C$3&"'!$B$80:$B$240"),"D5") -> 13 | I20: =COUNTIFS(INDIRECT("'"&$C$3&"'!$B$80:$B$240"),"D5",INDIRECT("'"&$C$3&"'!$F$80:$F$240"),0) -> 1 | J20: =COUNTIFS(INDIRECT("'"&$C$3&"'!$B$80:$B$240"),"D5",INDIRECT("'"&$C$3&"'!$F$80:$F$240"),1) -> 5 | K20: =COUNTIFS(INDIRECT("'"&$C$3&"'!$B$80:$B$240"),"D5",INDIRECT("'"&$C$3&"'!$F$80:$F$240"),2) -> 6 | L20: =COUNTIFS(INDIRECT("'"&$C$3&"'!$B$80:$B$240"),"D5",INDIRECT("'"&$C$3&"'!$F$80:$F$240"),3) -> 1 | M20: =COUNTIFS(INDIRECT("'"&$C$3&"'!$B$80:$B$240"),"D5",INDIRECT("'"&$C$3&"'!$F$80:$F$240"),"N/A") -> 0 | N20: =H20-SUM(I20:M20) -> 0 | O20: =INDIRECT("'"&$C$3&"'!D46") -> No está definido el manejo de errores (reintentos, idempotencia, conciliación).
B21: D6 · Novedad y reutilización | C21: =INDIRECT("'"&$C$3&"'!H47") -> Complementaria | D21: =INDIRECT("'"&$C$3&"'!E47") -> 0.05 | E21: =INDIRECT("'"&$C$3&"'!F47") -> 0.47222222 | F21: =INDIRECT("'"&$C$3&"'!G47") -> N3 - Intermedio | G21: =INDIRECT("'"&$C$3&"'!I47") -> 0.023611111 | H21: =COUNTIF(INDIRECT("'"&$C$3&"'!$B$80:$B$240"),"D6") -> 7 | I21: =COUNTIFS(INDIRECT("'"&$C$3&"'!$B$80:$B$240"),"D6",INDIRECT("'"&$C$3&"'!$F$80:$F$240"),0) -> 0 | J21: =COUNTIFS(INDIRECT("'"&$C$3&"'!$B$80:$B$240"),"D6",INDIRECT("'"&$C$3&"'!$F$80:$F$240"),1) -> 3 | K21: =COUNTIFS(INDIRECT("'"&$C$3&"'!$B$80:$B$240"),"D6",INDIRECT("'"&$C$3&"'!$F$80:$F$240"),2) -> 3 | L21: =COUNTIFS(INDIRECT("'"&$C$3&"'!$B$80:$B$240"),"D6",INDIRECT("'"&$C$3&"'!$F$80:$F$240"),3) -> 0 | M21: =COUNTIFS(INDIRECT("'"&$C$3&"'!$B$80:$B$240"),"D6",INDIRECT("'"&$C$3&"'!$F$80:$F$240"),"N/A") -> 1 | N21: =H21-SUM(I21:M21) -> 0 | O21: =INDIRECT("'"&$C$3&"'!D47") -> El reuso no está clasificado por funcionalidad; el porcentaje reutilizable es una suposición.
B22: D7 · Entorno tecnológico | C22: =INDIRECT("'"&$C$3&"'!H48") -> Complementaria | D22: =INDIRECT("'"&$C$3&"'!E48") -> 0.05 | E22: =INDIRECT("'"&$C$3&"'!F48") -> 0.68888889 | F22: =INDIRECT("'"&$C$3&"'!G48") -> N4 - Definido | G22: =INDIRECT("'"&$C$3&"'!I48") -> 0.034444444 | H22: =COUNTIF(INDIRECT("'"&$C$3&"'!$B$80:$B$240"),"D7") -> 7 | I22: =COUNTIFS(INDIRECT("'"&$C$3&"'!$B$80:$B$240"),"D7",INDIRECT("'"&$C$3&"'!$F$80:$F$240"),0) -> 0 | J22: =COUNTIFS(INDIRECT("'"&$C$3&"'!$B$80:$B$240"),"D7",INDIRECT("'"&$C$3&"'!$F$80:$F$240"),1) -> 2 | K22: =COUNTIFS(INDIRECT("'"&$C$3&"'!$B$80:$B$240"),"D7",INDIRECT("'"&$C$3&"'!$F$80:$F$240"),2) -> 3 | L22: =COUNTIFS(INDIRECT("'"&$C$3&"'!$B$80:$B$240"),"D7",INDIRECT("'"&$C$3&"'!$F$80:$F$240"),3) -> 2 | M22: =COUNTIFS(INDIRECT("'"&$C$3&"'!$B$80:$B$240"),"D7",INDIRECT("'"&$C$3&"'!$F$80:$F$240"),"N/A") -> 0 | N22: =H22-SUM(I22:M22) -> 0 | O22: =INDIRECT("'"&$C$3&"'!D48") -> No se conocen las restricciones tecnológicas del cliente.
B23: D8 · Madurez del alcance | C23: =INDIRECT("'"&$C$3&"'!H49") -> Complementaria | D23: =INDIRECT("'"&$C$3&"'!E49") -> 0.07 | E23: =INDIRECT("'"&$C$3&"'!F49") -> 0.56521739 | F23: =INDIRECT("'"&$C$3&"'!G49") -> N3 - Intermedio | G23: =INDIRECT("'"&$C$3&"'!I49") -> 0.039565217 | H23: =COUNTIF(INDIRECT("'"&$C$3&"'!$B$80:$B$240"),"D8") -> 11 | I23: =COUNTIFS(INDIRECT("'"&$C$3&"'!$B$80:$B$240"),"D8",INDIRECT("'"&$C$3&"'!$F$80:$F$240"),0) -> 0 | J23: =COUNTIFS(INDIRECT("'"&$C$3&"'!$B$80:$B$240"),"D8",INDIRECT("'"&$C$3&"'!$F$80:$F$240"),1) -> 5 | K23: =COUNTIFS(INDIRECT("'"&$C$3&"'!$B$80:$B$240"),"D8",INDIRECT("'"&$C$3&"'!$F$80:$F$240"),2) -> 4 | L23: =COUNTIFS(INDIRECT("'"&$C$3&"'!$B$80:$B$240"),"D8",INDIRECT("'"&$C$3&"'!$F$80:$F$240"),3) -> 2 | M23: =COUNTIFS(INDIRECT("'"&$C$3&"'!$B$80:$B$240"),"D8",INDIRECT("'"&$C$3&"'!$F$80:$F$240"),"N/A") -> 0 | N23: =H23-SUM(I23:M23) -> 0 | O23: =INDIRECT("'"&$C$3&"'!D49") -> No hay criterios de aceptación verificables; sin ellos el alcance de pruebas y la aceptación son inciertos.
B24: D9 · Contexto de ejecución | C24: =INDIRECT("'"&$C$3&"'!H50") -> Complementaria | D24: =INDIRECT("'"&$C$3&"'!E50") -> 0.05 | E24: =INDIRECT("'"&$C$3&"'!F50") -> 0.64583333 | F24: =INDIRECT("'"&$C$3&"'!G50") -> N4 - Definido | G24: =INDIRECT("'"&$C$3&"'!I50") -> 0.032291667 | H24: =COUNTIF(INDIRECT("'"&$C$3&"'!$B$80:$B$240"),"D9") -> 8 | I24: =COUNTIFS(INDIRECT("'"&$C$3&"'!$B$80:$B$240"),"D9",INDIRECT("'"&$C$3&"'!$F$80:$F$240"),0) -> 0 | J24: =COUNTIFS(INDIRECT("'"&$C$3&"'!$B$80:$B$240"),"D9",INDIRECT("'"&$C$3&"'!$F$80:$F$240"),1) -> 2 | K24: =COUNTIFS(INDIRECT("'"&$C$3&"'!$B$80:$B$240"),"D9",INDIRECT("'"&$C$3&"'!$F$80:$F$240"),2) -> 4 | L24: =COUNTIFS(INDIRECT("'"&$C$3&"'!$B$80:$B$240"),"D9",INDIRECT("'"&$C$3&"'!$F$80:$F$240"),3) -> 2 | M24: =COUNTIFS(INDIRECT("'"&$C$3&"'!$B$80:$B$240"),"D9",INDIRECT("'"&$C$3&"'!$F$80:$F$240"),"N/A") -> 0 | N24: =H24-SUM(I24:M24) -> 0 | O24: =INDIRECT("'"&$C$3&"'!D50") -> No se conocen las dependencias externas de ejecución ni sus tiempos.
B25: D10 · Sector / contexto de negocio | C25: =INDIRECT("'"&$C$3&"'!H51") -> Complementaria | D25: =INDIRECT("'"&$C$3&"'!E51") -> 0.03 | E25: =INDIRECT("'"&$C$3&"'!F51") -> 0.60606061 | F25: =INDIRECT("'"&$C$3&"'!G51") -> N4 - Definido | G25: =INDIRECT("'"&$C$3&"'!I51") -> 0.018181818 | H25: =COUNTIF(INDIRECT("'"&$C$3&"'!$B$80:$B$240"),"D10") -> 6 | I25: =COUNTIFS(INDIRECT("'"&$C$3&"'!$B$80:$B$240"),"D10",INDIRECT("'"&$C$3&"'!$F$80:$F$240"),0) -> 0 | J25: =COUNTIFS(INDIRECT("'"&$C$3&"'!$B$80:$B$240"),"D10",INDIRECT("'"&$C$3&"'!$F$80:$F$240"),1) -> 2 | K25: =COUNTIFS(INDIRECT("'"&$C$3&"'!$B$80:$B$240"),"D10",INDIRECT("'"&$C$3&"'!$F$80:$F$240"),2) -> 3 | L25: =COUNTIFS(INDIRECT("'"&$C$3&"'!$B$80:$B$240"),"D10",INDIRECT("'"&$C$3&"'!$F$80:$F$240"),3) -> 1 | M25: =COUNTIFS(INDIRECT("'"&$C$3&"'!$B$80:$B$240"),"D10",INDIRECT("'"&$C$3&"'!$F$80:$F$240"),"N/A") -> 0 | N25: =H25-SUM(I25:M25) -> 0 | O25: =INDIRECT("'"&$C$3&"'!D51") -> No se conocen los stakeholders ni el ciclo de aprobaciones.
B26: D11 · Evidencia histórica disponible | C26: =INDIRECT("'"&$C$3&"'!H52") -> Complementaria | D26: =INDIRECT("'"&$C$3&"'!E52") -> 0.05 | E26: =INDIRECT("'"&$C$3&"'!F52") -> 0.39583333 | F26: =INDIRECT("'"&$C$3&"'!G52") -> N2 - Preliminar | G26: =INDIRECT("'"&$C$3&"'!I52") -> 0.019791667 | H26: =COUNTIF(INDIRECT("'"&$C$3&"'!$B$80:$B$240"),"D11") -> 7 | I26: =COUNTIFS(INDIRECT("'"&$C$3&"'!$B$80:$B$240"),"D11",INDIRECT("'"&$C$3&"'!$F$80:$F$240"),0) -> 1 | J26: =COUNTIFS(INDIRECT("'"&$C$3&"'!$B$80:$B$240"),"D11",INDIRECT("'"&$C$3&"'!$F$80:$F$240"),1) -> 4 | K26: =COUNTIFS(INDIRECT("'"&$C$3&"'!$B$80:$B$240"),"D11",INDIRECT("'"&$C$3&"'!$F$80:$F$240"),2) -> 1 | L26: =COUNTIFS(INDIRECT("'"&$C$3&"'!$B$80:$B$240"),"D11",INDIRECT("'"&$C$3&"'!$F$80:$F$240"),3) -> 1 | M26: =COUNTIFS(INDIRECT("'"&$C$3&"'!$B$80:$B$240"),"D11",INDIRECT("'"&$C$3&"'!$F$80:$F$240"),"N/A") -> 0 | N26: =H26-SUM(I26:M26) -> 0 | O26: =INDIRECT("'"&$C$3&"'!D52") -> El tamaño de los comparables no está normalizado.
B27: Madurez general ponderada | D27: =SUM(D16:D26) -> 1 | E27: =INDIRECT("'"&$C$3&"'!F53") -> 0.56716233 | F27: =INDIRECT("'"&$C$3&"'!G55") -> N3 - Intermedio | G27: =SUM(G16:G26) -> 0.56716233 | H27: =SUM(H16:H26) -> 109 | I27: =SUM(I16:I26) -> 4 | J27: =SUM(J16:J26) -> 39 | K27: =SUM(K16:K26) -> 48 | L27: =SUM(L16:L26) -> 16 | M27: =SUM(M16:M26) -> 2 | N27: =SUM(N16:N26) -> 0 | O27: =INDIRECT("'"&$C$3&"'!G54") -> No aplica tope
B48: Caracterización del proyecto (valores del catálogo)
B49: D1 · Tipo de desarrollo predominante | C49: =IF(INDIRECT("'"&$C$3&"'!G14")="","",INDIRECT("'"&$C$3&"'!G14")) -> Nuevo desarrollo
B50: D1 · Control de composición | C50: =IF(INDIRECT("'"&$C$3&"'!G15")="","",INDIRECT("'"&$C$3&"'!G15")) -> Composición suma 100%
B51: D2 · Arquetipo principal | C51: =IF(INDIRECT("'"&$C$3&"'!G18")="","",INDIRECT("'"&$C$3&"'!G18")) -> Aplicaciones y soluciones digitales
B52: D2 · Arquetipos secundarios | C52: =IF(INDIRECT("'"&$C$3&"'!E19")="","",INDIRECT("'"&$C$3&"'!E19")) -> Seguridad, identidad y confianza digital; Integración e interoperabilidad
B53: D2 · Predominio del arquetipo | C53: =IF(INDIRECT("'"&$C$3&"'!G20")="","",INDIRECT("'"&$C$3&"'!G20")) -> Predominio claro
B54: D3 · Clase de tamaño | C54: =IF(INDIRECT("'"&$C$3&"'!G21")="","",INDIRECT("'"&$C$3&"'!G21")) -> Clase L
B55: D3 · Tamaño aproximado | C55: =IF(INDIRECT("'"&$C$3&"'!G22")="","",INDIRECT("'"&$C$3&"'!G22")) -> ≈ 272 PF (aproximación)
B56: D3 · Tamaño medido | C56: =IF(INDIRECT("'"&$C$3&"'!G23")="","",INDIRECT("'"&$C$3&"'!G23")) -> Sin medición detallada
B57: D4 · Puntaje de complejidad | C57: =IF(INDIRECT("'"&$C$3&"'!G24")="","",INDIRECT("'"&$C$3&"'!G24")) -> Puntaje 7 / 10
B58: D4 · Nivel de complejidad | C58: =IF(INDIRECT("'"&$C$3&"'!G25")="","",INDIRECT("'"&$C$3&"'!G25")) -> Complejidad Alta
B59: D5 · Nivel de integración | C59: =IF(INDIRECT("'"&$C$3&"'!G29")="","",INDIRECT("'"&$C$3&"'!G29")) -> I2 - Media
B60: D6 · Nivel de reutilización | C60: =IF(INDIRECT("'"&$C$3&"'!G32")="","",INDIRECT("'"&$C$3&"'!G32")) -> R3 - Baja
B61: D7 · Entorno tecnológico | C61: =IF(INDIRECT("'"&$C$3&"'!G33")="","",INDIRECT("'"&$C$3&"'!G33")) -> T2 - Parcialmente conocida
B62: D8 · Madurez del alcance (catálogo) | C62: =IF(INDIRECT("'"&$C$3&"'!G34")="","",INDIRECT("'"&$C$3&"'!G34")) -> M3 - Definido
B63: D9 · Contexto de ejecución | C63: =IF(INDIRECT("'"&$C$3&"'!G35")="","",INDIRECT("'"&$C$3&"'!G35")) -> Parcialmente conocido
B64: D10 · Sector | C64: =IF(INDIRECT("'"&$C$3&"'!G36")="","",INDIRECT("'"&$C$3&"'!G36")) -> Gobierno
B65: D11 · Evidencia histórica | C65: =IF(INDIRECT("'"&$C$3&"'!G37")="","",INDIRECT("'"&$C$3&"'!G37")) -> E2 - Baja
B68: Top 10 brechas priorizadas (puntaje bajo × peso del criterio × peso de la dimensión)
B69: Criterio | C69: ID | D69: Puntaje | E69: Subdimensión | O69: Hallazgo / comentario sugerido | P69: Prioridad
B70: =IF(C70="","",INDEX(Rubricas!$F$4:$F$112,MATCH(C70,Rubricas!$A$4:$A$112,0))) -> Movimientos de datos por proceso | C70: =IF(P70=0,"",INDEX(INDIRECT("'"&$C$3&"'!$A$80:$A$240"),MATCH(P70,INDIRECT("'"&$C$3&"'!$K$80:$K$240"),0))) -> D3.07 | D70: =IF(C70="","",IF(INDEX(INDIRECT("'"&$C$3&"'!$F$80:$F$240"),MATCH(P70,INDIRECT("'"&$C$3&"'!$K$80:$K$240"),0))="","Sin evaluar",INDEX(INDIRECT("'"&$C$3&"'!$F$80:$F$240"),MATCH(P70,INDIRECT("'"&$C$3&"'!$K$80:$K$240"),0)))) -> 1 | E70: =IF(C70="","",INDEX(INDIRECT("'"&$C$3&"'!$C$80:$C$240"),MATCH(P70,INDIRECT("'"&$C$3&"'!$K$80:$K$240"),0))) -> Movimientos de datos | O70: =IF(C70="","",INDEX(INDIRECT("'"&$C$3&"'!$J$80:$J$240"),MATCH(P70,INDIRECT("'"&$C$3&"'!$K$80:$K$240"),0))) -> No se identifican los movimientos de datos (Entradas, Salidas, Lecturas, Escrituras); el tamaño queda como aproximación. Medir al menos una muestra representativa. | P70: =LARGE(INDIRECT("'"&$C$3&"'!$K$80:$K$240"),1) -> 108.00113
B71: =IF(C71="","",INDEX(Rubricas!$F$4:$F$112,MATCH(C71,Rubricas!$A$4:$A$112,0))) -> Requisitos de seguridad clasificados | C71: =IF(P71=0,"",INDEX(INDIRECT("'"&$C$3&"'!$A$80:$A$240"),MATCH(P71,INDIRECT("'"&$C$3&"'!$K$80:$K$240"),0))) -> D4.06 | D71: =IF(C71="","",IF(INDEX(INDIRECT("'"&$C$3&"'!$F$80:$F$240"),MATCH(P71,INDIRECT("'"&$C$3&"'!$K$80:$K$240"),0))="","Sin evaluar",INDEX(INDIRECT("'"&$C$3&"'!$F$80:$F$240"),MATCH(P71,INDIRECT("'"&$C$3&"'!$K$80:$K$240"),0)))) -> 1 | E71: =IF(C71="","",INDEX(INDIRECT("'"&$C$3&"'!$C$80:$C$240"),MATCH(P71,INDIRECT("'"&$C$3&"'!$K$80:$K$240"),0))) -> Seguridad | O71: =IF(C71="","",INDEX(INDIRECT("'"&$C$3&"'!$J$80:$J$240"),MATCH(P71,INDIRECT("'"&$C$3&"'!$K$80:$K$240"),0))) -> Los requisitos de seguridad no están especificados ni clasificados. | P71: =LARGE(INDIRECT("'"&$C$3&"'!$K$80:$K$240"),2) -> 90.00127
B72: =IF(C72="","",INDEX(Rubricas!$F$4:$F$112,MATCH(C72,Rubricas!$A$4:$A$112,0))) -> Caracterización de reglas | C72: =IF(P72=0,"",INDEX(INDIRECT("'"&$C$3&"'!$A$80:$A$240"),MATCH(P72,INDIRECT("'"&$C$3&"'!$K$80:$K$240"),0))) -> D4.02 | D72: =IF(C72="","",IF(INDEX(INDIRECT("'"&$C$3&"'!$F$80:$F$240"),MATCH(P72,INDIRECT("'"&$C$3&"'!$K$80:$K$240"),0))="","Sin evaluar",INDEX(INDIRECT("'"&$C$3&"'!$F$80:$F$240"),MATCH(P72,INDIRECT("'"&$C$3&"'!$K$80:$K$240"),0)))) -> 1 | E72: =IF(C72="","",INDEX(INDIRECT("'"&$C$3&"'!$C$80:$C$240"),MATCH(P72,INDIRECT("'"&$C$3&"'!$K$80:$K$240"),0))) -> Reglas de negocio | O72: =IF(C72="","",INDEX(INDIRECT("'"&$C$3&"'!$J$80:$J$240"),MATCH(P72,INDIRECT("'"&$C$3&"'!$K$80:$K$240"),0))) -> Las reglas no están caracterizadas (faltan excepciones o cálculos); la calificación de complejidad no es confiable. | P72: =LARGE(INDIRECT("'"&$C$3&"'!$K$80:$K$240"),3) -> 90.00123
B73: =IF(C73="","",INDEX(Rubricas!$F$4:$F$112,MATCH(C73,Rubricas!$A$4:$A$112,0))) -> Manejo de errores y recuperación | C73: =IF(P73=0,"",INDEX(INDIRECT("'"&$C$3&"'!$A$80:$A$240"),MATCH(P73,INDIRECT("'"&$C$3&"'!$K$80:$K$240"),0))) -> D5.07 | D73: =IF(C73="","",IF(INDEX(INDIRECT("'"&$C$3&"'!$F$80:$F$240"),MATCH(P73,INDIRECT("'"&$C$3&"'!$K$80:$K$240"),0))="","Sin evaluar",INDEX(INDIRECT("'"&$C$3&"'!$F$80:$F$240"),MATCH(P73,INDIRECT("'"&$C$3&"'!$K$80:$K$240"),0)))) -> 0 | E73: =IF(C73="","",INDEX(INDIRECT("'"&$C$3&"'!$C$80:$C$240"),MATCH(P73,INDIRECT("'"&$C$3&"'!$K$80:$K$240"),0))) -> Comportamiento y errores | O73: =IF(C73="","",INDEX(INDIRECT("'"&$C$3&"'!$J$80:$J$240"),MATCH(P73,INDIRECT("'"&$C$3&"'!$K$80:$K$240"),0))) -> No está definido el manejo de errores (reintentos, idempotencia, conciliación). | P73: =LARGE(INDIRECT("'"&$C$3&"'!$K$80:$K$240"),4) -> 84.00141
B74: =IF(C74="","",INDEX(Rubricas!$F$4:$F$112,MATCH(C74,Rubricas!$A$4:$A$112,0))) -> Intercambios mapeados a datos y procesos | C74: =IF(P74=0,"",INDEX(INDIRECT("'"&$C$3&"'!$A$80:$A$240"),MATCH(P74,INDIRECT("'"&$C$3&"'!$K$80:$K$240"),0))) -> D5.02 | D74: =IF(C74="","",IF(INDEX(INDIRECT("'"&$C$3&"'!$F$80:$F$240"),MATCH(P74,INDIRECT("'"&$C$3&"'!$K$80:$K$240"),0))="","Sin evaluar",INDEX(INDIRECT("'"&$C$3&"'!$F$80:$F$240"),MATCH(P74,INDIRECT("'"&$C$3&"'!$K$80:$K$240"),0)))) -> 1 | E74: =IF(C74="","",INDEX(INDIRECT("'"&$C$3&"'!$C$80:$C$240"),MATCH(P74,INDIRECT("'"&$C$3&"'!$K$80:$K$240"),0))) -> Inventario de interfaces | O74: =IF(C74="","",INDEX(INDIRECT("'"&$C$3&"'!$J$80:$J$240"),MATCH(P74,INDIRECT("'"&$C$3&"'!$K$80:$K$240"),0))) -> Las interfaces no están asociadas a procesos ni a los datos intercambiados; el tamaño de la integración queda sin sustento. | P74: =LARGE(INDIRECT("'"&$C$3&"'!$K$80:$K$240"),5) -> 84.00136
B75: =IF(C75="","",INDEX(Rubricas!$F$4:$F$112,MATCH(C75,Rubricas!$A$4:$A$112,0))) -> Trazabilidad requisito – medición | C75: =IF(P75=0,"",INDEX(INDIRECT("'"&$C$3&"'!$A$80:$A$240"),MATCH(P75,INDIRECT("'"&$C$3&"'!$K$80:$K$240"),0))) -> D3.13 | D75: =IF(C75="","",IF(INDEX(INDIRECT("'"&$C$3&"'!$F$80:$F$240"),MATCH(P75,INDIRECT("'"&$C$3&"'!$K$80:$K$240"),0))="","Sin evaluar",INDEX(INDIRECT("'"&$C$3&"'!$F$80:$F$240"),MATCH(P75,INDIRECT("'"&$C$3&"'!$K$80:$K$240"),0)))) -> 1 | E75: =IF(C75="","",INDEX(INDIRECT("'"&$C$3&"'!$C$80:$C$240"),MATCH(P75,INDIRECT("'"&$C$3&"'!$K$80:$K$240"),0))) -> Consolidación del tamaño | O75: =IF(C75="","",INDEX(INDIRECT("'"&$C$3&"'!$J$80:$J$240"),MATCH(P75,INDIRECT("'"&$C$3&"'!$K$80:$K$240"),0))) -> No hay trazabilidad requisito–proceso–tamaño; dificulta auditar la medición y gestionar cambios de alcance. | P75: =LARGE(INDIRECT("'"&$C$3&"'!$K$80:$K$240"),6) -> 72.00119
B76: =IF(C76="","",INDEX(Rubricas!$F$4:$F$112,MATCH(C76,Rubricas!$A$4:$A$112,0))) -> RNF que se convierten en funcionalidad | C76: =IF(P76=0,"",INDEX(INDIRECT("'"&$C$3&"'!$A$80:$A$240"),MATCH(P76,INDIRECT("'"&$C$3&"'!$K$80:$K$240"),0))) -> D3.10 | D76: =IF(C76="","",IF(INDEX(INDIRECT("'"&$C$3&"'!$F$80:$F$240"),MATCH(P76,INDIRECT("'"&$C$3&"'!$K$80:$K$240"),0))="","Sin evaluar",INDEX(INDIRECT("'"&$C$3&"'!$F$80:$F$240"),MATCH(P76,INDIRECT("'"&$C$3&"'!$K$80:$K$240"),0)))) -> 1 | E76: =IF(C76="","",INDEX(INDIRECT("'"&$C$3&"'!$C$80:$C$240"),MATCH(P76,INDIRECT("'"&$C$3&"'!$K$80:$K$240"),0))) -> Requisitos no funcionales | O76: =IF(C76="","",INDEX(INDIRECT("'"&$C$3&"'!$J$80:$J$240"),MATCH(P76,INDIRECT("'"&$C$3&"'!$K$80:$K$240"),0))) -> Requisitos como auditoría, notificaciones o gestión de permisos no se trasladaron al tamaño funcional; suelen omitirse y generar subestimación. | P76: =LARGE(INDIRECT("'"&$C$3&"'!$K$80:$K$240"),7) -> 72.00116
B77: =IF(C77="","",INDEX(Rubricas!$F$4:$F$112,MATCH(C77,Rubricas!$A$4:$A$112,0))) -> Tamaño del cambio en evolutivos | C77: =IF(P77=0,"",INDEX(INDIRECT("'"&$C$3&"'!$A$80:$A$240"),MATCH(P77,INDIRECT("'"&$C$3&"'!$K$80:$K$240"),0))) -> D3.09 | D77: =IF(C77="","",IF(INDEX(INDIRECT("'"&$C$3&"'!$F$80:$F$240"),MATCH(P77,INDIRECT("'"&$C$3&"'!$K$80:$K$240"),0))="","Sin evaluar",INDEX(INDIRECT("'"&$C$3&"'!$F$80:$F$240"),MATCH(P77,INDIRECT("'"&$C$3&"'!$K$80:$K$240"),0)))) -> 1 | E77: =IF(C77="","",INDEX(INDIRECT("'"&$C$3&"'!$C$80:$C$240"),MATCH(P77,INDIRECT("'"&$C$3&"'!$K$80:$K$240"),0))) -> Consolidación del tamaño | O77: =IF(C77="","",INDEX(INDIRECT("'"&$C$3&"'!$J$80:$J$240"),MATCH(P77,INDIRECT("'"&$C$3&"'!$K$80:$K$240"),0))) -> El tamaño del cambio no está desagregado en agregados, modificados y eliminados. | P77: =LARGE(INDIRECT("'"&$C$3&"'!$K$80:$K$240"),8) -> 72.00115
B78: =IF(C78="","",INDEX(Rubricas!$F$4:$F$112,MATCH(C78,Rubricas!$A$4:$A$112,0))) -> Eventos desencadenantes | C78: =IF(P78=0,"",INDEX(INDIRECT("'"&$C$3&"'!$A$80:$A$240"),MATCH(P78,INDIRECT("'"&$C$3&"'!$K$80:$K$240"),0))) -> D3.04 | D78: =IF(C78="","",IF(INDEX(INDIRECT("'"&$C$3&"'!$F$80:$F$240"),MATCH(P78,INDIRECT("'"&$C$3&"'!$K$80:$K$240"),0))="","Sin evaluar",INDEX(INDIRECT("'"&$C$3&"'!$F$80:$F$240"),MATCH(P78,INDIRECT("'"&$C$3&"'!$K$80:$K$240"),0)))) -> 1 | E78: =IF(C78="","",INDEX(INDIRECT("'"&$C$3&"'!$C$80:$C$240"),MATCH(P78,INDIRECT("'"&$C$3&"'!$K$80:$K$240"),0))) -> Procesos funcionales | O78: =IF(C78="","",INDEX(INDIRECT("'"&$C$3&"'!$J$80:$J$240"),MATCH(P78,INDIRECT("'"&$C$3&"'!$K$80:$K$240"),0))) -> No se identifican los eventos desencadenantes; es la base para delimitar correctamente cada proceso funcional. | P78: =LARGE(INDIRECT("'"&$C$3&"'!$K$80:$K$240"),9) -> 72.0011
B79: =IF(C79="","",INDEX(Rubricas!$F$4:$F$112,MATCH(C79,Rubricas!$A$4:$A$112,0))) -> Nivel de granularidad homogéneo | C79: =IF(P79=0,"",INDEX(INDIRECT("'"&$C$3&"'!$A$80:$A$240"),MATCH(P79,INDIRECT("'"&$C$3&"'!$K$80:$K$240"),0))) -> D3.02 | D79: =IF(C79="","",IF(INDEX(INDIRECT("'"&$C$3&"'!$F$80:$F$240"),MATCH(P79,INDIRECT("'"&$C$3&"'!$K$80:$K$240"),0))="","Sin evaluar",INDEX(INDIRECT("'"&$C$3&"'!$F$80:$F$240"),MATCH(P79,INDIRECT("'"&$C$3&"'!$K$80:$K$240"),0)))) -> 1 | E79: =IF(C79="","",INDEX(INDIRECT("'"&$C$3&"'!$C$80:$C$240"),MATCH(P79,INDIRECT("'"&$C$3&"'!$K$80:$K$240"),0))) -> Estrategia de medición | O79: =IF(C79="","",INDEX(INDIRECT("'"&$C$3&"'!$J$80:$J$240"),MATCH(P79,INDIRECT("'"&$C$3&"'!$K$80:$K$240"),0))) -> La granularidad de los requisitos es heterogénea; medir con requisitos a distinto nivel genera errores de tamaño. Normalizar al nivel de proceso funcional. | P79: =LARGE(INDIRECT("'"&$C$3&"'!$K$80:$K$240"),10) -> 72.00108
B82: Validaciones de consistencia
B83: Regla | C83: Estado | D83: Acción sugerida
B84: =INDIRECT("'"&$C$3&"'!A61")&" · "&INDIRECT("'"&$C$3&"'!B61") -> V1 · Los porcentajes de composición del tipo de desarrollo suman 100%. | C84: =INDIRECT("'"&$C$3&"'!E61") -> OK | D84: =INDIRECT("'"&$C$3&"'!G61")
B85: =INDIRECT("'"&$C$3&"'!A62")&" · "&INDIRECT("'"&$C$3&"'!B62") -> V2 · Si hay componente evolutivo, de modernización o mantenimiento, existe línea base del activo (D1.03). | C85: =INDIRECT("'"&$C$3&"'!E62") -> ⚠ Revisar | D85: =INDIRECT("'"&$C$3&"'!G62") -> Se modifica un activo existente sin línea base funcional: D1.03 no debería ser N/A ni ≤ 1.
B86: =INDIRECT("'"&$C$3&"'!A63")&" · "&INDIRECT("'"&$C$3&"'!B63") -> V3 · El arquetipo Modernización no convive con un tipo de desarrollo predominantemente nuevo. | C86: =INDIRECT("'"&$C$3&"'!E63") -> OK | D86: =INDIRECT("'"&$C$3&"'!G63")
B87: =INDIRECT("'"&$C$3&"'!A64")&" · "&INDIRECT("'"&$C$3&"'!B64") -> V4 · El arquetipo principal Integración tiene al menos 3 interfaces. | C87: =INDIRECT("'"&$C$3&"'!E64") -> OK | D87: =INDIRECT("'"&$C$3&"'!G64")
B88: =INDIRECT("'"&$C$3&"'!A65")&" · "&INDIRECT("'"&$C$3&"'!B65") -> V5 · Si se declara Integración (principal o secundario) se registra el N° de interfaces. | C88: =INDIRECT("'"&$C$3&"'!E65") -> OK | D88: =INDIRECT("'"&$C$3&"'!G65")
B89: =INDIRECT("'"&$C$3&"'!A66")&" · "&INDIRECT("'"&$C$3&"'!B66") -> V6 · Las interfaces declaradas cuentan con inventario (D5.01 ≥ 2). | C89: =INDIRECT("'"&$C$3&"'!E66") -> OK | D89: =INDIRECT("'"&$C$3&"'!G66")
B90: =INDIRECT("'"&$C$3&"'!A67")&" · "&INDIRECT("'"&$C$3&"'!B67") -> V7 · El N° de procesos funcionales está respaldado por inventario (D3.05 ≥ 2). | C90: =INDIRECT("'"&$C$3&"'!E67") -> OK | D90: =INDIRECT("'"&$C$3&"'!G67")
B91: =INDIRECT("'"&$C$3&"'!A68")&" · "&INDIRECT("'"&$C$3&"'!B68") -> V8 · Si el inventario de procesos está calificado (D3.05 ≥ 2) se registra la cantidad. | C91: =INDIRECT("'"&$C$3&"'!E68") -> OK | D91: =INDIRECT("'"&$C$3&"'!G68")
B92: =INDIRECT("'"&$C$3&"'!A69")&" · "&INDIRECT("'"&$C$3&"'!B69") -> V9 · Seguridad calificada como crítica (factor = 2) tiene requisitos especificados (D4.06 ≥ 2). | C92: =INDIRECT("'"&$C$3&"'!E69") -> ⚠ Revisar | D92: =INDIRECT("'"&$C$3&"'!G69") -> Se califica la seguridad como crítica sin requisitos especificados; la complejidad no está sustentada.
B93: =INDIRECT("'"&$C$3&"'!A70")&" · "&INDIRECT("'"&$C$3&"'!B70") -> V10 · Reglas calificadas como complejas (factor = 2) están caracterizadas (D4.02 ≥ 2). | C93: =INDIRECT("'"&$C$3&"'!E70") -> OK | D93: =INDIRECT("'"&$C$3&"'!G70")
B94: =INDIRECT("'"&$C$3&"'!A71")&" · "&INDIRECT("'"&$C$3&"'!B71") -> V11 · Reutilización alta (> 70%) respaldada por la evaluación de los activos (D6.03 ≥ 2). | C94: =INDIRECT("'"&$C$3&"'!E71") -> OK | D94: =INDIRECT("'"&$C$3&"'!G71")
B95: =INDIRECT("'"&$C$3&"'!A72")&" · "&INDIRECT("'"&$C$3&"'!B72") -> V12 · Tecnología T1 respaldada por la evaluación de familiaridad (D7.04 ≥ 2). | C95: =INDIRECT("'"&$C$3&"'!E72") -> OK | D95: =INDIRECT("'"&$C$3&"'!G72")
B96: =INDIRECT("'"&$C$3&"'!A73")&" · "&INDIRECT("'"&$C$3&"'!B73") -> V13 · Con 4 o más comparables, sus datos están completos (D11.03 ≥ 2). | C96: =INDIRECT("'"&$C$3&"'!E73") -> OK | D96: =INDIRECT("'"&$C$3&"'!G73")
B97: =INDIRECT("'"&$C$3&"'!A74")&" · "&INDIRECT("'"&$C$3&"'!B74") -> V14 · Un alcance M3/M4 es coherente con una madurez de tamaño ≥ umbral núcleo. | C97: =INDIRECT("'"&$C$3&"'!E74") -> OK | D97: =INDIRECT("'"&$C$3&"'!G74")
B98: =INDIRECT("'"&$C$3&"'!A75")&" · "&INDIRECT("'"&$C$3&"'!B75") -> V15 · Integración I3 con ambientes de prueba de terceros confirmados (D5.09 ≥ 2). | C98: =INDIRECT("'"&$C$3&"'!E75") -> OK | D98: =INDIRECT("'"&$C$3&"'!G75")
B99: Inconsistencias detectadas | C99: =COUNTIF(C84:C98,"⚠ Revisar") -> 2
B102: Interpretación de niveles de madurez
B103: Nivel | C103: Desde | D103: Interpretación | O103: Técnica sugerida
B104: =Parametros!B30 -> N1 - Incipiente | C104: =Parametros!A30 -> 0 | D104: =Parametros!D30 -> Información insuficiente; la estimación sería una conjetura. | O104: =Parametros!E30 -> Juicio experto / Delphi con rango amplio; priorizar levantamiento de información antes de comprometer una cifra.
B105: =Parametros!B31 -> N2 - Preliminar | C105: =Parametros!A31 -> 0.2 | D105: =Parametros!D31 -> Visión general con vacíos críticos. | O105: =Parametros!E31 -> Juicio experto + analogía; estimación de orden de magnitud.
B106: =Parametros!B32 -> N3 - Intermedio | C106: =Parametros!A32 -> 0.4 | D106: =Parametros!D32 -> Alcance principal conocido; faltan detalles relevantes. | O106: =Parametros!E32 -> Analogía con histórico + descomposición (WBS); estimación preliminar.
B107: =Parametros!B33 -> N4 - Definido | C107: =Parametros!A33 -> 0.6 | D107: =Parametros!D33 -> Alcance definido y mayormente cuantificado. | O107: =Parametros!E33 -> Tamaño funcional + productividad histórica, contrastado con descomposición.
B108: =Parametros!B34 -> N5 - Validado | C108: =Parametros!A34 -> 0.8 | D108: =Parametros!D34 -> Información completa, cuantificada y validada. | O108: =Parametros!E34 -> Tamaño funcional + modelo paramétrico calibrado; desempeño empírico si el equipo es conocido.

Sheet Glosario
A1: Glosario de conceptos de medición funcional usados en el modelo
A2: Los criterios de Tamaño, Integración y Tipo de desarrollo aplican los conceptos del método de medición funcional COSMIC (ISO/IEC 19761). Se incluyen aquí para que el evaluador califique con el mismo significado.
A3: Concepto | B3: Definición | C3: Uso en la evaluación
A4: Propósito de la medición | B4: Razón por la cual se mide (p. ej. cotizar un proyecto). Determina qué se incluye y con qué detalle. | C4: D3.01
A5: Alcance de la medición | B5: Conjunto de requisitos funcionales y piezas de software incluidos en una medición. | C5: D3.01, D1.07
A6: Capa | B6: División funcional de la arquitectura (p. ej. aplicación, servicios, infraestructura) cuyos componentes se miden por separado. | C6: D1.08
A7: Componente par | B7: Pieza de software en la misma capa que intercambia datos con la que se mide; se trata como usuario funcional. | C7: D1.08, D5.02
A8: Frontera | B8: Límite conceptual entre el software medido y sus usuarios funcionales. | C8: D1.07, D5.02
A9: Usuario funcional | B9: Emisor o receptor de datos del software: persona (por rol), otro sistema, dispositivo o componente. | C9: D2.08, D3.03
A10: Evento desencadenante | B10: Suceso fuera del software (acción de usuario, mensaje, tiempo) que inicia un proceso funcional. | C10: D3.04
A11: Proceso funcional | B11: Conjunto único de movimientos de datos que responde a un evento desencadenante y termina cuando completa su respuesta. Unidad para contar «funcionalidades». | C11: D1.04, D3.05, Parte A (D3)
A12: Objeto de interés | B12: Cosa del negocio sobre la que el software almacena o procesa información (contrato, proveedor…). | C12: D3.06
A13: Grupo de datos | B13: Conjunto de atributos que describen un mismo objeto de interés. | C13: D3.06, D5.02
A14: Movimiento de datos | B14: Movimiento de un grupo de datos. Hay cuatro tipos: Entrada, Salida, Lectura y Escritura. Cada uno vale 1 punto de función. | C14: D3.07, D3.12
... A23: Requisito no funcional que genera funcionalidad | B23: Requisito de calidad que al detallarse se implementa como procesos funcionales (bitácoras, notificaciones, permisos). | C23: D3.10
